Workbook

Sheet Summary
A1: CONSOLIDATED PORTFOLIO SUMMARY – ALL MANAGED ACCOUNTS
A2: Built 23.10.2026 from 6 statements. All market values at NSE/BSE close of 22.10.2026 (Prices sheet); statement-reported values kept alongside for reconciliation.
A5: Portfolio | B5: Broker | C5: Holdings as of | D5: Statement price basis | E5: # Holdings | F5: Invested (₹) | G5: Market Value (₹) | H5: Unrealised P&L (₹) | I5: P&L % | J5: Share of Combined MV | K5: Stmt Invested (₹) | L5: Stmt Market Value (₹) | M5: Repricing Impact (₹)
A6: Gautam | B6: HDFC Securities | C6: 23.10.2026 | D6: HDFC statement prices 23.10.2026 | E6: =COUNTIFS(Gautam!$D$7:$D$300,">0",Gautam!$B$7:$B$300,"<>Cash*") -> 31 | F6: =Gautam!E6 -> 5501448 | G6: =Gautam!H6 -> 5225157.3 | H6: =G6-F6 -> -276290.7 | I6: =IF(F6>0,H6/F6,"") -> -0.050221451 | J6: =IF($G$12=0,"",G6/$G$12) -> 0.13848002 | K6: 5501448.5 | L6: 5224564 | M6: =G6-L6 -> 593.3
A7: Manish Shilpa | B7: Axis Direct + HDFC Securities | C7: 23.10.2026 (live, ~11:23 IST) | D7: Live LTP 23.10.2026 ~11:23 IST (equity); MF NAV per Axis statement 23.10.2026 (three demats + MF merged) | E7: =COUNTIFS('Manish Shilpa'!$D$7:$D$300,">0",'Manish Shilpa'!$B$7:$B$300,"<>Cash*") -> 47 | F7: ='Manish Shilpa'!E6 -> 9857778 | G7: ='Manish Shilpa'!H6 -> 11825895 | H7: =G7-F7 -> 1968116.9 | I7: =IF(F7>0,H7/F7,"") -> 0.19965117 | J7: =IF($G$12=0,"",G7/$G$12) -> 0.31341643 | K7: 9857779 | L7: 11636410 | M7: =G7-L7 -> 189484.74
A8: Saloni Mehra | B8: Angel One | C8: 20.10.2026 + trades of 21–22.10.2026 | D8: 20.10.2026 statement prices (only for rows with no trades since) | E8: =COUNTIFS('Saloni Mehra'!$D$7:$D$300,">0",'Saloni Mehra'!$B$7:$B$300,"<>Cash*") -> 25 | F8: ='Saloni Mehra'!E6 -> 11014028 | G8: ='Saloni Mehra'!H6 -> 11167526 | H8: =G8-F8 -> 153497.65 | I8: =IF(F8>0,H8/F8,"") -> 0.013936559 | J8: =IF($G$12=0,"",G8/$G$12) -> 0.29596797 | K8: 11014028 | L8: 3325492 | M8: =G8-L8 -> 7842033.7
A9: Vidushi Malhotra | B9: Zerodha | C9: 04.10.2026 (+ trades of 05.10.2026) | D9: LTP 05.10.2026 | E9: =COUNTIFS('Vidushi Malhotra'!$D$7:$D$300,">0",'Vidushi Malhotra'!$B$7:$B$300,"<>Cash*") -> 12 | F9: ='Vidushi Malhotra'!E6 -> 201361 | G9: ='Vidushi Malhotra'!H6 -> 226299.36 | H9: =G9-F9 -> 24938.363 | I9: =IF(F9>0,H9/F9,"") -> 0.12384902 | J9: =IF($G$12=0,"",G9/$G$12) -> 0.0059975114 | K9: 201361 | L9: 230319 | M9: =G9-L9 -> -4019.6371
A10: Dr Umesh Choudhry | B10: ICICI Direct | C10: 04.10.2026 + trades of 09.10.2026 | D10: NSE live 09.10.2026 ~09:45 IST | E10: =COUNTIFS('Dr Umesh Choudhry'!$D$7:$D$300,">0",'Dr Umesh Choudhry'!$B$7:$B$300,"<>Cash*") -> 20 | F10: ='Dr Umesh Choudhry'!E6 -> 5222229 | G10: ='Dr Umesh Choudhry'!H6 -> 5421322.8 | H10: =G10-F10 -> 199093.76 | I10: =IF(F10>0,H10/F10,"") -> 0.038124288 | J10: =IF($G$12=0,"",G10/$G$12) -> 0.14367891 | K10: 5222229 | L10: 5467267.2 | M10: =G10-L10 -> -45944.47
A11: DA | B11: HDFC Securities + Kotak Securities | C11: Post 12.09.2026 trades (file dated 04.10.2026) | D11: As on statement (date not printed) | E11: =COUNTIFS(DA!$D$7:$D$300,">0",DA!$B$7:$B$300,"<>Cash*") -> 53 | F11: =DA!E6 -> 4364996 | G11: =DA!H6 -> 3866010.7 | H11: =G11-F11 -> -498985.26 | I11: =IF(F11>0,H11/F11,"") -> -0.11431517 | J11: =IF($G$12=0,"",G11/$G$12) -> 0.10245916 | K11: 4364995 | L11: 4141021 | M11: =G11-L11 -> -275010.26
A12: COMBINED (ALL 6) | B12: HDFC Securities + Axis Direct + HDFC Securities + Angel One + Zerodha + ICICI Direct + HDFC Securities + Kotak Securities | E12: ='Side by Side'!E6 -> 88 | F12: =SUM(F6:F11) -> 36161840 | G12: =SUM(G6:G11) -> 37732211 | H12: =SUM(H6:H11) -> 1570370.7 | I12: =IF(F12>0,H12/F12,"") -> 0.043426184 | J12: =SUM(J6:J11) -> 1 | K12: =SUM(K6:K11) -> 36161841 | L12: =SUM(L6:L11) -> 30025073 | M12: =SUM(M6:M11) -> 7707137.3
L13: Statement totals as printed on each statement (inputs).
A15: TOP 10 COMBINED EXPOSURES – weight in each portfolio
A16: Rank | B16: Security | C16: Combined MV (₹) | D16: Combined Weight | E16: Gautam | F16: Manish Shilpa | G16: Saloni Mehra | H16: Vidushi Malhotra | I16: Dr Umesh Choudhry | J16: DA | K16: Held in (# a/cs)
A17: 1 | B17: =INDEX('Side by Side'!$B$7:$B$95,MATCH(C17,'Side by Side'!$I$7:$I$95,0)) -> Bajaj Finance Ltd | C17: =LARGE('Side by Side'!$I$7:$I$95,A17) -> 13148890 | D17: =INDEX('Side by Side'!$L$7:$L$95,MATCH(C17,'Side by Side'!$I$7:$I$95,0)) -> 0.34847918 | E17: =INDEX('Side by Side'!$S$7:$S$95,MATCH(C17,'Side by Side'!$I$7:$I$95,0)) -> 0.34275181 | F17: =INDEX('Side by Side'!$Z$7:$Z$95,MATCH(C17,'Side by Side'!$I$7:$I$95,0)) -> 0.31029191 | G17: =INDEX('Side by Side'!$AG$7:$AG$95,MATCH(C17,'Side by Side'!$I$7:$I$95,0)) -> 0.39759186 | H17: =INDEX('Side by Side'!$AN$7:$AN$95,MATCH(C17,'Side by Side'!$I$7:$I$95,0)) -> 0.50373142 | I17: =INDEX('Side by Side'!$AU$7:$AU$95,MATCH(C17,'Side by Side'!$I$7:$I$95,0)) -> 0.41914959 | J17: =INDEX('Side by Side'!$BB$7:$BB$95,MATCH(C17,'Side by Side'!$I$7:$I$95,0)) -> 0.22297442 | K17: =INDEX('Side by Side'!$E$7:$E$95,MATCH(C17,'Side by Side'!$I$7:$I$95,0)) -> 6
A18: 2 | B18: =INDEX('Side by Side'!$B$7:$B$95,MATCH(C18,'Side by Side'!$I$7:$I$95,0)) -> Titan Company Ltd | C18: =LARGE('Side by Side'!$I$7:$I$95,A18) -> 3027600 | D18: =INDEX('Side by Side'!$L$7:$L$95,MATCH(C18,'Side by Side'!$I$7:$I$95,0)) -> 0.080239136 | E18: =INDEX('Side by Side'!$S$7:$S$95,MATCH(C18,'Side by Side'!$I$7:$I$95,0)) -> 0.039128009 | F18: =INDEX('Side by Side'!$Z$7:$Z$95,MATCH(C18,'Side by Side'!$I$7:$I$95,0)) -> 0.060693081 | G18: =INDEX('Side by Side'!$AG$7:$AG$95,MATCH(C18,'Side by Side'!$I$7:$I$95,0)) -> 0.095043435 | H18: =INDEX('Side by Side'!$AN$7:$AN$95,MATCH(C18,'Side by Side'!$I$7:$I$95,0)) -> 0.17300093 | I18: =INDEX('Side by Side'!$AU$7:$AU$95,MATCH(C18,'Side by Side'!$I$7:$I$95,0)) -> 0.1380106 | J18: =INDEX('Side by Side'!$BB$7:$BB$95,MATCH(C18,'Side by Side'!$I$7:$I$95,0)) -> 0.066386262 | K18: =INDEX('Side by Side'!$E$7:$E$95,MATCH(C18,'Side by Side'!$I$7:$I$95,0)) -> 6
A19: 3 | B19: =INDEX('Side by Side'!$B$7:$B$95,MATCH(C19,'Side by Side'!$I$7:$I$95,0)) -> Nippon India ETF Nifty 50 BeES | C19: =LARGE('Side by Side'!$I$7:$I$95,A19) -> 2864949.7 | D19: =INDEX('Side by Side'!$L$7:$L$95,MATCH(C19,'Side by Side'!$I$7:$I$95,0)) -> 0.075928488 | E19: =INDEX('Side by Side'!$S$7:$S$95,MATCH(C19,'Side by Side'!$I$7:$I$95,0)) -> 0 | F19: =INDEX('Side by Side'!$Z$7:$Z$95,MATCH(C19,'Side by Side'!$I$7:$I$95,0)) -> 0.242239 | G19: =INDEX('Side by Side'!$AG$7:$AG$95,MATCH(C19,'Side by Side'!$I$7:$I$95,0)) -> 0 | H19: =INDEX('Side by Side'!$AN$7:$AN$95,MATCH(C19,'Side by Side'!$I$7:$I$95,0)) -> 0.0011343069 | I19: =INDEX('Side by Side'!$AU$7:$AU$95,MATCH(C19,'Side by Side'!$I$7:$I$95,0)) -> 0 | J19: =INDEX('Side by Side'!$BB$7:$BB$95,MATCH(C19,'Side by Side'!$I$7:$I$95,0)) -> 0 | K19: =INDEX('Side by Side'!$E$7:$E$95,MATCH(C19,'Side by Side'!$I$7:$I$95,0)) -> 2
A20: 4 | B20: =INDEX('Side by Side'!$B$7:$B$95,MATCH(C20,'Side by Side'!$I$7:$I$95,0)) -> HDFC Bank Ltd | C20: =LARGE('Side by Side'!$I$7:$I$95,A20) -> 2484699 | D20: =INDEX('Side by Side'!$L$7:$L$95,MATCH(C20,'Side by Side'!$I$7:$I$95,0)) -> 0.065850873 | E20: =INDEX('Side by Side'!$S$7:$S$95,MATCH(C20,'Side by Side'!$I$7:$I$95,0)) -> 0.059374356 | F20: =INDEX('Side by Side'!$Z$7:$Z$95,MATCH(C20,'Side by Side'!$I$7:$I$95,0)) -> 0.059451962 | G20: =INDEX('Side by Side'!$AG$7:$AG$95,MATCH(C20,'Side by Side'!$I$7:$I$95,0)) -> 0.067680207 | H20: =INDEX('Side by Side'!$AN$7:$AN$95,MATCH(C20,'Side by Side'!$I$7:$I$95,0)) -> 0.064406058 | I20: =INDEX('Side by Side'!$AU$7:$AU$95,MATCH(C20,'Side by Side'!$I$7:$I$95,0)) -> 0.086158982 | J20: =INDEX('Side by Side'!$BB$7:$BB$95,MATCH(C20,'Side by Side'!$I$7:$I$95,0)) -> 0.06050031 | K20: =INDEX('Side by Side'!$E$7:$E$95,MATCH(C20,'Side by Side'!$I$7:$I$95,0)) -> 6
A21: 5 | B21: =INDEX('Side by Side'!$B$7:$B$95,MATCH(C21,'Side by Side'!$I$7:$I$95,0)) -> Poonawalla Fincorp Ltd | C21: =LARGE('Side by Side'!$I$7:$I$95,A21) -> 2331770.4 | D21: =INDEX('Side by Side'!$L$7:$L$95,MATCH(C21,'Side by Side'!$I$7:$I$95,0)) -> 0.061797874 | E21: =INDEX('Side by Side'!$S$7:$S$95,MATCH(C21,'Side by Side'!$I$7:$I$95,0)) -> 0.093687782 | F21: =INDEX('Side by Side'!$Z$7:$Z$95,MATCH(C21,'Side by Side'!$I$7:$I$95,0)) -> 0.050975872 | G21: =INDEX('Side by Side'!$AG$7:$AG$95,MATCH(C21,'Side by Side'!$I$7:$I$95,0)) -> 0.049063165 | H21: =INDEX('Side by Side'!$AN$7:$AN$95,MATCH(C21,'Side by Side'!$I$7:$I$95,0)) -> 0.072616643 | I21: =INDEX('Side by Side'!$AU$7:$AU$95,MATCH(C21,'Side by Side'!$I$7:$I$95,0)) -> 0.061341865 | J21: =INDEX('Side by Side'!$BB$7:$BB$95,MATCH(C21,'Side by Side'!$I$7:$I$95,0)) -> 0.088592718 | K21: =INDEX('Side by Side'!$E$7:$E$95,MATCH(C21,'Side by Side'!$I$7:$I$95,0)) -> 6
A22: 6 | B22: =INDEX('Side by Side'!$B$7:$B$95,MATCH(C22,'Side by Side'!$I$7:$I$95,0)) -> AFCOM Holdings Ltd | C22: =LARGE('Side by Side'!$I$7:$I$95,A22) -> 1645740 | D22: =INDEX('Side by Side'!$L$7:$L$95,MATCH(C22,'Side by Side'!$I$7:$I$95,0)) -> 0.043616315 | E22: =INDEX('Side by Side'!$S$7:$S$95,MATCH(C22,'Side by Side'!$I$7:$I$95,0)) -> 0.031496468 | F22: =INDEX('Side by Side'!$Z$7:$Z$95,MATCH(C22,'Side by Side'!$I$7:$I$95,0)) -> 0.041749229 | G22: =INDEX('Side by Side'!$AG$7:$AG$95,MATCH(C22,'Side by Side'!$I$7:$I$95,0)) -> 0.04421051 | H22: =INDEX('Side by Side'!$AN$7:$AN$95,MATCH(C22,'Side by Side'!$I$7:$I$95,0)) -> 0 | I22: =INDEX('Side by Side'!$AU$7:$AU$95,MATCH(C22,'Side by Side'!$I$7:$I$95,0)) -> 0.060713596 | J22: =INDEX('Side by Side'!$BB$7:$BB$95,MATCH(C22,'Side by Side'!$I$7:$I$95,0)) -> 0.042569463 | K22: =INDEX('Side by Side'!$E$7:$E$95,MATCH(C22,'Side by Side'!$I$7:$I$95,0)) -> 5
A23: 7 | B23: =INDEX('Side by Side'!$B$7:$B$95,MATCH(C23,'Side by Side'!$I$7:$I$95,0)) -> Tata Consultancy Services Ltd | C23: =LARGE('Side by Side'!$I$7:$I$95,A23) -> 1173229.2 | D23: =INDEX('Side by Side'!$L$7:$L$95,MATCH(C23,'Side by Side'!$I$7:$I$95,0)) -> 0.031093572 | E23: =INDEX('Side by Side'!$S$7:$S$95,MATCH(C23,'Side by Side'!$I$7:$I$95,0)) -> 0.044139303 | F23: =INDEX('Side by Side'!$Z$7:$Z$95,MATCH(C23,'Side by Side'!$I$7:$I$95,0)) -> 0.0061475348 | G23: =INDEX('Side by Side'!$AG$7:$AG$95,MATCH(C23,'Side by Side'!$I$7:$I$95,0)) -> 0.068466778 | H23: =INDEX('Side by Side'!$AN$7:$AN$95,MATCH(C23,'Side by Side'!$I$7:$I$95,0)) -> 0 | I23: =INDEX('Side by Side'!$AU$7:$AU$95,MATCH(C23,'Side by Side'!$I$7:$I$95,0)) -> 0.01341003 | J23: =INDEX('Side by Side'!$BB$7:$BB$95,MATCH(C23,'Side by Side'!$I$7:$I$95,0)) -> 0.0084298007 | K23: =INDEX('Side by Side'!$E$7:$E$95,MATCH(C23,'Side by Side'!$I$7:$I$95,0)) -> 5
A24: 8 | B24: =INDEX('Side by Side'!$B$7:$B$95,MATCH(C24,'Side by Side'!$I$7:$I$95,0)) -> LTM Ltd (formerly LTIMindtree) | C24: =LARGE('Side by Side'!$I$7:$I$95,A24) -> 1081322 | D24: =INDEX('Side by Side'!$L$7:$L$95,MATCH(C24,'Side by Side'!$I$7:$I$95,0)) -> 0.028657796 | E24: =INDEX('Side by Side'!$S$7:$S$95,MATCH(C24,'Side by Side'!$I$7:$I$95,0)) -> 0.049077948 | F24: =INDEX('Side by Side'!$Z$7:$Z$95,MATCH(C24,'Side by Side'!$I$7:$I$95,0)) -> 0.023853079 | G24: =INDEX('Side by Side'!$AG$7:$AG$95,MATCH(C24,'Side by Side'!$I$7:$I$95,0)) -> 0.031765497 | H24: =INDEX('Side by Side'!$AN$7:$AN$95,MATCH(C24,'Side by Side'!$I$7:$I$95,0)) -> 0.037772974 | I24: =INDEX('Side by Side'!$AU$7:$AU$95,MATCH(C24,'Side by Side'!$I$7:$I$95,0)) -> 0.029169634 | J24: =INDEX('Side by Side'!$BB$7:$BB$95,MATCH(C24,'Side by Side'!$I$7:$I$95,0)) -> 0.0055276618 | K24: =INDEX('Side by Side'!$E$7:$E$95,MATCH(C24,'Side by Side'!$I$7:$I$95,0)) -> 6
A25: 9 | B25: =INDEX('Side by Side'!$B$7:$B$95,MATCH(C25,'Side by Side'!$I$7:$I$95,0)) -> Bajaj Housing Finance Ltd | C25: =LARGE('Side by Side'!$I$7:$I$95,A25) -> 1075378.5 | D25: =INDEX('Side by Side'!$L$7:$L$95,MATCH(C25,'Side by Side'!$I$7:$I$95,0)) -> 0.028500277 | E25: =INDEX('Side by Side'!$S$7:$S$95,MATCH(C25,'Side by Side'!$I$7:$I$95,0)) -> 0.024809205 | F25: =INDEX('Side by Side'!$Z$7:$Z$95,MATCH(C25,'Side by Side'!$I$7:$I$95,0)) -> 0.025773715 | G25: =INDEX('Side by Side'!$AG$7:$AG$95,MATCH(C25,'Side by Side'!$I$7:$I$95,0)) -> 0.028004162 | H25: =INDEX('Side by Side'!$AN$7:$AN$95,MATCH(C25,'Side by Side'!$I$7:$I$95,0)) -> 0.043320582 | I25: =INDEX('Side by Side'!$AU$7:$AU$95,MATCH(C25,'Side by Side'!$I$7:$I$95,0)) -> 0.032848433 | J25: =INDEX('Side by Side'!$BB$7:$BB$95,MATCH(C25,'Side by Side'!$I$7:$I$95,0)) -> 0.03629753 | K25: =INDEX('Side by Side'!$E$7:$E$95,MATCH(C25,'Side by Side'!$I$7:$I$95,0)) -> 6
A26: 10 | B26: =INDEX('Side by Side'!$B$7:$B$95,MATCH(C26,'Side by Side'!$I$7:$I$95,0)) -> Connplex Cinemas Ltd | C26: =LARGE('Side by Side'!$I$7:$I$95,A26) -> 937000 | D26: =INDEX('Side by Side'!$L$7:$L$95,MATCH(C26,'Side by Side'!$I$7:$I$95,0)) -> 0.024832894 | E26: =INDEX('Side by Side'!$S$7:$S$95,MATCH(C26,'Side by Side'!$I$7:$I$95,0)) -> 0.035864949 | F26: =INDEX('Side by Side'!$Z$7:$Z$95,MATCH(C26,'Side by Side'!$I$7:$I$95,0)) -> 0.015846581 | G26: =INDEX('Side by Side'!$AG$7:$AG$95,MATCH(C26,'Side by Side'!$I$7:$I$95,0)) -> 0.016780799 | H26: =INDEX('Side by Side'!$AN$7:$AN$95,MATCH(C26,'Side by Side'!$I$7:$I$95,0)) -> 0 | I26: =INDEX('Side by Side'!$AU$7:$AU$95,MATCH(C26,'Side by Side'!$I$7:$I$95,0)) -> 0.03456721 | J26: =INDEX('Side by Side'!$BB$7:$BB$95,MATCH(C26,'Side by Side'!$I$7:$I$95,0)) -> 0.04847374 | K26: =INDEX('Side by Side'!$E$7:$E$95,MATCH(C26,'Side by Side'!$I$7:$I$95,0)) -> 5
A29: NOTES & FLAGS
A30: • Pricing: every holding is valued at the NSE/BSE close of 22.10.2026 (Screener.in daily price series), one price per security across all accounts. 'Repricing Impact' = workbook value minus each statement's own market value.
A31: ="• Securities on an exchange close: "&COUNTIF(Prices!$K$6:$K$300,"Close*")&" | on a statement price: "&COUNTIF(Prices!$K$6:$K$300,"No exchange*")&" | held in all 6 accounts: "&COUNTIF('Side by Side'!$E$7:$E$95,6) -> • Securities on an exchange close: 79 | on a statement price: 9 | held in all 6 accounts: 9
A32: • No exchange close for the 4 ETFs (Nifty 50 BeES, Gold BeES, Liquid BeES, HDFC Gold ETF), the Utkarsh SFB rights entitlement, NEPC Agro and PSL Ltd – these stay at statement price (Liquid BeES holds near ₹1,000).
A33: • Names aligned across statements: LTM Ltd = LTIMindtree (DA); Connplex Cinemas = Connplex Smart Theatres (DA); AFCOM = Afcom Holdings.
A34: • Trades blended into holdings and listed on each tab: Vidushi 05.10.2026 (3 buys, ₹9,889); Dr Umesh 09.10.2026 (13 buys, ₹5.01 L, incl. new Eicher Motors and Rategain).
A35: • Dr Umesh holds ₹36,000 uninvested cash at ICICI Direct – row 'Cash – ICICI Direct' at ₹1 per unit, counted in totals but not as a holding.
A36: • Statement invested/market totals reconcile to transcribed rows within ₹2 (rupee rounding on the statements).
A37: • Gautam: NEPC Agro Foods (144 sh) and PSL Ltd (1,000 sh) still have no cost or price on the statement – carried at nil.
A38: • Manish Shilpa: Axis and HDFC CSVs carry short names (e.g. 'Nip. India Nifty', 'C D S L', 'Waaree Renewab.'); aligned to canonical names. 'Nippon ETF Infra' is carried as Nippon India ETF Infra BeES. ETFs have no exchange close and stay on the statement price.
A39: • Gautam refreshed from HDFC statement of 23.10.2026 (31 lines; invested ₹55,01,448 reconciles to ₹55,01,448.50). Changes vs the 05.10 statement are derived: 16 buys and 1 exit (International Gemmological Institute, 80 sh, valued at the 05.10 statement price).
A40: • Vidushi, Dr Umesh and DA have no new statements since 09.10 and are only repriced to the 22.10.2026 close.
A41: • Manish Shilpa is new (23.10.2026): Axis Direct (Shilpa), Axis Direct (Manish), HDFC Securities (Manish) and Manish's Axis mutual fund (UTI Nifty 50 Index Fund – 2 folios, ₹1,99,990 invested) merged into one account. A stock held in more than one demat is one row; the row note lists the split. Statement totals: invested ₹98,57,779, market value ₹1,16,36,410 (equity at live ~11:23 IST prices, MF at statement NAV).
A42: • Saloni Mehra is new (Angel One): 26-holding statement of 20.10.2026 (invested ₹1,10,23,244; market value ₹1,13,95,012) rolled forward with the 15 trades of 21–22.10.2026. Buys add cost including all charges; Kotak Mahindra Bank (1,580 sh, realised ≈ ₹62,288) and LIC Housing Finance (700 sh, realised ≈ ₹-29,271) were sold out; Trent is a new position. Statement invested is now the row sum (no printed total after trades). Rows touched by trades have no statement value, so the account's 'Stmt Market Value' covers untraded rows only.

Sheet Side by Side
A1: SIDE-BY-SIDE HOLDINGS – COMBINED AND BY PORTFOLIO
A2: All values at the common Ref Price (Prices sheet). Sorted by combined market value at build; '-' = not held. Amber price = only a stale statement price available.
F4: COMBINED (ALL 6) | M4: GAUTAM – HDFC Securities | T4: MANISH SHILPA – Axis Direct + HDFC Securities | AA4: SALONI MEHRA – Angel One | AH4: VIDUSHI MALHOTRA – Zerodha | AO4: DR UMESH CHOUDHRY – ICICI Direct | AV4: DA – HDFC Securities + Kotak Securities
A5: # | B5: Security | C5: Ref Price (₹) | D5: Price Basis | E5: Held in (# a/cs) | F5: Qty | G5: Wtd Avg Cost (₹) | H5: Invested (₹) | I5: Mkt Value (₹) | J5: P&L (₹) | K5: P&L % | L5: Weight % | M5: Qty | N5: Wtd Avg Cost (₹) | O5: Invested (₹) | P5: Mkt Value (₹) | Q5: P&L (₹) | R5: P&L % | S5: Weight % | T5: Qty | U5: Wtd Avg Cost (₹) | V5: Invested (₹) | W5: Mkt Value (₹) | X5: P&L (₹) | Y5: P&L % | Z5: Weight % | AA5: Qty | AB5: Wtd Avg Cost (₹) | AC5: Invested (₹) | AD5: Mkt Value (₹) | AE5: P&L (₹) | AF5: P&L % | AG5: Weight % | AH5: Qty | AI5: Wtd Avg Cost (₹) | AJ5: Invested (₹) | AK5: Mkt Value (₹) | AL5: P&L (₹) | AM5: P&L % | AN5: Weight % | AO5: Qty | AP5: Wtd Avg Cost (₹) | AQ5: Invested (₹) | AR5: Mkt Value (₹) | AS5: P&L (₹) | AT5: P&L % | AU5: Weight % | AV5: Qty | AW5: Wtd Avg Cost (₹) | AX5: Invested (₹) | AY5: Mkt Value (₹) | AZ5: P&L (₹) | BA5: P&L % | BB5: Weight %
B6: TOTAL | E6: =COUNTIFS(E7:E95,">0",B7:B95,"<>Cash*") -> 88 | F6: =COUNTIFS(F7:F95,">0",$B7:$B95,"<>Cash*") -> 88 | H6: =SUM(H7:H95) -> 36161840 | I6: =SUM(I7:I95) -> 37732211 | J6: =I6-H6 -> 1570370.7 | K6: =IF(H6>0,J6/H6,"") -> 0.043426184 | L6: =SUM(L7:L95) -> 1 | M6: =COUNTIFS(M7:M95,">0",$B7:$B95,"<>Cash*") -> 31 | O6: =SUM(O7:O95) -> 5501448 | P6: =SUM(P7:P95) -> 5225157.3 | Q6: =P6-O6 -> -276290.7 | R6: =IF(O6>0,Q6/O6,"") -> -0.050221451 | S6: =SUM(S7:S95) -> 1 | T6: =COUNTIFS(T7:T95,">0",$B7:$B95,"<>Cash*") -> 47 | V6: =SUM(V7:V95) -> 9857778 | W6: =SUM(W7:W95) -> 11825895 | X6: =W6-V6 -> 1968116.9 | Y6: =IF(V6>0,X6/V6,"") -> 0.19965117 | Z6: =SUM(Z7:Z95) -> 1 | AA6: =COUNTIFS(AA7:AA95,">0",$B7:$B95,"<>Cash*") -> 25 | AC6: =SUM(AC7:AC95) -> 11014028 | AD6: =SUM(AD7:AD95) -> 11167526 | AE6: =AD6-AC6 -> 153497.65 | AF6: =IF(AC6>0,AE6/AC6,"") -> 0.013936559 | AG6: =SUM(AG7:AG95) -> 1 | AH6: =COUNTIFS(AH7:AH95,">0",$B7:$B95,"<>Cash*") -> 12 | AJ6: =SUM(AJ7:AJ95) -> 201361 | AK6: =SUM(AK7:AK95) -> 226299.36 | AL6: =AK6-AJ6 -> 24938.363 | AM6: =IF(AJ6>0,AL6/AJ6,"") -> 0.12384902 | AN6: =SUM(AN7:AN95) -> 1 | AO6: =COUNTIFS(AO7:AO95,">0",$B7:$B95,"<>Cash*") -> 20 | AQ6: =SUM(AQ7:AQ95) -> 5222229 | AR6: =SUM(AR7:AR95) -> 5421322.8 | AS6: =AR6-AQ6 -> 199093.76 | AT6: =IF(AQ6>0,AS6/AQ6,"") -> 0.038124288 | AU6: =SUM(AU7:AU95) -> 1 | AV6: =COUNTIFS(AV7:AV95,">0",$B7:$B95,"<>Cash*") -> 53 | AX6: =SUM(AX7:AX95) -> 4364996 | AY6: =SUM(AY7:AY95) -> 3866010.7 | AZ6: =AY6-AX6 -> -498985.26 | BA6: =IF(AX6>0,AZ6/AX6,"") -> -0.11431517 | BB6: =SUM(BB7:BB95) -> 1
A7: 1 | B7: Bajaj Finance Ltd | C7: =IFERROR(INDEX(Prices!$C$6:$C$300,MATCH($B7,Prices!$A$6:$A$300,0)),"") -> 942.1 | D7: =IFERROR(INDEX(Prices!$D$6:$D$300,MATCH($B7,Prices!$A$6:$A$300,0)),"") -> Close 22.10.2026 (Screener.in) | E7: =(M7>0)+(T7>0)+(AA7>0)+(AH7>0)+(AO7>0)+(AV7>0) -> 6 | F7: =M7+T7+AA7+AH7+AO7+AV7 -> 13957 | G7: =IF(AND(F7>0,H7>0),H7/F7,"") -> 877.77295 | H7: =O7+V7+AC7+AJ7+AQ7+AX7 -> 12251077 | I7: =P7+W7+AD7+AK7+AR7+AY7 -> 13148890 | J7: =I7-H7 -> 897812.7 | K7: =IF(H7>0,J7/H7,"") -> 0.07328439 | L7: =IF(I$6=0,"",I7/I$6) -> 0.34847918 | M7: =SUMIFS(Gautam!$D$7:$D$300,Gautam!$B$7:$B$300,$B7) -> 1901 | N7: =IF(AND(M7>0,O7>0),O7/M7,"") -> 1005.9332 | O7: =SUMIFS(Gautam!$E$7:$E$300,Gautam!$B$7:$B$300,$B7) -> 1912279 | P7: =SUMIFS(Gautam!$H$7:$H$300,Gautam!$B$7:$B$300,$B7) -> 1790932.1 | Q7: =P7-O7 -> -121346.9 | R7: =IF(O7>0,Q7/O7,"") -> -0.063456692 | S7: =IF(P$6=0,"",P7/P$6) -> 0.34275181 | T7: =SUMIFS('Manish Shilpa'!$D$7:$D$300,'Manish Shilpa'!$B$7:$B$300,$B7) -> 3895 | U7: =IF(AND(T7>0,V7>0),V7/T7,"") -> 747.72503 | V7: =SUMIFS('Manish Shilpa'!$E$7:$E$300,'Manish Shilpa'!$B$7:$B$300,$B7) -> 2912389 | W7: =SUMIFS('Manish Shilpa'!$H$7:$H$300,'Manish Shilpa'!$B$7:$B$300,$B7) -> 3669479.5 | X7: =W7-V7 -> 757090.5 | Y7: =IF(V7>0,X7/V7,"") -> 0.25995514 | Z7: =IF(W$6=0,"",W7/W$6) -> 0.31029191 | AA7: =SUMIFS('Saloni Mehra'!$D$7:$D$300,'Saloni Mehra'!$B$7:$B$300,$B7) -> 4713 | AB7: =IF(AND(AA7>0,AC7>0),AC7/AA7,"") -> 941.87948 | AC7: =SUMIFS('Saloni Mehra'!$E$7:$E$300,'Saloni Mehra'!$B$7:$B$300,$B7) -> 4439078 | AD7: =SUMIFS('Saloni Mehra'!$H$7:$H$300,'Saloni Mehra'!$B$7:$B$300,$B7) -> 4440117.3 | AE7: =AD7-AC7 -> 1039.3 | AF7: =IF(AC7>0,AE7/AC7,"") -> 0.00023412519 | AG7: =IF(AD$6=0,"",AD7/AD$6) -> 0.39759186 | AH7: =SUMIFS('Vidushi Malhotra'!$D$7:$D$300,'Vidushi Malhotra'!$B$7:$B$300,$B7) -> 121 | AI7: =IF(AND(AH7>0,AJ7>0),AJ7/AH7,"") -> 768 | AJ7: =SUMIFS('Vidushi Malhotra'!$E$7:$E$300,'Vidushi Malhotra'!$B$7:$B$300,$B7) -> 92928 | AK7: =SUMIFS('Vidushi Malhotra'!$H$7:$H$300,'Vidushi Malhotra'!$B$7:$B$300,$B7) -> 113994.1 | AL7: =AK7-AJ7 -> 21066.1 | AM7: =IF(AJ7>0,AL7/AJ7,"") -> 0.22669271 | AN7: =IF(AK$6=0,"",AK7/AK$6) -> 0.50373142 | AO7: =SUMIFS('Dr Umesh Choudhry'!$D$7:$D$300,'Dr Umesh Choudhry'!$B$7:$B$300,$B7) -> 2412 | AP7: =IF(AND(AO7>0,AQ7>0),AQ7/AO7,"") -> 800.28441 | AQ7: =SUMIFS('Dr Umesh Choudhry'!$E$7:$E$300,'Dr Umesh Choudhry'!$B$7:$B$300,$B7) -> 1930286 | AR7: =SUMIFS('Dr Umesh Choudhry'!$H$7:$H$300,'Dr Umesh Choudhry'!$B$7:$B$300,$B7) -> 2272345.2 | AS7: =AR7-AQ7 -> 342059.2 | AT7: =IF(AQ7>0,AS7/AQ7,"") -> 0.17720649 | AU7: =IF(AR$6=0,"",AR7/AR$6) -> 0.41914959 | AV7: =SUMIFS(DA!$D$7:$D$300,DA!$B$7:$B$300,$B7) -> 915 | AW7: =IF(AND(AV7>0,AX7>0),AX7/AV7,"") -> 1053.6798 | AX7: =SUMIFS(DA!$E$7:$E$300,DA!$B$7:$B$300,$B7) -> 964117 | AY7: =SUMIFS(DA!$H$7:$H$300,DA!$B$7:$B$300,$B7) -> 862021.5 | AZ7: =AY7-AX7 -> -102095.5 | BA7: =IF(AX7>0,AZ7/AX7,"") -> -0.10589534 | BB7: =IF(AY$6=0,"",AY7/AY$6) -> 0.22297442
A8: 2 | B8: Titan Company Ltd | C8: =IFERROR(INDEX(Prices!$C$6:$C$300,MATCH($B8,Prices!$A$6:$A$300,0)),"") -> 4350 | D8: =IFERROR(INDEX(Prices!$D$6:$D$300,MATCH($B8,Prices!$A$6:$A$300,0)),"") -> Close 22.10.2026 (Screener.in) | E8: =(M8>0)+(T8>0)+(AA8>0)+(AH8>0)+(AO8>0)+(AV8>0) -> 6 | F8: =M8+T8+AA8+AH8+AO8+AV8 -> 696 | G8: =IF(AND(F8>0,H8>0),H8/F8,"") -> 3938.1006 | H8: =O8+V8+AC8+AJ8+AQ8+AX8 -> 2740918 | I8: =P8+W8+AD8+AK8+AR8+AY8 -> 3027600 | J8: =I8-H8 -> 286682 | K8: =IF(H8>0,J8/H8,"") -> 0.10459342 | L8: =IF(I$6=0,"",I8/I$6) -> 0.080239136 | M8: =SUMIFS(Gautam!$D$7:$D$300,Gautam!$B$7:$B$300,$B8) -> 47 | N8: =IF(AND(M8>0,O8>0),O8/M8,"") -> 4763.7872 | O8: =SUMIFS(Gautam!$E$7:$E$300,Gautam!$B$7:$B$300,$B8) -> 223898 | P8: =SUMIFS(Gautam!$H$7:$H$300,Gautam!$B$7:$B$300,$B8) -> 204450 | Q8: =P8-O8 -> -19448 | R8: =IF(O8>0,Q8/O8,"") -> -0.086860981 | S8: =IF(P$6=0,"",P8/P$6) -> 0.039128009 | T8: =SUMIFS('Manish Shilpa'!$D$7:$D$300,'Manish Shilpa'!$B$7:$B$300,$B8) -> 165 | U8: =IF(AND(T8>0,V8>0),V8/T8,"") -> 3421.3939 | V8: =SUMIFS('Manish Shilpa'!$E$7:$E$300,'Manish Shilpa'!$B$7:$B$300,$B8) -> 564530 | W8: =SUMIFS('Manish Shilpa'!$H$7:$H$300,'Manish Shilpa'!$B$7:$B$300,$B8) -> 717750 | X8: =W8-V8 -> 153220 | Y8: =IF(V8>0,X8/V8,"") -> 0.27141162 | Z8: =IF(W$6=0,"",W8/W$6) -> 0.060693081 | AA8: =SUMIFS('Saloni Mehra'!$D$7:$D$300,'Saloni Mehra'!$B$7:$B$300,$B8) -> 244 | AB8: =IF(AND(AA8>0,AC8>0),AC8/AA8,"") -> 4288.8074 | AC8: =SUMIFS('Saloni Mehra'!$E$7:$E$300,'Saloni Mehra'!$B$7:$B$300,$B8) -> 1046469 | AD8: =SUMIFS('Saloni Mehra'!$H$7:$H$300,'Saloni Mehra'!$B$7:$B$300,$B8) -> 1061400 | AE8: =AD8-AC8 -> 14931 | AF8: =IF(AC8>0,AE8/AC8,"") -> 0.014267981 | AG8: =IF(AD$6=0,"",AD8/AD$6) -> 0.095043435 | AH8: =SUMIFS('Vidushi Malhotra'!$D$7:$D$300,'Vidushi Malhotra'!$B$7:$B$300,$B8) -> 9 | AI8: =IF(AND(AH8>0,AJ8>0),AJ8/AH8,"") -> 3160.1111 | AJ8: =SUMIFS('Vidushi Malhotra'!$E$7:$E$300,'Vidushi Malhotra'!$B$7:$B$300,$B8) -> 28441 | AK8: =SUMIFS('Vidushi Malhotra'!$H$7:$H$300,'Vidushi Malhotra'!$B$7:$B$300,$B8) -> 39150 | AL8: =AK8-AJ8 -> 10709 | AM8: =IF(AJ8>0,AL8/AJ8,"") -> 0.37653388 | AN8: =IF(AK$6=0,"",AK8/AK$6) -> 0.17300093 | AO8: =SUMIFS('Dr Umesh Choudhry'!$D$7:$D$300,'Dr Umesh Choudhry'!$B$7:$B$300,$B8) -> 172 | AP8: =IF(AND(AO8>0,AQ8>0),AQ8/AO8,"") -> 3589.9244 | AQ8: =SUMIFS('Dr Umesh Choudhry'!$E$7:$E$300,'Dr Umesh Choudhry'!$B$7:$B$300,$B8) -> 617467 | AR8: =SUMIFS('Dr Umesh Choudhry'!$H$7:$H$300,'Dr Umesh Choudhry'!$B$7:$B$300,$B8) -> 748200 | AS8: =AR8-AQ8 -> 130733 | AT8: =IF(AQ8>0,AS8/AQ8,"") -> 0.21172468 | AU8: =IF(AR$6=0,"",AR8/AR$6) -> 0.1380106 | AV8: =SUMIFS(DA!$D$7:$D$300,DA!$B$7:$B$300,$B8) -> 59 | AW8: =IF(AND(AV8>0,AX8>0),AX8/AV8,"") -> 4408.6949 | AX8: =SUMIFS(DA!$E$7:$E$300,DA!$B$7:$B$300,$B8) -> 260113 | AY8: =SUMIFS(DA!$H$7:$H$300,DA!$B$7:$B$300,$B8) -> 256650 | AZ8: =AY8-AX8 -> -3463 | BA8: =IF(AX8>0,AZ8/AX8,"") -> -0.013313445 | BB8: =IF(AY$6=0,"",AY8/AY$6) -> 0.066386262
A9: 3 | B9: Nippon India ETF Nifty 50 BeES | C9: =IFERROR(INDEX(Prices!$C$6:$C$300,MATCH($B9,Prices!$A$6:$A$300,0)),"") -> 256.69292 | D9: =IFERROR(INDEX(Prices!$D$6:$D$300,MATCH($B9,Prices!$A$6:$A$300,0)),"") -> Manish Shilpa stmt – live 23.10 | E9: =(M9>0)+(T9>0)+(AA9>0)+(AH9>0)+(AO9>0)+(AV9>0) -> 2 | F9: =M9+T9+AA9+AH9+AO9+AV9 -> 11161 | G9: =IF(AND(F9>0,H9>0),H9/F9,"") -> 151.22579 | H9: =O9+V9+AC9+AJ9+AQ9+AX9 -> 1687831 | I9: =P9+W9+AD9+AK9+AR9+AY9 -> 2864949.7 | J9: =I9-H9 -> 1177118.7 | K9: =IF(H9>0,J9/H9,"") -> 0.69741502 | L9: =IF(I$6=0,"",I9/I$6) -> 0.075928488 | M9: =SUMIFS(Gautam!$D$7:$D$300,Gautam!$B$7:$B$300,$B9) -> 0 | N9: =IF(AND(M9>0,O9>0),O9/M9,"") | O9: =SUMIFS(Gautam!$E$7:$E$300,Gautam!$B$7:$B$300,$B9) -> 0 | P9: =SUMIFS(Gautam!$H$7:$H$300,Gautam!$B$7:$B$300,$B9) -> 0 | Q9: =P9-O9 -> 0 | R9: =IF(O9>0,Q9/O9,"") | S9: =IF(P$6=0,"",P9/P$6) -> 0 | T9: =SUMIFS('Manish Shilpa'!$D$7:$D$300,'Manish Shilpa'!$B$7:$B$300,$B9) -> 11160 | U9: =IF(AND(T9>0,V9>0),V9/T9,"") -> 151.21685 | V9: =SUMIFS('Manish Shilpa'!$E$7:$E$300,'Manish Shilpa'!$B$7:$B$300,$B9) -> 1687580 | W9: =SUMIFS('Manish Shilpa'!$H$7:$H$300,'Manish Shilpa'!$B$7:$B$300,$B9) -> 2864693 | X9: =W9-V9 -> 1177113 | Y9: =IF(V9>0,X9/V9,"") -> 0.69751538 | Z9: =IF(W$6=0,"",W9/W$6) -> 0.242239 | AA9: =SUMIFS('Saloni Mehra'!$D$7:$D$300,'Saloni Mehra'!$B$7:$B$300,$B9) -> 0 | AB9: =IF(AND(AA9>0,AC9>0),AC9/AA9,"") | AC9: =SUMIFS('Saloni Mehra'!$E$7:$E$300,'Saloni Mehra'!$B$7:$B$300,$B9) -> 0 | AD9: =SUMIFS('Saloni Mehra'!$H$7:$H$300,'Saloni Mehra'!$B$7:$B$300,$B9) -> 0 | AE9: =AD9-AC9 -> 0 | AF9: =IF(AC9>0,AE9/AC9,"") | AG9: =IF(AD$6=0,"",AD9/AD$6) -> 0 | AH9: =SUMIFS('Vidushi Malhotra'!$D$7:$D$300,'Vidushi Malhotra'!$B$7:$B$300,$B9) -> 1 | AI9: =IF(AND(AH9>0,AJ9>0),AJ9/AH9,"") -> 251 | AJ9: =SUMIFS('Vidushi Malhotra'!$E$7:$E$300,'Vidushi Malhotra'!$B$7:$B$300,$B9) -> 251 | AK9: =SUMIFS('Vidushi Malhotra'!$H$7:$H$300,'Vidushi Malhotra'!$B$7:$B$300,$B9) -> 256.69292 | AL9: =AK9-AJ9 -> 5.6929211 | AM9: =IF(AJ9>0,AL9/AJ9,"") -> 0.022680961 | AN9: =IF(AK$6=0,"",AK9/AK$6) -> 0.0011343069 | AO9: =SUMIFS('Dr Umesh Choudhry'!$D$7:$D$300,'Dr Umesh Choudhry'!$B$7:$B$300,$B9) -> 0 | AP9: =IF(AND(AO9>0,AQ9>0),AQ9/AO9,"") | AQ9: =SUMIFS('Dr Umesh Choudhry'!$E$7:$E$300,'Dr Umesh Choudhry'!$B$7:$B$300,$B9) -> 0 | AR9: =SUMIFS('Dr Umesh Choudhry'!$H$7:$H$300,'Dr Umesh Choudhry'!$B$7:$B$300,$B9) -> 0 | AS9: =AR9-AQ9 -> 0 | AT9: =IF(AQ9>0,AS9/AQ9,"") | AU9: =IF(AR$6=0,"",AR9/AR$6) -> 0 | AV9: =SUMIFS(DA!$D$7:$D$300,DA!$B$7:$B$300,$B9) -> 0 | AW9: =IF(AND(AV9>0,AX9>0),AX9/AV9,"") | AX9: =SUMIFS(DA!$E$7:$E$300,DA!$B$7:$B$300,$B9) -> 0 | AY9: =SUMIFS(DA!$H$7:$H$300,DA!$B$7:$B$300,$B9) -> 0 | AZ9: =AY9-AX9 -> 0 | BA9: =IF(AX9>0,AZ9/AX9,"") | BB9: =IF(AY$6=0,"",AY9/AY$6) -> 0
A10: 4 | B10: HDFC Bank Ltd | C10: =IFERROR(INDEX(Prices!$C$6:$C$300,MATCH($B10,Prices!$A$6:$A$300,0)),"") -> 694.05 | D10: =IFERROR(INDEX(Prices!$D$6:$D$300,MATCH($B10,Prices!$A$6:$A$300,0)),"") -> Close 22.10.2026 (Screener.in) | E10: =(M10>0)+(T10>0)+(AA10>0)+(AH10>0)+(AO10>0)+(AV10>0) -> 6 | F10: =M10+T10+AA10+AH10+AO10+AV10 -> 3580 | G10: =IF(AND(F10>0,H10>0),H10/F10,"") -> 793.61704 | H10: =O10+V10+AC10+AJ10+AQ10+AX10 -> 2841149 | I10: =P10+W10+AD10+AK10+AR10+AY10 -> 2484699 | J10: =I10-H10 -> -356450 | K10: =IF(H10>0,J10/H10,"") -> -0.12545981 | L10: =IF(I$6=0,"",I10/I$6) -> 0.065850873 | M10: =SUMIFS(Gautam!$D$7:$D$300,Gautam!$B$7:$B$300,$B10) -> 447 | N10: =IF(AND(M10>0,O10>0),O10/M10,"") -> 716.1566 | O10: =SUMIFS(Gautam!$E$7:$E$300,Gautam!$B$7:$B$300,$B10) -> 320122 | P10: =SUMIFS(Gautam!$H$7:$H$300,Gautam!$B$7:$B$300,$B10) -> 310240.35 | Q10: =P10-O10 -> -9881.65 | R10: =IF(O10>0,Q10/O10,"") -> -0.030868388 | S10: =IF(P$6=0,"",P10/P$6) -> 0.059374356 | T10: =SUMIFS('Manish Shilpa'!$D$7:$D$300,'Manish Shilpa'!$B$7:$B$300,$B10) -> 1013 | U10: =IF(AND(T10>0,V10>0),V10/T10,"") -> 802.2537 | V10: =SUMIFS('Manish Shilpa'!$E$7:$E$300,'Manish Shilpa'!$B$7:$B$300,$B10) -> 812683 | W10: =SUMIFS('Manish Shilpa'!$H$7:$H$300,'Manish Shilpa'!$B$7:$B$300,$B10) -> 703072.65 | X10: =W10-V10 -> -109610.35 | Y10: =IF(V10>0,X10/V10,"") -> -0.13487467 | Z10: =IF(W$6=0,"",W10/W$6) -> 0.059451962 | AA10: =SUMIFS('Saloni Mehra'!$D$7:$D$300,'Saloni Mehra'!$B$7:$B$300,$B10) -> 1089 | AB10: =IF(AND(AA10>0,AC10>0),AC10/AA10,"") -> 772.60882 | AC10: =SUMIFS('Saloni Mehra'!$E$7:$E$300,'Saloni Mehra'!$B$7:$B$300,$B10) -> 841371 | AD10: =SUMIFS('Saloni Mehra'!$H$7:$H$300,'Saloni Mehra'!$B$7:$B$300,$B10) -> 755820.45 | AE10: =AD10-AC10 -> -85550.55 | AF10: =IF(AC10>0,AE10/AC10,"") -> -0.10167994 | AG10: =IF(AD$6=0,"",AD10/AD$6) -> 0.067680207 | AH10: =SUMIFS('Vidushi Malhotra'!$D$7:$D$300,'Vidushi Malhotra'!$B$7:$B$300,$B10) -> 21 | AI10: =IF(AND(AH10>0,AJ10>0),AJ10/AH10,"") -> 790.38095 | AJ10: =SUMIFS('Vidushi Malhotra'!$E$7:$E$300,'Vidushi Malhotra'!$B$7:$B$300,$B10) -> 16598 | AK10: =SUMIFS('Vidushi Malhotra'!$H$7:$H$300,'Vidushi Malhotra'!$B$7:$B$300,$B10) -> 14575.05 | AL10: =AK10-AJ10 -> -2022.95 | AM10: =IF(AJ10>0,AL10/AJ10,"") -> -0.12187914 | AN10: =IF(AK$6=0,"",AK10/AK$6) -> 0.064406058 | AO10: =SUMIFS('Dr Umesh Choudhry'!$D$7:$D$300,'Dr Umesh Choudhry'!$B$7:$B$300,$B10) -> 673 | AP10: =IF(AND(AO10>0,AQ10>0),AQ10/AO10,"") -> 890.65973 | AQ10: =SUMIFS('Dr Umesh Choudhry'!$E$7:$E$300,'Dr Umesh Choudhry'!$B$7:$B$300,$B10) -> 599414 | AR10: =SUMIFS('Dr Umesh Choudhry'!$H$7:$H$300,'Dr Umesh Choudhry'!$B$7:$B$300,$B10) -> 467095.65 | AS10: =AR10-AQ10 -> -132318.35 | AT10: =IF(AQ10>0,AS10/AQ10,"") -> -0.22074618 | AU10: =IF(AR$6=0,"",AR10/AR$6) -> 0.086158982 | AV10: =SUMIFS(DA!$D$7:$D$300,DA!$B$7:$B$300,$B10) -> 337 | AW10: =IF(AND(AV10>0,AX10>0),AX10/AV10,"") -> 744.69139 | AX10: =SUMIFS(DA!$E$7:$E$300,DA!$B$7:$B$300,$B10) -> 250961 | AY10: =SUMIFS(DA!$H$7:$H$300,DA!$B$7:$B$300,$B10) -> 233894.85 | AZ10: =AY10-AX10 -> -17066.15 | BA10: =IF(AX10>0,AZ10/AX10,"") -> -0.068003196 | BB10: =IF(AY$6=0,"",AY10/AY$6) -> 0.06050031
A11: 5 | B11: Poonawalla Fincorp Ltd | C11: =IFERROR(INDEX(Prices!$C$6:$C$300,MATCH($B11,Prices!$A$6:$A$300,0)),"") -> 432.45 | D11: =IFERROR(INDEX(Prices!$D$6:$D$300,MATCH($B11,Prices!$A$6:$A$300,0)),"") -> Close 22.10.2026 (Screener.in) | E11: =(M11>0)+(T11>0)+(AA11>0)+(AH11>0)+(AO11>0)+(AV11>0) -> 6 | F11: =M11+T11+AA11+AH11+AO11+AV11 -> 5392 | G11: =IF(AND(F11>0,H11>0),H11/F11,"") -> 453.12277 | H11: =O11+V11+AC11+AJ11+AQ11+AX11 -> 2443238 | I11: =P11+W11+AD11+AK11+AR11+AY11 -> 2331770.4 | J11: =I11-H11 -> -111467.6 | K11: =IF(H11>0,J11/H11,"") -> -0.045622899 | L11: =IF(I$6=0,"",I11/I$6) -> 0.061797874 | M11: =SUMIFS(Gautam!$D$7:$D$300,Gautam!$B$7:$B$300,$B11) -> 1132 | N11: =IF(AND(M11>0,O11>0),O11/M11,"") -> 465.69965 | O11: =SUMIFS(Gautam!$E$7:$E$300,Gautam!$B$7:$B$300,$B11) -> 527172 | P11: =SUMIFS(Gautam!$H$7:$H$300,Gautam!$B$7:$B$300,$B11) -> 489533.4 | Q11: =P11-O11 -> -37638.6 | R11: =IF(O11>0,Q11/O11,"") -> -0.071397191 | S11: =IF(P$6=0,"",P11/P$6) -> 0.093687782 | T11: =SUMIFS('Manish Shilpa'!$D$7:$D$300,'Manish Shilpa'!$B$7:$B$300,$B11) -> 1394 | U11: =IF(AND(T11>0,V11>0),V11/T11,"") -> 446.566 | V11: =SUMIFS('Manish Shilpa'!$E$7:$E$300,'Manish Shilpa'!$B$7:$B$300,$B11) -> 622513 | W11: =SUMIFS('Manish Shilpa'!$H$7:$H$300,'Manish Shilpa'!$B$7:$B$300,$B11) -> 602835.3 | X11: =W11-V11 -> -19677.7 | Y11: =IF(V11>0,X11/V11,"") -> -0.031610103 | Z11: =IF(W$6=0,"",W11/W$6) -> 0.050975872 | AA11: =SUMIFS('Saloni Mehra'!$D$7:$D$300,'Saloni Mehra'!$B$7:$B$300,$B11) -> 1267 | AB11: =IF(AND(AA11>0,AC11>0),AC11/AA11,"") -> 436.33623 | AC11: =SUMIFS('Saloni Mehra'!$E$7:$E$300,'Saloni Mehra'!$B$7:$B$300,$B11) -> 552838 | AD11: =SUMIFS('Saloni Mehra'!$H$7:$H$300,'Saloni Mehra'!$B$7:$B$300,$B11) -> 547914.15 | AE11: =AD11-AC11 -> -4923.85 | AF11: =IF(AC11>0,AE11/AC11,"") -> -0.008906497 | AG11: =IF(AD$6=0,"",AD11/AD$6) -> 0.049063165 | AH11: =SUMIFS('Vidushi Malhotra'!$D$7:$D$300,'Vidushi Malhotra'!$B$7:$B$300,$B11) -> 38 | AI11: =IF(AND(AH11>0,AJ11>0),AJ11/AH11,"") -> 452.42105 | AJ11: =SUMIFS('Vidushi Malhotra'!$E$7:$E$300,'Vidushi Malhotra'!$B$7:$B$300,$B11) -> 17192 | AK11: =SUMIFS('Vidushi Malhotra'!$H$7:$H$300,'Vidushi Malhotra'!$B$7:$B$300,$B11) -> 16433.1 | AL11: =AK11-AJ11 -> -758.9 | AM11: =IF(AJ11>0,AL11/AJ11,"") -> -0.044142624 | AN11: =IF(AK$6=0,"",AK11/AK$6) -> 0.072616643 | AO11: =SUMIFS('Dr Umesh Choudhry'!$D$7:$D$300,'Dr Umesh Choudhry'!$B$7:$B$300,$B11) -> 769 | AP11: =IF(AND(AO11>0,AQ11>0),AQ11/AO11,"") -> 451.22237 | AQ11: =SUMIFS('Dr Umesh Choudhry'!$E$7:$E$300,'Dr Umesh Choudhry'!$B$7:$B$300,$B11) -> 346990 | AR11: =SUMIFS('Dr Umesh Choudhry'!$H$7:$H$300,'Dr Umesh Choudhry'!$B$7:$B$300,$B11) -> 332554.05 | AS11: =AR11-AQ11 -> -14435.95 | AT11: =IF(AQ11>0,AS11/AQ11,"") -> -0.04160336 | AU11: =IF(AR$6=0,"",AR11/AR$6) -> 0.061341865 | AV11: =SUMIFS(DA!$D$7:$D$300,DA!$B$7:$B$300,$B11) -> 792 | AW11: =IF(AND(AV11>0,AX11>0),AX11/AV11,"") -> 475.42045 | AX11: =SUMIFS(DA!$E$7:$E$300,DA!$B$7:$B$300,$B11) -> 376533 | AY11: =SUMIFS(DA!$H$7:$H$300,DA!$B$7:$B$300,$B11) -> 342500.4 | AZ11: =AY11-AX11 -> -34032.6 | BA11: =IF(AX11>0,AZ11/AX11,"") -> -0.09038411 | BB11: =IF(AY$6=0,"",AY11/AY$6) -> 0.088592718
A12: 6 | B12: AFCOM Holdings Ltd | C12: =IFERROR(INDEX(Prices!$C$6:$C$300,MATCH($B12,Prices!$A$6:$A$300,0)),"") -> 1371.45 | D12: =IFERROR(INDEX(Prices!$D$6:$D$300,MATCH($B12,Prices!$A$6:$A$300,0)),"") -> Close 22.10.2026 (Screener.in) | E12: =(M12>0)+(T12>0)+(AA12>0)+(AH12>0)+(AO12>0)+(AV12>0) -> 5 | F12: =M12+T12+AA12+AH12+AO12+AV12 -> 1200 | G12: =IF(AND(F12>0,H12>0),H12/F12,"") -> 1079.9858 | H12: =O12+V12+AC12+AJ12+AQ12+AX12 -> 1295983 | I12: =P12+W12+AD12+AK12+AR12+AY12 -> 1645740 | J12: =I12-H12 -> 349757 | K12: =IF(H12>0,J12/H12,"") -> 0.26987777 | L12: =IF(I$6=0,"",I12/I$6) -> 0.043616315 | M12: =SUMIFS(Gautam!$D$7:$D$300,Gautam!$B$7:$B$300,$B12) -> 120 | N12: =IF(AND(M12>0,O12>0),O12/M12,"") -> 1666 | O12: =SUMIFS(Gautam!$E$7:$E$300,Gautam!$B$7:$B$300,$B12) -> 199920 | P12: =SUMIFS(Gautam!$H$7:$H$300,Gautam!$B$7:$B$300,$B12) -> 164574 | Q12: =P12-O12 -> -35346 | R12: =IF(O12>0,Q12/O12,"") -> -0.17680072 | S12: =IF(P$6=0,"",P12/P$6) -> 0.031496468 | T12: =SUMIFS('Manish Shilpa'!$D$7:$D$300,'Manish Shilpa'!$B$7:$B$300,$B12) -> 360 | U12: =IF(AND(T12>0,V12>0),V12/T12,"") -> 1007.5667 | V12: =SUMIFS('Manish Shilpa'!$E$7:$E$300,'Manish Shilpa'!$B$7:$B$300,$B12) -> 362724 | W12: =SUMIFS('Manish Shilpa'!$H$7:$H$300,'Manish Shilpa'!$B$7:$B$300,$B12) -> 493722 | X12: =W12-V12 -> 130998 | Y12: =IF(V12>0,X12/V12,"") -> 0.36115063 | Z12: =IF(W$6=0,"",W12/W$6) -> 0.041749229 | AA12: =SUMIFS('Saloni Mehra'!$D$7:$D$300,'Saloni Mehra'!$B$7:$B$300,$B12) -> 360 | AB12: =IF(AND(AA12>0,AC12>0),AC12/AA12,"") -> 1003 | AC12: =SUMIFS('Saloni Mehra'!$E$7:$E$300,'Saloni Mehra'!$B$7:$B$300,$B12) -> 361080 | AD12: =SUMIFS('Saloni Mehra'!$H$7:$H$300,'Saloni Mehra'!$B$7:$B$300,$B12) -> 493722 | AE12: =AD12-AC12 -> 132642 | AF12: =IF(AC12>0,AE12/AC12,"") -> 0.36734796 | AG12: =IF(AD$6=0,"",AD12/AD$6) -> 0.04421051 | AH12: =SUMIFS('Vidushi Malhotra'!$D$7:$D$300,'Vidushi Malhotra'!$B$7:$B$300,$B12) -> 0 | AI12: =IF(AND(AH12>0,AJ12>0),AJ12/AH12,"") | AJ12: =SUMIFS('Vidushi Malhotra'!$E$7:$E$300,'Vidushi Malhotra'!$B$7:$B$300,$B12) -> 0 | AK12: =SUMIFS('Vidushi Malhotra'!$H$7:$H$300,'Vidushi Malhotra'!$B$7:$B$300,$B12) -> 0 | AL12: =AK12-AJ12 -> 0 | AM12: =IF(AJ12>0,AL12/AJ12,"") | AN12: =IF(AK$6=0,"",AK12/AK$6) -> 0 | AO12: =SUMIFS('Dr Umesh Choudhry'!$D$7:$D$300,'Dr Umesh Choudhry'!$B$7:$B$300,$B12) -> 240 | AP12: =IF(AND(AO12>0,AQ12>0),AQ12/AO12,"") -> 846.57917 | AQ12: =SUMIFS('Dr Umesh Choudhry'!$E$7:$E$300,'Dr Umesh Choudhry'!$B$7:$B$300,$B12) -> 203179 | AR12: =SUMIFS('Dr Umesh Choudhry'!$H$7:$H$300,'Dr Umesh Choudhry'!$B$7:$B$300,$B12) -> 329148 | AS12: =AR12-AQ12 -> 125969 | AT12: =IF(AQ12>0,AS12/AQ12,"") -> 0.61999025 | AU12: =IF(AR$6=0,"",AR12/AR$6) -> 0.060713596 | AV12: =SUMIFS(DA!$D$7:$D$300,DA!$B$7:$B$300,$B12) -> 120 | AW12: =IF(AND(AV12>0,AX12>0),AX12/AV12,"") -> 1409 | AX12: =SUMIFS(DA!$E$7:$E$300,DA!$B$7:$B$300,$B12) -> 169080 | AY12: =SUMIFS(DA!$H$7:$H$300,DA!$B$7:$B$300,$B12) -> 164574 | AZ12: =AY12-AX12 -> -4506 | BA12: =IF(AX12>0,AZ12/AX12,"") -> -0.026650106 | BB12: =IF(AY$6=0,"",AY12/AY$6) -> 0.042569463
A13: 7 | B13: Tata Consultancy Services Ltd | C13: =IFERROR(INDEX(Prices!$C$6:$C$300,MATCH($B13,Prices!$A$6:$A$300,0)),"") -> 2506.9 | D13: =IFERROR(INDEX(Prices!$D$6:$D$300,MATCH($B13,Prices!$A$6:$A$300,0)),"") -> Close 22.10.2026 (Screener.in) | E13: =(M13>0)+(T13>0)+(AA13>0)+(AH13>0)+(AO13>0)+(AV13>0) -> 5 | F13: =M13+T13+AA13+AH13+AO13+AV13 -> 468 | G13: =IF(AND(F13>0,H13>0),H13/F13,"") -> 2396.8868 | H13: =O13+V13+AC13+AJ13+AQ13+AX13 -> 1121743 | I13: =P13+W13+AD13+AK13+AR13+AY13 -> 1173229.2 | J13: =I13-H13 -> 51486.2 | K13: =IF(H13>0,J13/H13,"") -> 0.045898392 | L13: =IF(I$6=0,"",I13/I$6) -> 0.031093572 | M13: =SUMIFS(Gautam!$D$7:$D$300,Gautam!$B$7:$B$300,$B13) -> 92 | N13: =IF(AND(M13>0,O13>0),O13/M13,"") -> 2289 | O13: =SUMIFS(Gautam!$E$7:$E$300,Gautam!$B$7:$B$300,$B13) -> 210588 | P13: =SUMIFS(Gautam!$H$7:$H$300,Gautam!$B$7:$B$300,$B13) -> 230634.8 | Q13: =P13-O13 -> 20046.8 | R13: =IF(O13>0,Q13/O13,"") -> 0.095194408 | S13: =IF(P$6=0,"",P13/P$6) -> 0.044139303 | T13: =SUMIFS('Manish Shilpa'!$D$7:$D$300,'Manish Shilpa'!$B$7:$B$300,$B13) -> 29 | U13: =IF(AND(T13>0,V13>0),V13/T13,"") -> 3379.1034 | V13: =SUMIFS('Manish Shilpa'!$E$7:$E$300,'Manish Shilpa'!$B$7:$B$300,$B13) -> 97994 | W13: =SUMIFS('Manish Shilpa'!$H$7:$H$300,'Manish Shilpa'!$B$7:$B$300,$B13) -> 72700.1 | X13: =W13-V13 -> -25293.9 | Y13: =IF(V13>0,X13/V13,"") -> -0.25811682 | Z13: =IF(W$6=0,"",W13/W$6) -> 0.0061475348 | AA13: =SUMIFS('Saloni Mehra'!$D$7:$D$300,'Saloni Mehra'!$B$7:$B$300,$B13) -> 305 | AB13: =IF(AND(AA13>0,AC13>0),AC13/AA13,"") -> 2162 | AC13: =SUMIFS('Saloni Mehra'!$E$7:$E$300,'Saloni Mehra'!$B$7:$B$300,$B13) -> 659410 | AD13: =SUMIFS('Saloni Mehra'!$H$7:$H$300,'Saloni Mehra'!$B$7:$B$300,$B13) -> 764604.5 | AE13: =AD13-AC13 -> 105194.5 | AF13: =IF(AC13>0,AE13/AC13,"") -> 0.15952821 | AG13: =IF(AD$6=0,"",AD13/AD$6) -> 0.068466778 | AH13: =SUMIFS('Vidushi Malhotra'!$D$7:$D$300,'Vidushi Malhotra'!$B$7:$B$300,$B13) -> 0 | AI13: =IF(AND(AH13>0,AJ13>0),AJ13/AH13,"") | AJ13: =SUMIFS('Vidushi Malhotra'!$E$7:$E$300,'Vidushi Malhotra'!$B$7:$B$300,$B13) -> 0 | AK13: =SUMIFS('Vidushi Malhotra'!$H$7:$H$300,'Vidushi Malhotra'!$B$7:$B$300,$B13) -> 0 | AL13: =AK13-AJ13 -> 0 | AM13: =IF(AJ13>0,AL13/AJ13,"") | AN13: =IF(AK$6=0,"",AK13/AK$6) -> 0 | AO13: =SUMIFS('Dr Umesh Choudhry'!$D$7:$D$300,'Dr Umesh Choudhry'!$B$7:$B$300,$B13) -> 29 | AP13: =IF(AND(AO13>0,AQ13>0),AQ13/AO13,"") -> 4227.6897 | AQ13: =SUMIFS('Dr Umesh Choudhry'!$E$7:$E$300,'Dr Umesh Choudhry'!$B$7:$B$300,$B13) -> 122603 | AR13: =SUMIFS('Dr Umesh Choudhry'!$H$7:$H$300,'Dr Umesh Choudhry'!$B$7:$B$300,$B13) -> 72700.1 | AS13: =AR13-AQ13 -> -49902.9 | AT13: =IF(AQ13>0,AS13/AQ13,"") -> -0.40702838 | AU13: =IF(AR$6=0,"",AR13/AR$6) -> 0.01341003 | AV13: =SUMIFS(DA!$D$7:$D$300,DA!$B$7:$B$300,$B13) -> 13 | AW13: =IF(AND(AV13>0,AX13>0),AX13/AV13,"") -> 2396 | AX13: =SUMIFS(DA!$E$7:$E$300,DA!$B$7:$B$300,$B13) -> 31148 | AY13: =SUMIFS(DA!$H$7:$H$300,DA!$B$7:$B$300,$B13) -> 32589.7 | AZ13: =AY13-AX13 -> 1441.7 | BA13: =IF(AX13>0,AZ13/AX13,"") -> 0.046285476 | BB13: =IF(AY$6=0,"",AY13/AY$6) -> 0.0084298007
A14: 8 | B14: LTM Ltd (formerly LTIMindtree) | C14: =IFERROR(INDEX(Prices!$C$6:$C$300,MATCH($B14,Prices!$A$6:$A$300,0)),"") -> 4274 | D14: =IFERROR(INDEX(Prices!$D$6:$D$300,MATCH($B14,Prices!$A$6:$A$300,0)),"") -> Close 22.10.2026 (Screener.in) | E14: =(M14>0)+(T14>0)+(AA14>0)+(AH14>0)+(AO14>0)+(AV14>0) -> 6 | F14: =M14+T14+AA14+AH14+AO14+AV14 -> 253 | G14: =IF(AND(F14>0,H14>0),H14/F14,"") -> 4727.1265 | H14: =O14+V14+AC14+AJ14+AQ14+AX14 -> 1195963 | I14: =P14+W14+AD14+AK14+AR14+AY14 -> 1081322 | J14: =I14-H14 -> -114641 | K14: =IF(H14>0,J14/H14,"") -> -0.095856644 | L14: =IF(I$6=0,"",I14/I$6) -> 0.028657796 | M14: =SUMIFS(Gautam!$D$7:$D$300,Gautam!$B$7:$B$300,$B14) -> 60 | N14: =IF(AND(M14>0,O14>0),O14/M14,"") -> 4564 | O14: =SUMIFS(Gautam!$E$7:$E$300,Gautam!$B$7:$B$300,$B14) -> 273840 | P14: =SUMIFS(Gautam!$H$7:$H$300,Gautam!$B$7:$B$300,$B14) -> 256440 | Q14: =P14-O14 -> -17400 | R14: =IF(O14>0,Q14/O14,"") -> -0.063540754 | S14: =IF(P$6=0,"",P14/P$6) -> 0.049077948 | T14: =SUMIFS('Manish Shilpa'!$D$7:$D$300,'Manish Shilpa'!$B$7:$B$300,$B14) -> 66 | U14: =IF(AND(T14>0,V14>0),V14/T14,"") -> 5274.803 | V14: =SUMIFS('Manish Shilpa'!$E$7:$E$300,'Manish Shilpa'!$B$7:$B$300,$B14) -> 348137 | W14: =SUMIFS('Manish Shilpa'!$H$7:$H$300,'Manish Shilpa'!$B$7:$B$300,$B14) -> 282084 | X14: =W14-V14 -> -66053 | Y14: =IF(V14>0,X14/V14,"") -> -0.18973278 | Z14: =IF(W$6=0,"",W14/W$6) -> 0.023853079 | AA14: =SUMIFS('Saloni Mehra'!$D$7:$D$300,'Saloni Mehra'!$B$7:$B$300,$B14) -> 83 | AB14: =IF(AND(AA14>0,AC14>0),AC14/AA14,"") -> 3897.9036 | AC14: =SUMIFS('Saloni Mehra'!$E$7:$E$300,'Saloni Mehra'!$B$7:$B$300,$B14) -> 323526 | AD14: =SUMIFS('Saloni Mehra'!$H$7:$H$300,'Saloni Mehra'!$B$7:$B$300,$B14) -> 354742 | AE14: =AD14-AC14 -> 31216 | AF14: =IF(AC14>0,AE14/AC14,"") -> 0.096486836 | AG14: =IF(AD$6=0,"",AD14/AD$6) -> 0.031765497 | AH14: =SUMIFS('Vidushi Malhotra'!$D$7:$D$300,'Vidushi Malhotra'!$B$7:$B$300,$B14) -> 2 | AI14: =IF(AND(AH14>0,AJ14>0),AJ14/AH14,"") -> 5099 | AJ14: =SUMIFS('Vidushi Malhotra'!$E$7:$E$300,'Vidushi Malhotra'!$B$7:$B$300,$B14) -> 10198 | AK14: =SUMIFS('Vidushi Malhotra'!$H$7:$H$300,'Vidushi Malhotra'!$B$7:$B$300,$B14) -> 8548 | AL14: =AK14-AJ14 -> -1650 | AM14: =IF(AJ14>0,AL14/AJ14,"") -> -0.16179643 | AN14: =IF(AK$6=0,"",AK14/AK$6) -> 0.037772974 | AO14: =SUMIFS('Dr Umesh Choudhry'!$D$7:$D$300,'Dr Umesh Choudhry'!$B$7:$B$300,$B14) -> 37 | AP14: =IF(AND(AO14>0,AQ14>0),AQ14/AO14,"") -> 5854.1081 | AQ14: =SUMIFS('Dr Umesh Choudhry'!$E$7:$E$300,'Dr Umesh Choudhry'!$B$7:$B$300,$B14) -> 216602 | AR14: =SUMIFS('Dr Umesh Choudhry'!$H$7:$H$300,'Dr Umesh Choudhry'!$B$7:$B$300,$B14) -> 158138 | AS14: =AR14-AQ14 -> -58464 | AT14: =IF(AQ14>0,AS14/AQ14,"") -> -0.26991441 | AU14: =IF(AR$6=0,"",AR14/AR$6) -> 0.029169634 | AV14: =SUMIFS(DA!$D$7:$D$300,DA!$B$7:$B$300,$B14) -> 5 | AW14: =IF(AND(AV14>0,AX14>0),AX14/AV14,"") -> 4732 | AX14: =SUMIFS(DA!$E$7:$E$300,DA!$B$7:$B$300,$B14) -> 23660 | AY14: =SUMIFS(DA!$H$7:$H$300,DA!$B$7:$B$300,$B14) -> 21370 | AZ14: =AY14-AX14 -> -2290 | BA14: =IF(AX14>0,AZ14/AX14,"") -> -0.096787828 | BB14: =IF(AY$6=0,"",AY14/AY$6) -> 0.0055276618
A15: 9 | B15: Bajaj Housing Finance Ltd | C15: =IFERROR(INDEX(Prices!$C$6:$C$300,MATCH($B15,Prices!$A$6:$A$300,0)),"") -> 81.02 | D15: =IFERROR(INDEX(Prices!$D$6:$D$300,MATCH($B15,Prices!$A$6:$A$300,0)),"") -> Close 22.10.2026 (Screener.in) | E15: =(M15>0)+(T15>0)+(AA15>0)+(AH15>0)+(AO15>0)+(AV15>0) -> 6 | F15: =M15+T15+AA15+AH15+AO15+AV15 -> 13273 | G15: =IF(AND(F15>0,H15>0),H15/F15,"") -> 100.94138 | H15: =O15+V15+AC15+AJ15+AQ15+AX15 -> 1339795 | I15: =P15+W15+AD15+AK15+AR15+AY15 -> 1075378.5 | J15: =I15-H15 -> -264416.54 | K15: =IF(H15>0,J15/H15,"") -> -0.19735597 | L15: =IF(I$6=0,"",I15/I$6) -> 0.028500277 | M15: =SUMIFS(Gautam!$D$7:$D$300,Gautam!$B$7:$B$300,$B15) -> 1600 | N15: =IF(AND(M15>0,O15>0),O15/M15,"") -> 83.08125 | O15: =SUMIFS(Gautam!$E$7:$E$300,Gautam!$B$7:$B$300,$B15) -> 132930 | P15: =SUMIFS(Gautam!$H$7:$H$300,Gautam!$B$7:$B$300,$B15) -> 129632 | Q15: =P15-O15 -> -3298 | R15: =IF(O15>0,Q15/O15,"") -> -0.02481005 | S15: =IF(P$6=0,"",P15/P$6) -> 0.024809205 | T15: =SUMIFS('Manish Shilpa'!$D$7:$D$300,'Manish Shilpa'!$B$7:$B$300,$B15) -> 3762 | U15: =IF(AND(T15>0,V15>0),V15/T15,"") -> 115.01675 | V15: =SUMIFS('Manish Shilpa'!$E$7:$E$300,'Manish Shilpa'!$B$7:$B$300,$B15) -> 432693 | W15: =SUMIFS('Manish Shilpa'!$H$7:$H$300,'Manish Shilpa'!$B$7:$B$300,$B15) -> 304797.24 | X15: =W15-V15 -> -127895.76 | Y15: =IF(V15>0,X15/V15,"") -> -0.29558084 | Z15: =IF(W$6=0,"",W15/W$6) -> 0.025773715 | AA15: =SUMIFS('Saloni Mehra'!$D$7:$D$300,'Saloni Mehra'!$B$7:$B$300,$B15) -> 3860 | AB15: =IF(AND(AA15>0,AC15>0),AC15/AA15,"") -> 85.925389 | AC15: =SUMIFS('Saloni Mehra'!$E$7:$E$300,'Saloni Mehra'!$B$7:$B$300,$B15) -> 331672 | AD15: =SUMIFS('Saloni Mehra'!$H$7:$H$300,'Saloni Mehra'!$B$7:$B$300,$B15) -> 312737.2 | AE15: =AD15-AC15 -> -18934.8 | AF15: =IF(AC15>0,AE15/AC15,"") -> -0.057088931 | AG15: =IF(AD$6=0,"",AD15/AD$6) -> 0.028004162 | AH15: =SUMIFS('Vidushi Malhotra'!$D$7:$D$300,'Vidushi Malhotra'!$B$7:$B$300,$B15) -> 121 | AI15: =IF(AND(AH15>0,AJ15>0),AJ15/AH15,"") -> 115.43802 | AJ15: =SUMIFS('Vidushi Malhotra'!$E$7:$E$300,'Vidushi Malhotra'!$B$7:$B$300,$B15) -> 13968 | AK15: =SUMIFS('Vidushi Malhotra'!$H$7:$H$300,'Vidushi Malhotra'!$B$7:$B$300,$B15) -> 9803.42 | AL15: =AK15-AJ15 -> -4164.58 | AM15: =IF(AJ15>0,AL15/AJ15,"") -> -0.29815149 | AN15: =IF(AK$6=0,"",AK15/AK$6) -> 0.043320582 | AO15: =SUMIFS('Dr Umesh Choudhry'!$D$7:$D$300,'Dr Umesh Choudhry'!$B$7:$B$300,$B15) -> 2198 | AP15: =IF(AND(AO15>0,AQ15>0),AQ15/AO15,"") -> 116.37853 | AQ15: =SUMIFS('Dr Umesh Choudhry'!$E$7:$E$300,'Dr Umesh Choudhry'!$B$7:$B$300,$B15) -> 255800 | AR15: =SUMIFS('Dr Umesh Choudhry'!$H$7:$H$300,'Dr Umesh Choudhry'!$B$7:$B$300,$B15) -> 178081.96 | AS15: =AR15-AQ15 -> -77718.04 | AT15: =IF(AQ15>0,AS15/AQ15,"") -> -0.30382346 | AU15: =IF(AR$6=0,"",AR15/AR$6) -> 0.032848433 | AV15: =SUMIFS(DA!$D$7:$D$300,DA!$B$7:$B$300,$B15) -> 1732 | AW15: =IF(AND(AV15>0,AX15>0),AX15/AV15,"") -> 99.729792 | AX15: =SUMIFS(DA!$E$7:$E$300,DA!$B$7:$B$300,$B15) -> 172732 | AY15: =SUMIFS(DA!$H$7:$H$300,DA!$B$7:$B$300,$B15) -> 140326.64 | AZ15: =AY15-AX15 -> -32405.36 | BA15: =IF(AX15>0,AZ15/AX15,"") -> -0.18760484 | BB15: =IF(AY$6=0,"",AY15/AY$6) -> 0.03629753
A16: 10 | B16: Connplex Cinemas Ltd | C16: =IFERROR(INDEX(Prices!$C$6:$C$300,MATCH($B16,Prices!$A$6:$A$300,0)),"") -> 234.25 | D16: =IFERROR(INDEX(Prices!$D$6:$D$300,MATCH($B16,Prices!$A$6:$A$300,0)),"") -> Close 22.10.2026 (Screener.in) | E16: =(M16>0)+(T16>0)+(AA16>0)+(AH16>0)+(AO16>0)+(AV16>0) -> 5 | F16: =M16+T16+AA16+AH16+AO16+AV16 -> 4000 | G16: =IF(AND(F16>0,H16>0),H16/F16,"") -> 233.36675 | H16: =O16+V16+AC16+AJ16+AQ16+AX16 -> 933467 | I16: =P16+W16+AD16+AK16+AR16+AY16 -> 937000 | J16: =I16-H16 -> 3533 | K16: =IF(H16>0,J16/H16,"") -> 0.0037848151 | L16: =IF(I$6=0,"",I16/I$6) -> 0.024832894 | M16: =SUMIFS(Gautam!$D$7:$D$300,Gautam!$B$7:$B$300,$B16) -> 800 | N16: =IF(AND(M16>0,O16>0),O16/M16,"") -> 264 | O16: =SUMIFS(Gautam!$E$7:$E$300,Gautam!$B$7:$B$300,$B16) -> 211200 | P16: =SUMIFS(Gautam!$H$7:$H$300,Gautam!$B$7:$B$300,$B16) -> 187400 | Q16: =P16-O16 -> -23800 | R16: =IF(O16>0,Q16/O16,"") -> -0.11268939 | S16: =IF(P$6=0,"",P16/P$6) -> 0.035864949 | T16: =SUMIFS('Manish Shilpa'!$D$7:$D$300,'Manish Shilpa'!$B$7:$B$300,$B16) -> 800 | U16: =IF(AND(T16>0,V16>0),V16/T16,"") -> 235.09375 | V16: =SUMIFS('Manish Shilpa'!$E$7:$E$300,'Manish Shilpa'!$B$7:$B$300,$B16) -> 188075 | W16: =SUMIFS('Manish Shilpa'!$H$7:$H$300,'Manish Shilpa'!$B$7:$B$300,$B16) -> 187400 | X16: =W16-V16 -> -675 | Y16: =IF(V16>0,X16/V16,"") -> -0.0035889938 | Z16: =IF(W$6=0,"",W16/W$6) -> 0.015846581 | AA16: =SUMIFS('Saloni Mehra'!$D$7:$D$300,'Saloni Mehra'!$B$7:$B$300,$B16) -> 800 | AB16: =IF(AND(AA16>0,AC16>0),AC16/AA16,"") -> 212.75 | AC16: =SUMIFS('Saloni Mehra'!$E$7:$E$300,'Saloni Mehra'!$B$7:$B$300,$B16) -> 170200 | AD16: =SUMIFS('Saloni Mehra'!$H$7:$H$300,'Saloni Mehra'!$B$7:$B$300,$B16) -> 187400 | AE16: =AD16-AC16 -> 17200 | AF16: =IF(AC16>0,AE16/AC16,"") -> 0.10105758 | AG16: =IF(AD$6=0,"",AD16/AD$6) -> 0.016780799 | AH16: =SUMIFS('Vidushi Malhotra'!$D$7:$D$300,'Vidushi Malhotra'!$B$7:$B$300,$B16) -> 0 | AI16: =IF(AND(AH16>0,AJ16>0),AJ16/AH16,"") | AJ16: =SUMIFS('Vidushi Malhotra'!$E$7:$E$300,'Vidushi Malhotra'!$B$7:$B$300,$B16) -> 0 | AK16: =SUMIFS('Vidushi Malhotra'!$H$7:$H$300,'Vidushi Malhotra'!$B$7:$B$300,$B16) -> 0 | AL16: =AK16-AJ16 -> 0 | AM16: =IF(AJ16>0,AL16/AJ16,"") | AN16: =IF(AK$6=0,"",AK16/AK$6) -> 0 | AO16: =SUMIFS('Dr Umesh Choudhry'!$D$7:$D$300,'Dr Umesh Choudhry'!$B$7:$B$300,$B16) -> 800 | AP16: =IF(AND(AO16>0,AQ16>0),AQ16/AO16,"") -> 229.99 | AQ16: =SUMIFS('Dr Umesh Choudhry'!$E$7:$E$300,'Dr Umesh Choudhry'!$B$7:$B$300,$B16) -> 183992 | AR16: =SUMIFS('Dr Umesh Choudhry'!$H$7:$H$300,'Dr Umesh Choudhry'!$B$7:$B$300,$B16) -> 187400 | AS16: =AR16-AQ16 -> 3408 | AT16: =IF(AQ16>0,AS16/AQ16,"") -> 0.018522544 | AU16: =IF(AR$6=0,"",AR16/AR$6) -> 0.03456721 | AV16: =SUMIFS(DA!$D$7:$D$300,DA!$B$7:$B$300,$B16) -> 800 | AW16: =IF(AND(AV16>0,AX16>0),AX16/AV16,"") -> 225 | AX16: =SUMIFS(DA!$E$7:$E$300,DA!$B$7:$B$300,$B16) -> 180000 | AY16: =SUMIFS(DA!$H$7:$H$300,DA!$B$7:$B$300,$B16) -> 187400 | AZ16: =AY16-AX16 -> 7400 | BA16: =IF(AX16>0,AZ16/AX16,"") -> 0.041111111 | BB16: =IF(AY$6=0,"",AY16/AY$6) -> 0.04847374
A17: 11 | B17: L&T Technology Services Ltd | C17: =IFERROR(INDEX(Prices!$C$6:$C$300,MATCH($B17,Prices!$A$6:$A$300,0)),"") -> 3954.8 | D17: =IFERROR(INDEX(Prices!$D$6:$D$300,MATCH($B17,Prices!$A$6:$A$300,0)),"") -> Close 22.10.2026 (Screener.in) | E17: =(M17>0)+(T17>0)+(AA17>0)+(AH17>0)+(AO17>0)+(AV17>0) -> 6 | F17: =M17+T17+AA17+AH17+AO17+AV17 -> 231 | G17: =IF(AND(F17>0,H17>0),H17/F17,"") -> 3876.0303 | H17: =O17+V17+AC17+AJ17+AQ17+AX17 -> 895363 | I17: =P17+W17+AD17+AK17+AR17+AY17 -> 913558.8 | J17: =I17-H17 -> 18195.8 | K17: =IF(H17>0,J17/H17,"") -> 0.02032226 | L17: =IF(I$6=0,"",I17/I$6) -> 0.024211643 | M17: =SUMIFS(Gautam!$D$7:$D$300,Gautam!$B$7:$B$300,$B17) -> 30 | N17: =IF(AND(M17>0,O17>0),O17/M17,"") -> 3484.3667 | O17: =SUMIFS(Gautam!$E$7:$E$300,Gautam!$B$7:$B$300,$B17) -> 104531 | P17: =SUMIFS(Gautam!$H$7:$H$300,Gautam!$B$7:$B$300,$B17) -> 118644 | Q17: =P17-O17 -> 14113 | R17: =IF(O17>0,Q17/O17,"") -> 0.13501258 | S17: =IF(P$6=0,"",P17/P$6) -> 0.022706302 | T17: =SUMIFS('Manish Shilpa'!$D$7:$D$300,'Manish Shilpa'!$B$7:$B$300,$B17) -> 72 | U17: =IF(AND(T17>0,V17>0),V17/T17,"") -> 4214.8194 | V17: =SUMIFS('Manish Shilpa'!$E$7:$E$300,'Manish Shilpa'!$B$7:$B$300,$B17) -> 303467 | W17: =SUMIFS('Manish Shilpa'!$H$7:$H$300,'Manish Shilpa'!$B$7:$B$300,$B17) -> 284745.6 | X17: =W17-V17 -> -18721.4 | Y17: =IF(V17>0,X17/V17,"") -> -0.061691716 | Z17: =IF(W$6=0,"",W17/W$6) -> 0.024078144 | AA17: =SUMIFS('Saloni Mehra'!$D$7:$D$300,'Saloni Mehra'!$B$7:$B$300,$B17) -> 72 | AB17: =IF(AND(AA17>0,AC17>0),AC17/AA17,"") -> 3415.2083 | AC17: =SUMIFS('Saloni Mehra'!$E$7:$E$300,'Saloni Mehra'!$B$7:$B$300,$B17) -> 245895 | AD17: =SUMIFS('Saloni Mehra'!$H$7:$H$300,'Saloni Mehra'!$B$7:$B$300,$B17) -> 284745.6 | AE17: =AD17-AC17 -> 38850.6 | AF17: =IF(AC17>0,AE17/AC17,"") -> 0.15799671 | AG17: =IF(AD$6=0,"",AD17/AD$6) -> 0.025497645 | AH17: =SUMIFS('Vidushi Malhotra'!$D$7:$D$300,'Vidushi Malhotra'!$B$7:$B$300,$B17) -> 1 | AI17: =IF(AND(AH17>0,AJ17>0),AJ17/AH17,"") -> 4607 | AJ17: =SUMIFS('Vidushi Malhotra'!$E$7:$E$300,'Vidushi Malhotra'!$B$7:$B$300,$B17) -> 4607 | AK17: =SUMIFS('Vidushi Malhotra'!$H$7:$H$300,'Vidushi Malhotra'!$B$7:$B$300,$B17) -> 3954.8 | AL17: =AK17-AJ17 -> -652.2 | AM17: =IF(AJ17>0,AL17/AJ17,"") -> -0.14156718 | AN17: =IF(AK$6=0,"",AK17/AK$6) -> 0.017475966 | AO17: =SUMIFS('Dr Umesh Choudhry'!$D$7:$D$300,'Dr Umesh Choudhry'!$B$7:$B$300,$B17) -> 32 | AP17: =IF(AND(AO17>0,AQ17>0),AQ17/AO17,"") -> 4719.9688 | AQ17: =SUMIFS('Dr Umesh Choudhry'!$E$7:$E$300,'Dr Umesh Choudhry'!$B$7:$B$300,$B17) -> 151039 | AR17: =SUMIFS('Dr Umesh Choudhry'!$H$7:$H$300,'Dr Umesh Choudhry'!$B$7:$B$300,$B17) -> 126553.6 | AS17: =AR17-AQ17 -> -24485.4 | AT17: =IF(AQ17>0,AS17/AQ17,"") -> -0.1621131 | AU17: =IF(AR$6=0,"",AR17/AR$6) -> 0.023343676 | AV17: =SUMIFS(DA!$D$7:$D$300,DA!$B$7:$B$300,$B17) -> 24 | AW17: =IF(AND(AV17>0,AX17>0),AX17/AV17,"") -> 3576 | AX17: =SUMIFS(DA!$E$7:$E$300,DA!$B$7:$B$300,$B17) -> 85824 | AY17: =SUMIFS(DA!$H$7:$H$300,DA!$B$7:$B$300,$B17) -> 94915.2 | AZ17: =AY17-AX17 -> 9091.2 | BA17: =IF(AX17>0,AZ17/AX17,"") -> 0.10592841 | BB17: =IF(AY$6=0,"",AY17/AY$6) -> 0.024551199
A18: 12 | B18: Jubilant FoodWorks Ltd | C18: =IFERROR(INDEX(Prices!$C$6:$C$300,MATCH($B18,Prices!$A$6:$A$300,0)),"") -> 404.9 | D18: =IFERROR(INDEX(Prices!$D$6:$D$300,MATCH($B18,Prices!$A$6:$A$300,0)),"") -> Close 22.10.2026 (Screener.in) | E18: =(M18>0)+(T18>0)+(AA18>0)+(AH18>0)+(AO18>0)+(AV18>0) -> 1 | F18: =M18+T18+AA18+AH18+AO18+AV18 -> 2000 | G18: =IF(AND(F18>0,H18>0),H18/F18,"") -> 422.65 | H18: =O18+V18+AC18+AJ18+AQ18+AX18 -> 845300 | I18: =P18+W18+AD18+AK18+AR18+AY18 -> 809800 | J18: =I18-H18 -> -35500 | K18: =IF(H18>0,J18/H18,"") -> -0.041996924 | L18: =IF(I$6=0,"",I18/I$6) -> 0.021461769 | M18: =SUMIFS(Gautam!$D$7:$D$300,Gautam!$B$7:$B$300,$B18) -> 0 | N18: =IF(AND(M18>0,O18>0),O18/M18,"") | O18: =SUMIFS(Gautam!$E$7:$E$300,Gautam!$B$7:$B$300,$B18) -> 0 | P18: =SUMIFS(Gautam!$H$7:$H$300,Gautam!$B$7:$B$300,$B18) -> 0 | Q18: =P18-O18 -> 0 | R18: =IF(O18>0,Q18/O18,"") | S18: =IF(P$6=0,"",P18/P$6) -> 0 | T18: =SUMIFS('Manish Shilpa'!$D$7:$D$300,'Manish Shilpa'!$B$7:$B$300,$B18) -> 0 | U18: =IF(AND(T18>0,V18>0),V18/T18,"") | V18: =SUMIFS('Manish Shilpa'!$E$7:$E$300,'Manish Shilpa'!$B$7:$B$300,$B18) -> 0 | W18: =SUMIFS('Manish Shilpa'!$H$7:$H$300,'Manish Shilpa'!$B$7:$B$300,$B18) -> 0 | X18: =W18-V18 -> 0 | Y18: =IF(V18>0,X18/V18,"") | Z18: =IF(W$6=0,"",W18/W$6) -> 0 | AA18: =SUMIFS('Saloni Mehra'!$D$7:$D$300,'Saloni Mehra'!$B$7:$B$300,$B18) -> 2000 | AB18: =IF(AND(AA18>0,AC18>0),AC18/AA18,"") -> 422.65 | AC18: =SUMIFS('Saloni Mehra'!$E$7:$E$300,'Saloni Mehra'!$B$7:$B$300,$B18) -> 845300 | AD18: =SUMIFS('Saloni Mehra'!$H$7:$H$300,'Saloni Mehra'!$B$7:$B$300,$B18) -> 809800 | AE18: =AD18-AC18 -> -35500 | AF18: =IF(AC18>0,AE18/AC18,"") -> -0.041996924 | AG18: =IF(AD$6=0,"",AD18/AD$6) -> 0.072513825 | AH18: =SUMIFS('Vidushi Malhotra'!$D$7:$D$300,'Vidushi Malhotra'!$B$7:$B$300,$B18) -> 0 | AI18: =IF(AND(AH18>0,AJ18>0),AJ18/AH18,"") | AJ18: =SUMIFS('Vidushi Malhotra'!$E$7:$E$300,'Vidushi Malhotra'!$B$7:$B$300,$B18) -> 0 | AK18: =SUMIFS('Vidushi Malhotra'!$H$7:$H$300,'Vidushi Malhotra'!$B$7:$B$300,$B18) -> 0 | AL18: =AK18-AJ18 -> 0 | AM18: =IF(AJ18>0,AL18/AJ18,"") | AN18: =IF(AK$6=0,"",AK18/AK$6) -> 0 | AO18: =SUMIFS('Dr Umesh Choudhry'!$D$7:$D$300,'Dr Umesh Choudhry'!$B$7:$B$300,$B18) -> 0 | AP18: =IF(AND(AO18>0,AQ18>0),AQ18/AO18,"") | AQ18: =SUMIFS('Dr Umesh Choudhry'!$E$7:$E$300,'Dr Umesh Choudhry'!$B$7:$B$300,$B18) -> 0 | AR18: =SUMIFS('Dr Umesh Choudhry'!$H$7:$H$300,'Dr Umesh Choudhry'!$B$7:$B$300,$B18) -> 0 | AS18: =AR18-AQ18 -> 0 | AT18: =IF(AQ18>0,AS18/AQ18,"") | AU18: =IF(AR$6=0,"",AR18/AR$6) -> 0 | AV18: =SUMIFS(DA!$D$7:$D$300,DA!$B$7:$B$300,$B18) -> 0 | AW18: =IF(AND(AV18>0,AX18>0),AX18/AV18,"") | AX18: =SUMIFS(DA!$E$7:$E$300,DA!$B$7:$B$300,$B18) -> 0 | AY18: =SUMIFS(DA!$H$7:$H$300,DA!$B$7:$B$300,$B18) -> 0 | AZ18: =AY18-AX18 -> 0 | BA18: =IF(AX18>0,AZ18/AX18,"") | BB18: =IF(AY$6=0,"",AY18/AY$6) -> 0
... A95: 89 | B95: PSL Ltd (formerly PSL Holdings Ltd) | C95: =IFERROR(INDEX(Prices!$C$6:$C$300,MATCH($B95,Prices!$A$6:$A$300,0)),"") | D95: =IFERROR(INDEX(Prices!$D$6:$D$300,MATCH($B95,Prices!$A$6:$A$300,0)),"") -> No price on any statement | E95: =(M95>0)+(T95>0)+(AA95>0)+(AH95>0)+(AO95>0)+(AV95>0) -> 1 | F95: =M95+T95+AA95+AH95+AO95+AV95 -> 1000 | G95: =IF(AND(F95>0,H95>0),H95/F95,"") | H95: =O95+V95+AC95+AJ95+AQ95+AX95 -> 0 | I95: =P95+W95+AD95+AK95+AR95+AY95 -> 0 | J95: =I95-H95 -> 0 | K95: =IF(H95>0,J95/H95,"") | L95: =IF(I$6=0,"",I95/I$6) -> 0 | M95: =SUMIFS(Gautam!$D$7:$D$300,Gautam!$B$7:$B$300,$B95) -> 1000 | N95: =IF(AND(M95>0,O95>0),O95/M95,"") | O95: =SUMIFS(Gautam!$E$7:$E$300,Gautam!$B$7:$B$300,$B95) -> 0 | P95: =SUMIFS(Gautam!$H$7:$H$300,Gautam!$B$7:$B$300,$B95) -> 0 | Q95: =P95-O95 -> 0 | R95: =IF(O95>0,Q95/O95,"") | S95: =IF(P$6=0,"",P95/P$6) -> 0 | T95: =SUMIFS('Manish Shilpa'!$D$7:$D$300,'Manish Shilpa'!$B$7:$B$300,$B95) -> 0 | U95: =IF(AND(T95>0,V95>0),V95/T95,"") | V95: =SUMIFS('Manish Shilpa'!$E$7:$E$300,'Manish Shilpa'!$B$7:$B$300,$B95) -> 0 | W95: =SUMIFS('Manish Shilpa'!$H$7:$H$300,'Manish Shilpa'!$B$7:$B$300,$B95) -> 0 | X95: =W95-V95 -> 0 | Y95: =IF(V95>0,X95/V95,"") | Z95: =IF(W$6=0,"",W95/W$6) -> 0 | AA95: =SUMIFS('Saloni Mehra'!$D$7:$D$300,'Saloni Mehra'!$B$7:$B$300,$B95) -> 0 | AB95: =IF(AND(AA95>0,AC95>0),AC95/AA95,"") | AC95: =SUMIFS('Saloni Mehra'!$E$7:$E$300,'Saloni Mehra'!$B$7:$B$300,$B95) -> 0 | AD95: =SUMIFS('Saloni Mehra'!$H$7:$H$300,'Saloni Mehra'!$B$7:$B$300,$B95) -> 0 | AE95: =AD95-AC95 -> 0 | AF95: =IF(AC95>0,AE95/AC95,"") | AG95: =IF(AD$6=0,"",AD95/AD$6) -> 0 | AH95: =SUMIFS('Vidushi Malhotra'!$D$7:$D$300,'Vidushi Malhotra'!$B$7:$B$300,$B95) -> 0 | AI95: =IF(AND(AH95>0,AJ95>0),AJ95/AH95,"") | AJ95: =SUMIFS('Vidushi Malhotra'!$E$7:$E$300,'Vidushi Malhotra'!$B$7:$B$300,$B95) -> 0 | AK95: =SUMIFS('Vidushi Malhotra'!$H$7:$H$300,'Vidushi Malhotra'!$B$7:$B$300,$B95) -> 0 | AL95: =AK95-AJ95 -> 0 | AM95: =IF(AJ95>0,AL95/AJ95,"") | AN95: =IF(AK$6=0,"",AK95/AK$6) -> 0 | AO95: =SUMIFS('Dr Umesh Choudhry'!$D$7:$D$300,'Dr Umesh Choudhry'!$B$7:$B$300,$B95) -> 0 | AP95: =IF(AND(AO95>0,AQ95>0),AQ95/AO95,"") | AQ95: =SUMIFS('Dr Umesh Choudhry'!$E$7:$E$300,'Dr Umesh Choudhry'!$B$7:$B$300,$B95) -> 0 | AR95: =SUMIFS('Dr Umesh Choudhry'!$H$7:$H$300,'Dr Umesh Choudhry'!$B$7:$B$300,$B95) -> 0 | AS95: =AR95-AQ95 -> 0 | AT95: =IF(AQ95>0,AS95/AQ95,"") | AU95: =IF(AR$6=0,"",AR95/AR$6) -> 0 | AV95: =SUMIFS(DA!$D$7:$D$300,DA!$B$7:$B$300,$B95) -> 0 | AW95: =IF(AND(AV95>0,AX95>0),AX95/AV95,"") | AX95: =SUMIFS(DA!$E$7:$E$300,DA!$B$7:$B$300,$B95) -> 0 | AY95: =SUMIFS(DA!$H$7:$H$300,DA!$B$7:$B$300,$B95) -> 0 | AZ95: =AY95-AX95 -> 0 | BA95: =IF(AX95>0,AZ95/AX95,"") | BB95: =IF(AY$6=0,"",AY95/AY$6) -> 0

Sheet Prices
A1: COMMON PRICE SHEET
A2: One price per security, used to value every portfolio. Without an exchange close, the statement price is used, freshest statement first: Gautam stmt – 23.10 → Manish Shilpa stmt – live 23.10 → Saloni stmt – 20.10 (stale) → Vidushi stmt – LTP 05.10 → Umesh stmt – NSE live 09.10 → DA stmt – older (stale).
A3: Column B holds NSE/BSE closes for 22.10.2026 (Screener.in). TO UPDATE: overwrite the yellow column B and the source text beside it — every portfolio and the combined view revalue. Blank B = statement price.
A5: Security | B5: Override Price (₹) ← type here | C5: Ref Price (₹) (used everywhere) | D5: Price Basis | E5: Gautam stmt (₹) | F5: Manish Shilpa stmt (₹) | G5: Saloni Mehra stmt (₹) | H5: Vidushi Malhotra stmt (₹) | I5: Dr Umesh Choudhry stmt (₹) | J5: DA stmt (₹) | K5: Override source | L5: Prev close 21.10 (₹) | M5: 1-day chg %
A6: Aarti Drugs Ltd | B6: 380.05 | C6: =IF(ISNUMBER(B6),B6,IF(ISNUMBER(E6),E6,IF(ISNUMBER(F6),F6,IF(ISNUMBER(G6),G6,IF(ISNUMBER(H6),H6,IF(ISNUMBER(I6),I6,IF(ISNUMBER(J6),J6,""))))))) -> 380.05 | D6: =IF(ISNUMBER(B6),IF(K6<>"",K6,"Manual override"),IF(ISNUMBER(E6),"Gautam stmt – 23.10",IF(ISNUMBER(F6),"Manish Shilpa stmt – live 23.10",IF(ISNUMBER(G6),"Saloni stmt – 20.10 (stale)",IF(ISNUMBER(H6),"Vidushi stmt – LTP 05.10",IF(ISNUMBER(I6),"Umesh stmt – NSE live 09.10",IF(ISNUMBER(J6),"DA stmt – older (stale)","No price on any statement"))))))) -> Close 22.10.2026 (Screener.in) | E6: =IFERROR(INDEX(Gautam!$M$7:$M$300,MATCH($A6,Gautam!$B$7:$B$300,0)),"") | F6: =IFERROR(INDEX('Manish Shilpa'!$M$7:$M$300,MATCH($A6,'Manish Shilpa'!$B$7:$B$300,0)),"") -> 373.5 | G6: =IFERROR(INDEX('Saloni Mehra'!$M$7:$M$300,MATCH($A6,'Saloni Mehra'!$B$7:$B$300,0)),"") | H6: =IFERROR(INDEX('Vidushi Malhotra'!$M$7:$M$300,MATCH($A6,'Vidushi Malhotra'!$B$7:$B$300,0)),"") | I6: =IFERROR(INDEX('Dr Umesh Choudhry'!$M$7:$M$300,MATCH($A6,'Dr Umesh Choudhry'!$B$7:$B$300,0)),"") | J6: =IFERROR(INDEX(DA!$M$7:$M$300,MATCH($A6,DA!$B$7:$B$300,0)),"") | K6: Close 22.10.2026 (Screener.in) | L6: 388.6 | M6: =IF(AND(ISNUMBER(B6),ISNUMBER(L6),N(L6)>0),B6/L6-1,"") -> -0.022002059
A7: Abbott India Ltd | B7: 25360 | C7: =IF(ISNUMBER(B7),B7,IF(ISNUMBER(E7),E7,IF(ISNUMBER(F7),F7,IF(ISNUMBER(G7),G7,IF(ISNUMBER(H7),H7,IF(ISNUMBER(I7),I7,IF(ISNUMBER(J7),J7,""))))))) -> 25360 | D7: =IF(ISNUMBER(B7),IF(K7<>"",K7,"Manual override"),IF(ISNUMBER(E7),"Gautam stmt – 23.10",IF(ISNUMBER(F7),"Manish Shilpa stmt – live 23.10",IF(ISNUMBER(G7),"Saloni stmt – 20.10 (stale)",IF(ISNUMBER(H7),"Vidushi stmt – LTP 05.10",IF(ISNUMBER(I7),"Umesh stmt – NSE live 09.10",IF(ISNUMBER(J7),"DA stmt – older (stale)","No price on any statement"))))))) -> Close 22.10.2026 (Screener.in) | E7: =IFERROR(INDEX(Gautam!$M$7:$M$300,MATCH($A7,Gautam!$B$7:$B$300,0)),"") | F7: =IFERROR(INDEX('Manish Shilpa'!$M$7:$M$300,MATCH($A7,'Manish Shilpa'!$B$7:$B$300,0)),"") -> 24800 | G7: =IFERROR(INDEX('Saloni Mehra'!$M$7:$M$300,MATCH($A7,'Saloni Mehra'!$B$7:$B$300,0)),"") | H7: =IFERROR(INDEX('Vidushi Malhotra'!$M$7:$M$300,MATCH($A7,'Vidushi Malhotra'!$B$7:$B$300,0)),"") | I7: =IFERROR(INDEX('Dr Umesh Choudhry'!$M$7:$M$300,MATCH($A7,'Dr Umesh Choudhry'!$B$7:$B$300,0)),"") | J7: =IFERROR(INDEX(DA!$M$7:$M$300,MATCH($A7,DA!$B$7:$B$300,0)),"") | K7: Close 22.10.2026 (Screener.in) | L7: 25680 | M7: =IF(AND(ISNUMBER(B7),ISNUMBER(L7),N(L7)>0),B7/L7-1,"") -> -0.012461059
A8: AFCOM Holdings Ltd | B8: 1371.45 | C8: =IF(ISNUMBER(B8),B8,IF(ISNUMBER(E8),E8,IF(ISNUMBER(F8),F8,IF(ISNUMBER(G8),G8,IF(ISNUMBER(H8),H8,IF(ISNUMBER(I8),I8,IF(ISNUMBER(J8),J8,""))))))) -> 1371.45 | D8: =IF(ISNUMBER(B8),IF(K8<>"",K8,"Manual override"),IF(ISNUMBER(E8),"Gautam stmt – 23.10",IF(ISNUMBER(F8),"Manish Shilpa stmt – live 23.10",IF(ISNUMBER(G8),"Saloni stmt – 20.10 (stale)",IF(ISNUMBER(H8),"Vidushi stmt – LTP 05.10",IF(ISNUMBER(I8),"Umesh stmt – NSE live 09.10",IF(ISNUMBER(J8),"DA stmt – older (stale)","No price on any statement"))))))) -> Close 22.10.2026 (Screener.in) | E8: =IFERROR(INDEX(Gautam!$M$7:$M$300,MATCH($A8,Gautam!$B$7:$B$300,0)),"") -> 1377 | F8: =IFERROR(INDEX('Manish Shilpa'!$M$7:$M$300,MATCH($A8,'Manish Shilpa'!$B$7:$B$300,0)),"") -> 1270 | G8: =IFERROR(INDEX('Saloni Mehra'!$M$7:$M$300,MATCH($A8,'Saloni Mehra'!$B$7:$B$300,0)),"") -> 1490.95 | H8: =IFERROR(INDEX('Vidushi Malhotra'!$M$7:$M$300,MATCH($A8,'Vidushi Malhotra'!$B$7:$B$300,0)),"") | I8: =IFERROR(INDEX('Dr Umesh Choudhry'!$M$7:$M$300,MATCH($A8,'Dr Umesh Choudhry'!$B$7:$B$300,0)),"") -> 1425 | J8: =IFERROR(INDEX(DA!$M$7:$M$300,MATCH($A8,DA!$B$7:$B$300,0)),"") -> 1540 | K8: Close 22.10.2026 (Screener.in) | L8: 1414.9 | M8: =IF(AND(ISNUMBER(B8),ISNUMBER(L8),N(L8)>0),B8/L8-1,"") -> -0.030708884
A9: Affle 3i Ltd | B9: 1362.8 | C9: =IF(ISNUMBER(B9),B9,IF(ISNUMBER(E9),E9,IF(ISNUMBER(F9),F9,IF(ISNUMBER(G9),G9,IF(ISNUMBER(H9),H9,IF(ISNUMBER(I9),I9,IF(ISNUMBER(J9),J9,""))))))) -> 1362.8 | D9: =IF(ISNUMBER(B9),IF(K9<>"",K9,"Manual override"),IF(ISNUMBER(E9),"Gautam stmt – 23.10",IF(ISNUMBER(F9),"Manish Shilpa stmt – live 23.10",IF(ISNUMBER(G9),"Saloni stmt – 20.10 (stale)",IF(ISNUMBER(H9),"Vidushi stmt – LTP 05.10",IF(ISNUMBER(I9),"Umesh stmt – NSE live 09.10",IF(ISNUMBER(J9),"DA stmt – older (stale)","No price on any statement"))))))) -> Close 22.10.2026 (Screener.in) | E9: =IFERROR(INDEX(Gautam!$M$7:$M$300,MATCH($A9,Gautam!$B$7:$B$300,0)),"") -> 1363 | F9: =IFERROR(INDEX('Manish Shilpa'!$M$7:$M$300,MATCH($A9,'Manish Shilpa'!$B$7:$B$300,0)),"") -> 1324.5532 | G9: =IFERROR(INDEX('Saloni Mehra'!$M$7:$M$300,MATCH($A9,'Saloni Mehra'!$B$7:$B$300,0)),"") | H9: =IFERROR(INDEX('Vidushi Malhotra'!$M$7:$M$300,MATCH($A9,'Vidushi Malhotra'!$B$7:$B$300,0)),"") -> 1456.6667 | I9: =IFERROR(INDEX('Dr Umesh Choudhry'!$M$7:$M$300,MATCH($A9,'Dr Umesh Choudhry'!$B$7:$B$300,0)),"") -> 1422.8936 | J9: =IFERROR(INDEX(DA!$M$7:$M$300,MATCH($A9,DA!$B$7:$B$300,0)),"") -> 1568 | K9: Close 22.10.2026 (Screener.in) | L9: 1395.3 | M9: =IF(AND(ISNUMBER(B9),ISNUMBER(L9),N(L9)>0),B9/L9-1,"") -> -0.023292482
A10: Alkyl Amines Chemicals Ltd | B10: 1704.2 | C10: =IF(ISNUMBER(B10),B10,IF(ISNUMBER(E10),E10,IF(ISNUMBER(F10),F10,IF(ISNUMBER(G10),G10,IF(ISNUMBER(H10),H10,IF(ISNUMBER(I10),I10,IF(ISNUMBER(J10),J10,""))))))) -> 1704.2 | D10: =IF(ISNUMBER(B10),IF(K10<>"",K10,"Manual override"),IF(ISNUMBER(E10),"Gautam stmt – 23.10",IF(ISNUMBER(F10),"Manish Shilpa stmt – live 23.10",IF(ISNUMBER(G10),"Saloni stmt – 20.10 (stale)",IF(ISNUMBER(H10),"Vidushi stmt – LTP 05.10",IF(ISNUMBER(I10),"Umesh stmt – NSE live 09.10",IF(ISNUMBER(J10),"DA stmt – older (stale)","No price on any statement"))))))) -> Close 22.10.2026 (Screener.in) | E10: =IFERROR(INDEX(Gautam!$M$7:$M$300,MATCH($A10,Gautam!$B$7:$B$300,0)),"") | F10: =IFERROR(INDEX('Manish Shilpa'!$M$7:$M$300,MATCH($A10,'Manish Shilpa'!$B$7:$B$300,0)),"") -> 1621.6667 | G10: =IFERROR(INDEX('Saloni Mehra'!$M$7:$M$300,MATCH($A10,'Saloni Mehra'!$B$7:$B$300,0)),"") | H10: =IFERROR(INDEX('Vidushi Malhotra'!$M$7:$M$300,MATCH($A10,'Vidushi Malhotra'!$B$7:$B$300,0)),"") | I10: =IFERROR(INDEX('Dr Umesh Choudhry'!$M$7:$M$300,MATCH($A10,'Dr Umesh Choudhry'!$B$7:$B$300,0)),"") | J10: =IFERROR(INDEX(DA!$M$7:$M$300,MATCH($A10,DA!$B$7:$B$300,0)),"") | K10: Close 22.10.2026 (Screener.in) | L10: 1721.4 | M10: =IF(AND(ISNUMBER(B10),ISNUMBER(L10),N(L10)>0),B10/L10-1,"") -> -0.0099918671
A11: Ambuja Cements Ltd | B11: 363 | C11: =IF(ISNUMBER(B11),B11,IF(ISNUMBER(E11),E11,IF(ISNUMBER(F11),F11,IF(ISNUMBER(G11),G11,IF(ISNUMBER(H11),H11,IF(ISNUMBER(I11),I11,IF(ISNUMBER(J11),J11,""))))))) -> 363 | D11: =IF(ISNUMBER(B11),IF(K11<>"",K11,"Manual override"),IF(ISNUMBER(E11),"Gautam stmt – 23.10",IF(ISNUMBER(F11),"Manish Shilpa stmt – live 23.10",IF(ISNUMBER(G11),"Saloni stmt – 20.10 (stale)",IF(ISNUMBER(H11),"Vidushi stmt – LTP 05.10",IF(ISNUMBER(I11),"Umesh stmt – NSE live 09.10",IF(ISNUMBER(J11),"DA stmt – older (stale)","No price on any statement"))))))) -> Close 22.10.2026 (Screener.in) | E11: =IFERROR(INDEX(Gautam!$M$7:$M$300,MATCH($A11,Gautam!$B$7:$B$300,0)),"") | F11: =IFERROR(INDEX('Manish Shilpa'!$M$7:$M$300,MATCH($A11,'Manish Shilpa'!$B$7:$B$300,0)),"") | G11: =IFERROR(INDEX('Saloni Mehra'!$M$7:$M$300,MATCH($A11,'Saloni Mehra'!$B$7:$B$300,0)),"") | H11: =IFERROR(INDEX('Vidushi Malhotra'!$M$7:$M$300,MATCH($A11,'Vidushi Malhotra'!$B$7:$B$300,0)),"") | I11: =IFERROR(INDEX('Dr Umesh Choudhry'!$M$7:$M$300,MATCH($A11,'Dr Umesh Choudhry'!$B$7:$B$300,0)),"") | J11: =IFERROR(INDEX(DA!$M$7:$M$300,MATCH($A11,DA!$B$7:$B$300,0)),"") -> 392 | K11: Close 22.10.2026 (Screener.in) | L11: 359.9 | M11: =IF(AND(ISNUMBER(B11),ISNUMBER(L11),N(L11)>0),B11/L11-1,"") -> 0.0086135038
A12: Ashoka Buildcon Ltd | B12: 101.09 | C12: =IF(ISNUMBER(B12),B12,IF(ISNUMBER(E12),E12,IF(ISNUMBER(F12),F12,IF(ISNUMBER(G12),G12,IF(ISNUMBER(H12),H12,IF(ISNUMBER(I12),I12,IF(ISNUMBER(J12),J12,""))))))) -> 101.09 | D12: =IF(ISNUMBER(B12),IF(K12<>"",K12,"Manual override"),IF(ISNUMBER(E12),"Gautam stmt – 23.10",IF(ISNUMBER(F12),"Manish Shilpa stmt – live 23.10",IF(ISNUMBER(G12),"Saloni stmt – 20.10 (stale)",IF(ISNUMBER(H12),"Vidushi stmt – LTP 05.10",IF(ISNUMBER(I12),"Umesh stmt – NSE live 09.10",IF(ISNUMBER(J12),"DA stmt – older (stale)","No price on any statement"))))))) -> Close 22.10.2026 (Screener.in) | E12: =IFERROR(INDEX(Gautam!$M$7:$M$300,MATCH($A12,Gautam!$B$7:$B$300,0)),"") | F12: =IFERROR(INDEX('Manish Shilpa'!$M$7:$M$300,MATCH($A12,'Manish Shilpa'!$B$7:$B$300,0)),"") | G12: =IFERROR(INDEX('Saloni Mehra'!$M$7:$M$300,MATCH($A12,'Saloni Mehra'!$B$7:$B$300,0)),"") | H12: =IFERROR(INDEX('Vidushi Malhotra'!$M$7:$M$300,MATCH($A12,'Vidushi Malhotra'!$B$7:$B$300,0)),"") | I12: =IFERROR(INDEX('Dr Umesh Choudhry'!$M$7:$M$300,MATCH($A12,'Dr Umesh Choudhry'!$B$7:$B$300,0)),"") | J12: =IFERROR(INDEX(DA!$M$7:$M$300,MATCH($A12,DA!$B$7:$B$300,0)),"") -> 114 | K12: Close 22.10.2026 (Screener.in) | L12: 102.18 | M12: =IF(AND(ISNUMBER(B12),ISNUMBER(L12),N(L12)>0),B12/L12-1,"") -> -0.01066745
A13: Asian Paints Ltd | B13: 2284.8 | C13: =IF(ISNUMBER(B13),B13,IF(ISNUMBER(E13),E13,IF(ISNUMBER(F13),F13,IF(ISNUMBER(G13),G13,IF(ISNUMBER(H13),H13,IF(ISNUMBER(I13),I13,IF(ISNUMBER(J13),J13,""))))))) -> 2284.8 | D13: =IF(ISNUMBER(B13),IF(K13<>"",K13,"Manual override"),IF(ISNUMBER(E13),"Gautam stmt – 23.10",IF(ISNUMBER(F13),"Manish Shilpa stmt – live 23.10",IF(ISNUMBER(G13),"Saloni stmt – 20.10 (stale)",IF(ISNUMBER(H13),"Vidushi stmt – LTP 05.10",IF(ISNUMBER(I13),"Umesh stmt – NSE live 09.10",IF(ISNUMBER(J13),"DA stmt – older (stale)","No price on any statement"))))))) -> Close 22.10.2026 (Screener.in) | E13: =IFERROR(INDEX(Gautam!$M$7:$M$300,MATCH($A13,Gautam!$B$7:$B$300,0)),"") | F13: =IFERROR(INDEX('Manish Shilpa'!$M$7:$M$300,MATCH($A13,'Manish Shilpa'!$B$7:$B$300,0)),"") -> 2274.8182 | G13: =IFERROR(INDEX('Saloni Mehra'!$M$7:$M$300,MATCH($A13,'Saloni Mehra'!$B$7:$B$300,0)),"") | H13: =IFERROR(INDEX('Vidushi Malhotra'!$M$7:$M$300,MATCH($A13,'Vidushi Malhotra'!$B$7:$B$300,0)),"") | I13: =IFERROR(INDEX('Dr Umesh Choudhry'!$M$7:$M$300,MATCH($A13,'Dr Umesh Choudhry'!$B$7:$B$300,0)),"") | J13: =IFERROR(INDEX(DA!$M$7:$M$300,MATCH($A13,DA!$B$7:$B$300,0)),"") | K13: Close 22.10.2026 (Screener.in) | L13: 2319.4 | M13: =IF(AND(ISNUMBER(B13),ISNUMBER(L13),N(L13)>0),B13/L13-1,"") -> -0.014917651
A14: Astec LifeSciences Ltd | B14: 669.2 | C14: =IF(ISNUMBER(B14),B14,IF(ISNUMBER(E14),E14,IF(ISNUMBER(F14),F14,IF(ISNUMBER(G14),G14,IF(ISNUMBER(H14),H14,IF(ISNUMBER(I14),I14,IF(ISNUMBER(J14),J14,""))))))) -> 669.2 | D14: =IF(ISNUMBER(B14),IF(K14<>"",K14,"Manual override"),IF(ISNUMBER(E14),"Gautam stmt – 23.10",IF(ISNUMBER(F14),"Manish Shilpa stmt – live 23.10",IF(ISNUMBER(G14),"Saloni stmt – 20.10 (stale)",IF(ISNUMBER(H14),"Vidushi stmt – LTP 05.10",IF(ISNUMBER(I14),"Umesh stmt – NSE live 09.10",IF(ISNUMBER(J14),"DA stmt – older (stale)","No price on any statement"))))))) -> Close 22.10.2026 (Screener.in) | E14: =IFERROR(INDEX(Gautam!$M$7:$M$300,MATCH($A14,Gautam!$B$7:$B$300,0)),"") | F14: =IFERROR(INDEX('Manish Shilpa'!$M$7:$M$300,MATCH($A14,'Manish Shilpa'!$B$7:$B$300,0)),"") | G14: =IFERROR(INDEX('Saloni Mehra'!$M$7:$M$300,MATCH($A14,'Saloni Mehra'!$B$7:$B$300,0)),"") | H14: =IFERROR(INDEX('Vidushi Malhotra'!$M$7:$M$300,MATCH($A14,'Vidushi Malhotra'!$B$7:$B$300,0)),"") | I14: =IFERROR(INDEX('Dr Umesh Choudhry'!$M$7:$M$300,MATCH($A14,'Dr Umesh Choudhry'!$B$7:$B$300,0)),"") | J14: =IFERROR(INDEX(DA!$M$7:$M$300,MATCH($A14,DA!$B$7:$B$300,0)),"") -> 700 | K14: Close 22.10.2026 (Screener.in) | L14: 665.9 | M14: =IF(AND(ISNUMBER(B14),ISNUMBER(L14),N(L14)>0),B14/L14-1,"") -> 0.0049556991
A15: Avenue Supermarts (DMart) Ltd | B15: 3166 | C15: =IF(ISNUMBER(B15),B15,IF(ISNUMBER(E15),E15,IF(ISNUMBER(F15),F15,IF(ISNUMBER(G15),G15,IF(ISNUMBER(H15),H15,IF(ISNUMBER(I15),I15,IF(ISNUMBER(J15),J15,""))))))) -> 3166 | D15: =IF(ISNUMBER(B15),IF(K15<>"",K15,"Manual override"),IF(ISNUMBER(E15),"Gautam stmt – 23.10",IF(ISNUMBER(F15),"Manish Shilpa stmt – live 23.10",IF(ISNUMBER(G15),"Saloni stmt – 20.10 (stale)",IF(ISNUMBER(H15),"Vidushi stmt – LTP 05.10",IF(ISNUMBER(I15),"Umesh stmt – NSE live 09.10",IF(ISNUMBER(J15),"DA stmt – older (stale)","No price on any statement"))))))) -> Close 22.10.2026 (Screener.in) | E15: =IFERROR(INDEX(Gautam!$M$7:$M$300,MATCH($A15,Gautam!$B$7:$B$300,0)),"") -> 3166 | F15: =IFERROR(INDEX('Manish Shilpa'!$M$7:$M$300,MATCH($A15,'Manish Shilpa'!$B$7:$B$300,0)),"") -> 3126.3333 | G15: =IFERROR(INDEX('Saloni Mehra'!$M$7:$M$300,MATCH($A15,'Saloni Mehra'!$B$7:$B$300,0)),"") | H15: =IFERROR(INDEX('Vidushi Malhotra'!$M$7:$M$300,MATCH($A15,'Vidushi Malhotra'!$B$7:$B$300,0)),"") | I15: =IFERROR(INDEX('Dr Umesh Choudhry'!$M$7:$M$300,MATCH($A15,'Dr Umesh Choudhry'!$B$7:$B$300,0)),"") -> 3567.5 | J15: =IFERROR(INDEX(DA!$M$7:$M$300,MATCH($A15,DA!$B$7:$B$300,0)),"") -> 3688 | K15: Close 22.10.2026 (Screener.in) | L15: 3250.9 | M15: =IF(AND(ISNUMBER(B15),ISNUMBER(L15),N(L15)>0),B15/L15-1,"") -> -0.026115845
A16: Bagmane Prime Office REIT | B16: 105.54 | C16: =IF(ISNUMBER(B16),B16,IF(ISNUMBER(E16),E16,IF(ISNUMBER(F16),F16,IF(ISNUMBER(G16),G16,IF(ISNUMBER(H16),H16,IF(ISNUMBER(I16),I16,IF(ISNUMBER(J16),J16,""))))))) -> 105.54 | D16: =IF(ISNUMBER(B16),IF(K16<>"",K16,"Manual override"),IF(ISNUMBER(E16),"Gautam stmt – 23.10",IF(ISNUMBER(F16),"Manish Shilpa stmt – live 23.10",IF(ISNUMBER(G16),"Saloni stmt – 20.10 (stale)",IF(ISNUMBER(H16),"Vidushi stmt – LTP 05.10",IF(ISNUMBER(I16),"Umesh stmt – NSE live 09.10",IF(ISNUMBER(J16),"DA stmt – older (stale)","No price on any statement"))))))) -> Close 22.10.2026 (Screener.in) | E16: =IFERROR(INDEX(Gautam!$M$7:$M$300,MATCH($A16,Gautam!$B$7:$B$300,0)),"") -> 106 | F16: =IFERROR(INDEX('Manish Shilpa'!$M$7:$M$300,MATCH($A16,'Manish Shilpa'!$B$7:$B$300,0)),"") | G16: =IFERROR(INDEX('Saloni Mehra'!$M$7:$M$300,MATCH($A16,'Saloni Mehra'!$B$7:$B$300,0)),"") | H16: =IFERROR(INDEX('Vidushi Malhotra'!$M$7:$M$300,MATCH($A16,'Vidushi Malhotra'!$B$7:$B$300,0)),"") | I16: =IFERROR(INDEX('Dr Umesh Choudhry'!$M$7:$M$300,MATCH($A16,'Dr Umesh Choudhry'!$B$7:$B$300,0)),"") | J16: =IFERROR(INDEX(DA!$M$7:$M$300,MATCH($A16,DA!$B$7:$B$300,0)),"") | K16: Close 22.10.2026 (Screener.in) | L16: 105.53 | M16: =IF(AND(ISNUMBER(B16),ISNUMBER(L16),N(L16)>0),B16/L16-1,"") -> 9.4759784e-05
A17: Bajaj Finance Ltd | B17: 942.1 | C17: =IF(ISNUMBER(B17),B17,IF(ISNUMBER(E17),E17,IF(ISNUMBER(F17),F17,IF(ISNUMBER(G17),G17,IF(ISNUMBER(H17),H17,IF(ISNUMBER(I17),I17,IF(ISNUMBER(J17),J17,""))))))) -> 942.1 | D17: =IF(ISNUMBER(B17),IF(K17<>"",K17,"Manual override"),IF(ISNUMBER(E17),"Gautam stmt – 23.10",IF(ISNUMBER(F17),"Manish Shilpa stmt – live 23.10",IF(ISNUMBER(G17),"Saloni stmt – 20.10 (stale)",IF(ISNUMBER(H17),"Vidushi stmt – LTP 05.10",IF(ISNUMBER(I17),"Umesh stmt – NSE live 09.10",IF(ISNUMBER(J17),"DA stmt – older (stale)","No price on any statement"))))))) -> Close 22.10.2026 (Screener.in) | E17: =IFERROR(INDEX(Gautam!$M$7:$M$300,MATCH($A17,Gautam!$B$7:$B$300,0)),"") -> 938 | F17: =IFERROR(INDEX('Manish Shilpa'!$M$7:$M$300,MATCH($A17,'Manish Shilpa'!$B$7:$B$300,0)),"") -> 930.91142 | G17: =IFERROR(INDEX('Saloni Mehra'!$M$7:$M$300,MATCH($A17,'Saloni Mehra'!$B$7:$B$300,0)),"") | H17: =IFERROR(INDEX('Vidushi Malhotra'!$M$7:$M$300,MATCH($A17,'Vidushi Malhotra'!$B$7:$B$300,0)),"") -> 973.90083 | I17: =IFERROR(INDEX('Dr Umesh Choudhry'!$M$7:$M$300,MATCH($A17,'Dr Umesh Choudhry'!$B$7:$B$300,0)),"") -> 961.34992 | J17: =IFERROR(INDEX(DA!$M$7:$M$300,MATCH($A17,DA!$B$7:$B$300,0)),"") -> 1034 | K17: Close 22.10.2026 (Screener.in) | L17: 926 | M17: =IF(AND(ISNUMBER(B17),ISNUMBER(L17),N(L17)>0),B17/L17-1,"") -> 0.017386609
... A21: Capacite Infraprojects Ltd | B21: 154.93 | C21: =IF(ISNUMBER(B21),B21,IF(ISNUMBER(E21),E21,IF(ISNUMBER(F21),F21,IF(ISNUMBER(G21),G21,IF(ISNUMBER(H21),H21,IF(ISNUMBER(I21),I21,IF(ISNUMBER(J21),J21,""))))))) -> 154.93 | D21: =IF(ISNUMBER(B21),IF(K21<>"",K21,"Manual override"),IF(ISNUMBER(E21),"Gautam stmt – 23.10",IF(ISNUMBER(F21),"Manish Shilpa stmt – live 23.10",IF(ISNUMBER(G21),"Saloni stmt – 20.10 (stale)",IF(ISNUMBER(H21),"Vidushi stmt – LTP 05.10",IF(ISNUMBER(I21),"Umesh stmt – NSE live 09.10",IF(ISNUMBER(J21),"DA stmt – older (stale)","No price on any statement"))))))) -> Close 22.10.2026 (Screener.in) | E21: =IFERROR(INDEX(Gautam!$M$7:$M$300,MATCH($A21,Gautam!$B$7:$B$300,0)),"") | F21: =IFERROR(INDEX('Manish Shilpa'!$M$7:$M$300,MATCH($A21,'Manish Shilpa'!$B$7:$B$300,0)),"") | G21: =IFERROR(INDEX('Saloni Mehra'!$M$7:$M$300,MATCH($A21,'Saloni Mehra'!$B$7:$B$300,0)),"") | H21: =IFERROR(INDEX('Vidushi Malhotra'!$M$7:$M$300,MATCH($A21,'Vidushi Malhotra'!$B$7:$B$300,0)),"") | I21: =IFERROR(INDEX('Dr Umesh Choudhry'!$M$7:$M$300,MATCH($A21,'Dr Umesh Choudhry'!$B$7:$B$300,0)),"") | J21: =IFERROR(INDEX(DA!$M$7:$M$300,MATCH($A21,DA!$B$7:$B$300,0)),"") -> 192 | K21: Close 22.10.2026 (Screener.in) | L21: 161.42 | M21: =IF(AND(ISNUMBER(B21),ISNUMBER(L21),N(L21)>0),B21/L21-1,"") -> -0.040205675
A22: Cash – ICICI Direct | B22: 1 | C22: =IF(ISNUMBER(B22),B22,IF(ISNUMBER(E22),E22,IF(ISNUMBER(F22),F22,IF(ISNUMBER(G22),G22,IF(ISNUMBER(H22),H22,IF(ISNUMBER(I22),I22,IF(ISNUMBER(J22),J22,""))))))) -> 1 | D22: =IF(ISNUMBER(B22),IF(K22<>"",K22,"Manual override"),IF(ISNUMBER(E22),"Gautam stmt – 23.10",IF(ISNUMBER(F22),"Manish Shilpa stmt – live 23.10",IF(ISNUMBER(G22),"Saloni stmt – 20.10 (stale)",IF(ISNUMBER(H22),"Vidushi stmt – LTP 05.10",IF(ISNUMBER(I22),"Umesh stmt – NSE live 09.10",IF(ISNUMBER(J22),"DA stmt – older (stale)","No price on any statement"))))))) -> Cash at par (₹1) | E22: =IFERROR(INDEX(Gautam!$M$7:$M$300,MATCH($A22,Gautam!$B$7:$B$300,0)),"") | F22: =IFERROR(INDEX('Manish Shilpa'!$M$7:$M$300,MATCH($A22,'Manish Shilpa'!$B$7:$B$300,0)),"") | G22: =IFERROR(INDEX('Saloni Mehra'!$M$7:$M$300,MATCH($A22,'Saloni Mehra'!$B$7:$B$300,0)),"") | H22: =IFERROR(INDEX('Vidushi Malhotra'!$M$7:$M$300,MATCH($A22,'Vidushi Malhotra'!$B$7:$B$300,0)),"") | I22: =IFERROR(INDEX('Dr Umesh Choudhry'!$M$7:$M$300,MATCH($A22,'Dr Umesh Choudhry'!$B$7:$B$300,0)),"") -> 1 | J22: =IFERROR(INDEX(DA!$M$7:$M$300,MATCH($A22,DA!$B$7:$B$300,0)),"") | K22: Cash at par (₹1) | M22: =IF(AND(ISNUMBER(B22),ISNUMBER(L22),N(L22)>0),B22/L22-1,"")
A23: Central Depository Services (India) Ltd | B23: 1225 | C23: =IF(ISNUMBER(B23),B23,IF(ISNUMBER(E23),E23,IF(ISNUMBER(F23),F23,IF(ISNUMBER(G23),G23,IF(ISNUMBER(H23),H23,IF(ISNUMBER(I23),I23,IF(ISNUMBER(J23),J23,""))))))) -> 1225 | D23: =IF(ISNUMBER(B23),IF(K23<>"",K23,"Manual override"),IF(ISNUMBER(E23),"Gautam stmt – 23.10",IF(ISNUMBER(F23),"Manish Shilpa stmt – live 23.10",IF(ISNUMBER(G23),"Saloni stmt – 20.10 (stale)",IF(ISNUMBER(H23),"Vidushi stmt – LTP 05.10",IF(ISNUMBER(I23),"Umesh stmt – NSE live 09.10",IF(ISNUMBER(J23),"DA stmt – older (stale)","No price on any statement"))))))) -> Close 22.10.2026 (Screener.in) | E23: =IFERROR(INDEX(Gautam!$M$7:$M$300,MATCH($A23,Gautam!$B$7:$B$300,0)),"") | F23: =IFERROR(INDEX('Manish Shilpa'!$M$7:$M$300,MATCH($A23,'Manish Shilpa'!$B$7:$B$300,0)),"") -> 1183.903 | G23: =IFERROR(INDEX('Saloni Mehra'!$M$7:$M$300,MATCH($A23,'Saloni Mehra'!$B$7:$B$300,0)),"") | H23: =IFERROR(INDEX('Vidushi Malhotra'!$M$7:$M$300,MATCH($A23,'Vidushi Malhotra'!$B$7:$B$300,0)),"") | I23: =IFERROR(INDEX('Dr Umesh Choudhry'!$M$7:$M$300,MATCH($A23,'Dr Umesh Choudhry'!$B$7:$B$300,0)),"") | J23: =IFERROR(INDEX(DA!$M$7:$M$300,MATCH($A23,DA!$B$7:$B$300,0)),"") | K23: Close 22.10.2026 (Screener.in) | L23: 1237.2 | M23: =IF(AND(ISNUMBER(B23),ISNUMBER(L23),N(L23)>0),B23/L23-1,"") -> -0.0098609764
A24: Clean Science and Technology Ltd | B24: 748.05 | C24: =IF(ISNUMBER(B24),B24,IF(ISNUMBER(E24),E24,IF(ISNUMBER(F24),F24,IF(ISNUMBER(G24),G24,IF(ISNUMBER(H24),H24,IF(ISNUMBER(I24),I24,IF(ISNUMBER(J24),J24,""))))))) -> 748.05 | D24: =IF(ISNUMBER(B24),IF(K24<>"",K24,"Manual override"),IF(ISNUMBER(E24),"Gautam stmt – 23.10",IF(ISNUMBER(F24),"Manish Shilpa stmt – live 23.10",IF(ISNUMBER(G24),"Saloni stmt – 20.10 (stale)",IF(ISNUMBER(H24),"Vidushi stmt – LTP 05.10",IF(ISNUMBER(I24),"Umesh stmt – NSE live 09.10",IF(ISNUMBER(J24),"DA stmt – older (stale)","No price on any statement"))))))) -> Close 22.10.2026 (Screener.in) | E24: =IFERROR(INDEX(Gautam!$M$7:$M$300,MATCH($A24,Gautam!$B$7:$B$300,0)),"") | F24: =IFERROR(INDEX('Manish Shilpa'!$M$7:$M$300,MATCH($A24,'Manish Shilpa'!$B$7:$B$300,0)),"") -> 726.28571 | G24: =IFERROR(INDEX('Saloni Mehra'!$M$7:$M$300,MATCH($A24,'Saloni Mehra'!$B$7:$B$300,0)),"") | H24: =IFERROR(INDEX('Vidushi Malhotra'!$M$7:$M$300,MATCH($A24,'Vidushi Malhotra'!$B$7:$B$300,0)),"") | I24: =IFERROR(INDEX('Dr Umesh Choudhry'!$M$7:$M$300,MATCH($A24,'Dr Umesh Choudhry'!$B$7:$B$300,0)),"") | J24: =IFERROR(INDEX(DA!$M$7:$M$300,MATCH($A24,DA!$B$7:$B$300,0)),"") | K24: Close 22.10.2026 (Screener.in) | L24: 741.1 | M24: =IF(AND(ISNUMBER(B24),ISNUMBER(L24),N(L24)>0),B24/L24-1,"") -> 0.0093779517
A25: Connplex Cinemas Ltd | B25: 234.25 | C25: =IF(ISNUMBER(B25),B25,IF(ISNUMBER(E25),E25,IF(ISNUMBER(F25),F25,IF(ISNUMBER(G25),G25,IF(ISNUMBER(H25),H25,IF(ISNUMBER(I25),I25,IF(ISNUMBER(J25),J25,""))))))) -> 234.25 | D25: =IF(ISNUMBER(B25),IF(K25<>"",K25,"Manual override"),IF(ISNUMBER(E25),"Gautam stmt – 23.10",IF(ISNUMBER(F25),"Manish Shilpa stmt – live 23.10",IF(ISNUMBER(G25),"Saloni stmt – 20.10 (stale)",IF(ISNUMBER(H25),"Vidushi stmt – LTP 05.10",IF(ISNUMBER(I25),"Umesh stmt – NSE live 09.10",IF(ISNUMBER(J25),"DA stmt – older (stale)","No price on any statement"))))))) -> Close 22.10.2026 (Screener.in) | E25: =IFERROR(INDEX(Gautam!$M$7:$M$300,MATCH($A25,Gautam!$B$7:$B$300,0)),"") -> 240 | F25: =IFERROR(INDEX('Manish Shilpa'!$M$7:$M$300,MATCH($A25,'Manish Shilpa'!$B$7:$B$300,0)),"") -> 219 | G25: =IFERROR(INDEX('Saloni Mehra'!$M$7:$M$300,MATCH($A25,'Saloni Mehra'!$B$7:$B$300,0)),"") -> 248 | H25: =IFERROR(INDEX('Vidushi Malhotra'!$M$7:$M$300,MATCH($A25,'Vidushi Malhotra'!$B$7:$B$300,0)),"") | I25: =IFERROR(INDEX('Dr Umesh Choudhry'!$M$7:$M$300,MATCH($A25,'Dr Umesh Choudhry'!$B$7:$B$300,0)),"") -> 245 | J25: =IFERROR(INDEX(DA!$M$7:$M$300,MATCH($A25,DA!$B$7:$B$300,0)),"") -> 265 | K25: Close 22.10.2026 (Screener.in) | L25: 239.7 | M25: =IF(AND(ISNUMBER(B25),ISNUMBER(L25),N(L25)>0),B25/L25-1,"") -> -0.022736754
A26: Cyient Ltd | B26: 1143.7 | C26: =IF(ISNUMBER(B26),B26,IF(ISNUMBER(E26),E26,IF(ISNUMBER(F26),F26,IF(ISNUMBER(G26),G26,IF(ISNUMBER(H26),H26,IF(ISNUMBER(I26),I26,IF(ISNUMBER(J26),J26,""))))))) -> 1143.7 | D26: =IF(ISNUMBER(B26),IF(K26<>"",K26,"Manual override"),IF(ISNUMBER(E26),"Gautam stmt – 23.10",IF(ISNUMBER(F26),"Manish Shilpa stmt – live 23.10",IF(ISNUMBER(G26),"Saloni stmt – 20.10 (stale)",IF(ISNUMBER(H26),"Vidushi stmt – LTP 05.10",IF(ISNUMBER(I26),"Umesh stmt – NSE live 09.10",IF(ISNUMBER(J26),"DA stmt – older (stale)","No price on any statement"))))))) -> Close 22.10.2026 (Screener.in) | E26: =IFERROR(INDEX(Gautam!$M$7:$M$300,MATCH($A26,Gautam!$B$7:$B$300,0)),"") | F26: =IFERROR(INDEX('Manish Shilpa'!$M$7:$M$300,MATCH($A26,'Manish Shilpa'!$B$7:$B$300,0)),"") | G26: =IFERROR(INDEX('Saloni Mehra'!$M$7:$M$300,MATCH($A26,'Saloni Mehra'!$B$7:$B$300,0)),"") | H26: =IFERROR(INDEX('Vidushi Malhotra'!$M$7:$M$300,MATCH($A26,'Vidushi Malhotra'!$B$7:$B$300,0)),"") | I26: =IFERROR(INDEX('Dr Umesh Choudhry'!$M$7:$M$300,MATCH($A26,'Dr Umesh Choudhry'!$B$7:$B$300,0)),"") | J26: =IFERROR(INDEX(DA!$M$7:$M$300,MATCH($A26,DA!$B$7:$B$300,0)),"") -> 1059 | K26: Close 22.10.2026 (Screener.in) | L26: 1169.7 | M26: =IF(AND(ISNUMBER(B26),ISNUMBER(L26),N(L26)>0),B26/L26-1,"") -> -0.022227922
A27: Deepak Nitrite Ltd | B27: 1487.4 | C27: =IF(ISNUMBER(B27),B27,IF(ISNUMBER(E27),E27,IF(ISNUMBER(F27),F27,IF(ISNUMBER(G27),G27,IF(ISNUMBER(H27),H27,IF(ISNUMBER(I27),I27,IF(ISNUMBER(J27),J27,""))))))) -> 1487.4 | D27: =IF(ISNUMBER(B27),IF(K27<>"",K27,"Manual override"),IF(ISNUMBER(E27),"Gautam stmt – 23.10",IF(ISNUMBER(F27),"Manish Shilpa stmt – live 23.10",IF(ISNUMBER(G27),"Saloni stmt – 20.10 (stale)",IF(ISNUMBER(H27),"Vidushi stmt – LTP 05.10",IF(ISNUMBER(I27),"Umesh stmt – NSE live 09.10",IF(ISNUMBER(J27),"DA stmt – older (stale)","No price on any statement"))))))) -> Close 22.10.2026 (Screener.in) | E27: =IFERROR(INDEX(Gautam!$M$7:$M$300,MATCH($A27,Gautam!$B$7:$B$300,0)),"") | F27: =IFERROR(INDEX('Manish Shilpa'!$M$7:$M$300,MATCH($A27,'Manish Shilpa'!$B$7:$B$300,0)),"") -> 1427 | G27: =IFERROR(INDEX('Saloni Mehra'!$M$7:$M$300,MATCH($A27,'Saloni Mehra'!$B$7:$B$300,0)),"") | H27: =IFERROR(INDEX('Vidushi Malhotra'!$M$7:$M$300,MATCH($A27,'Vidushi Malhotra'!$B$7:$B$300,0)),"") | I27: =IFERROR(INDEX('Dr Umesh Choudhry'!$M$7:$M$300,MATCH($A27,'Dr Umesh Choudhry'!$B$7:$B$300,0)),"") | J27: =IFERROR(INDEX(DA!$M$7:$M$300,MATCH($A27,DA!$B$7:$B$300,0)),"") | K27: Close 22.10.2026 (Screener.in) | L27: 1506.2 | M27: =IF(AND(ISNUMBER(B27),ISNUMBER(L27),N(L27)>0),B27/L27-1,"") -> -0.012481742
A28: Dr Lal PathLabs Ltd | B28: 1843.7 | C28: =IF(ISNUMBER(B28),B28,IF(ISNUMBER(E28),E28,IF(ISNUMBER(F28),F28,IF(ISNUMBER(G28),G28,IF(ISNUMBER(H28),H28,IF(ISNUMBER(I28),I28,IF(ISNUMBER(J28),J28,""))))))) -> 1843.7 | D28: =IF(ISNUMBER(B28),IF(K28<>"",K28,"Manual override"),IF(ISNUMBER(E28),"Gautam stmt – 23.10",IF(ISNUMBER(F28),"Manish Shilpa stmt – live 23.10",IF(ISNUMBER(G28),"Saloni stmt – 20.10 (stale)",IF(ISNUMBER(H28),"Vidushi stmt – LTP 05.10",IF(ISNUMBER(I28),"Umesh stmt – NSE live 09.10",IF(ISNUMBER(J28),"DA stmt – older (stale)","No price on any statement"))))))) -> Close 22.10.2026 (Screener.in) | E28: =IFERROR(INDEX(Gautam!$M$7:$M$300,MATCH($A28,Gautam!$B$7:$B$300,0)),"") | F28: =IFERROR(INDEX('Manish Shilpa'!$M$7:$M$300,MATCH($A28,'Manish Shilpa'!$B$7:$B$300,0)),"") -> 1825.2955 | G28: =IFERROR(INDEX('Saloni Mehra'!$M$7:$M$300,MATCH($A28,'Saloni Mehra'!$B$7:$B$300,0)),"") | H28: =IFERROR(INDEX('Vidushi Malhotra'!$M$7:$M$300,MATCH($A28,'Vidushi Malhotra'!$B$7:$B$300,0)),"") | I28: =IFERROR(INDEX('Dr Umesh Choudhry'!$M$7:$M$300,MATCH($A28,'Dr Umesh Choudhry'!$B$7:$B$300,0)),"") | J28: =IFERROR(INDEX(DA!$M$7:$M$300,MATCH($A28,DA!$B$7:$B$300,0)),"") | K28: Close 22.10.2026 (Screener.in) | L28: 1836.1 | M28: =IF(AND(ISNUMBER(B28),ISNUMBER(L28),N(L28)>0),B28/L28-1,"") -> 0.0041392081
A29: Eicher Motors Ltd | B29: 7084.5 | C29: =IF(ISNUMBER(B29),B29,IF(ISNUMBER(E29),E29,IF(ISNUMBER(F29),F29,IF(ISNUMBER(G29),G29,IF(ISNUMBER(H29),H29,IF(ISNUMBER(I29),I29,IF(ISNUMBER(J29),J29,""))))))) -> 7084.5 | D29: =IF(ISNUMBER(B29),IF(K29<>"",K29,"Manual override"),IF(ISNUMBER(E29),"Gautam stmt – 23.10",IF(ISNUMBER(F29),"Manish Shilpa stmt – live 23.10",IF(ISNUMBER(G29),"Saloni stmt – 20.10 (stale)",IF(ISNUMBER(H29),"Vidushi stmt – LTP 05.10",IF(ISNUMBER(I29),"Umesh stmt – NSE live 09.10",IF(ISNUMBER(J29),"DA stmt – older (stale)","No price on any statement"))))))) -> Close 22.10.2026 (Screener.in) | E29: =IFERROR(INDEX(Gautam!$M$7:$M$300,MATCH($A29,Gautam!$B$7:$B$300,0)),"") -> 7084 | F29: =IFERROR(INDEX('Manish Shilpa'!$M$7:$M$300,MATCH($A29,'Manish Shilpa'!$B$7:$B$300,0)),"") -> 6960 | G29: =IFERROR(INDEX('Saloni Mehra'!$M$7:$M$300,MATCH($A29,'Saloni Mehra'!$B$7:$B$300,0)),"") | H29: =IFERROR(INDEX('Vidushi Malhotra'!$M$7:$M$300,MATCH($A29,'Vidushi Malhotra'!$B$7:$B$300,0)),"") | I29: =IFERROR(INDEX('Dr Umesh Choudhry'!$M$7:$M$300,MATCH($A29,'Dr Umesh Choudhry'!$B$7:$B$300,0)),"") -> 6935 | J29: =IFERROR(INDEX(DA!$M$7:$M$300,MATCH($A29,DA!$B$7:$B$300,0)),"") -> 7530 | K29: Close 22.10.2026 (Screener.in) | L29: 7170.5 | M29: =IF(AND(ISNUMBER(B29),ISNUMBER(L29),N(L29)>0),B29/L29-1,"") -> -0.011993585
A30: Eternal Ltd | B30: 304.45 | C30: =IF(ISNUMBER(B30),B30,IF(ISNUMBER(E30),E30,IF(ISNUMBER(F30),F30,IF(ISNUMBER(G30),G30,IF(ISNUMBER(H30),H30,IF(ISNUMBER(I30),I30,IF(ISNUMBER(J30),J30,""))))))) -> 304.45 | D30: =IF(ISNUMBER(B30),IF(K30<>"",K30,"Manual override"),IF(ISNUMBER(E30),"Gautam stmt – 23.10",IF(ISNUMBER(F30),"Manish Shilpa stmt – live 23.10",IF(ISNUMBER(G30),"Saloni stmt – 20.10 (stale)",IF(ISNUMBER(H30),"Vidushi stmt – LTP 05.10",IF(ISNUMBER(I30),"Umesh stmt – NSE live 09.10",IF(ISNUMBER(J30),"DA stmt – older (stale)","No price on any statement"))))))) -> Close 22.10.2026 (Screener.in) | E30: =IFERROR(INDEX(Gautam!$M$7:$M$300,MATCH($A30,Gautam!$B$7:$B$300,0)),"") | F30: =IFERROR(INDEX('Manish Shilpa'!$M$7:$M$300,MATCH($A30,'Manish Shilpa'!$B$7:$B$300,0)),"") -> 306.20588 | G30: =IFERROR(INDEX('Saloni Mehra'!$M$7:$M$300,MATCH($A30,'Saloni Mehra'!$B$7:$B$300,0)),"") | H30: =IFERROR(INDEX('Vidushi Malhotra'!$M$7:$M$300,MATCH($A30,'Vidushi Malhotra'!$B$7:$B$300,0)),"") | I30: =IFERROR(INDEX('Dr Umesh Choudhry'!$M$7:$M$300,MATCH($A30,'Dr Umesh Choudhry'!$B$7:$B$300,0)),"") | J30: =IFERROR(INDEX(DA!$M$7:$M$300,MATCH($A30,DA!$B$7:$B$300,0)),"") | K30: Close 22.10.2026 (Screener.in) | L30: 312.35 | M30: =IF(AND(ISNUMBER(B30),ISNUMBER(L30),N(L30)>0),B30/L30-1,"") -> -0.02529214
A31: Eureka Forbes Ltd | B31: 316.8 | C31: =IF(ISNUMBER(B31),B31,IF(ISNUMBER(E31),E31,IF(ISNUMBER(F31),F31,IF(ISNUMBER(G31),G31,IF(ISNUMBER(H31),H31,IF(ISNUMBER(I31),I31,IF(ISNUMBER(J31),J31,""))))))) -> 316.8 | D31: =IF(ISNUMBER(B31),IF(K31<>"",K31,"Manual override"),IF(ISNUMBER(E31),"Gautam stmt – 23.10",IF(ISNUMBER(F31),"Manish Shilpa stmt – live 23.10",IF(ISNUMBER(G31),"Saloni stmt – 20.10 (stale)",IF(ISNUMBER(H31),"Vidushi stmt – LTP 05.10",IF(ISNUMBER(I31),"Umesh stmt – NSE live 09.10",IF(ISNUMBER(J31),"DA stmt – older (stale)","No price on any statement"))))))) -> Close 22.10.2026 (Screener.in) | E31: =IFERROR(INDEX(Gautam!$M$7:$M$300,MATCH($A31,Gautam!$B$7:$B$300,0)),"") | F31: =IFERROR(INDEX('Manish Shilpa'!$M$7:$M$300,MATCH($A31,'Manish Shilpa'!$B$7:$B$300,0)),"") -> 307.05714 | G31: =IFERROR(INDEX('Saloni Mehra'!$M$7:$M$300,MATCH($A31,'Saloni Mehra'!$B$7:$B$300,0)),"") | H31: =IFERROR(INDEX('Vidushi Malhotra'!$M$7:$M$300,MATCH($A31,'Vidushi Malhotra'!$B$7:$B$300,0)),"") | I31: =IFERROR(INDEX('Dr Umesh Choudhry'!$M$7:$M$300,MATCH($A31,'Dr Umesh Choudhry'!$B$7:$B$300,0)),"") | J31: =IFERROR(INDEX(DA!$M$7:$M$300,MATCH($A31,DA!$B$7:$B$300,0)),"") | K31: Close 22.10.2026 (Screener.in) | L31: 326.15 | M31: =IF(AND(ISNUMBER(B31),ISNUMBER(L31),N(L31)>0),B31/L31-1,"") -> -0.028667791
A32: Fineotex Chemical Ltd | B32: 51.55 | C32: =IF(ISNUMBER(B32),B32,IF(ISNUMBER(E32),E32,IF(ISNUMBER(F32),F32,IF(ISNUMBER(G32),G32,IF(ISNUMBER(H32),H32,IF(ISNUMBER(I32),I32,IF(ISNUMBER(J32),J32,""))))))) -> 51.55 | D32: =IF(ISNUMBER(B32),IF(K32<>"",K32,"Manual override"),IF(ISNUMBER(E32),"Gautam stmt – 23.10",IF(ISNUMBER(F32),"Manish Shilpa stmt – live 23.10",IF(ISNUMBER(G32),"Saloni stmt – 20.10 (stale)",IF(ISNUMBER(H32),"Vidushi stmt – LTP 05.10",IF(ISNUMBER(I32),"Umesh stmt – NSE live 09.10",IF(ISNUMBER(J32),"DA stmt – older (stale)","No price on any statement"))))))) -> Close 22.10.2026 (Screener.in) | E32: =IFERROR(INDEX(Gautam!$M$7:$M$300,MATCH($A32,Gautam!$B$7:$B$300,0)),"") -> 52.5 | F32: =IFERROR(INDEX('Manish Shilpa'!$M$7:$M$300,MATCH($A32,'Manish Shilpa'!$B$7:$B$300,0)),"") -> 47.93 | G32: =IFERROR(INDEX('Saloni Mehra'!$M$7:$M$300,MATCH($A32,'Saloni Mehra'!$B$7:$B$300,0)),"") -> 55.809938 | H32: =IFERROR(INDEX('Vidushi Malhotra'!$M$7:$M$300,MATCH($A32,'Vidushi Malhotra'!$B$7:$B$300,0)),"") -> 54.22 | I32: =IFERROR(INDEX('Dr Umesh Choudhry'!$M$7:$M$300,MATCH($A32,'Dr Umesh Choudhry'!$B$7:$B$300,0)),"") -> 56.329958 | J32: =IFERROR(INDEX(DA!$M$7:$M$300,MATCH($A32,DA!$B$7:$B$300,0)),"") -> 57.7 | K32: Close 22.10.2026 (Screener.in) | L32: 52.73 | M32: =IF(AND(ISNUMBER(B32),ISNUMBER(L32),N(L32)>0),B32/L32-1,"") -> -0.022378153
A33: Garware Technical Fibres Ltd | B33: 749.6 | C33: =IF(ISNUMBER(B33),B33,IF(ISNUMBER(E33),E33,IF(ISNUMBER(F33),F33,IF(ISNUMBER(G33),G33,IF(ISNUMBER(H33),H33,IF(ISNUMBER(I33),I33,IF(ISNUMBER(J33),J33,""))))))) -> 749.6 | D33: =IF(ISNUMBER(B33),IF(K33<>"",K33,"Manual override"),IF(ISNUMBER(E33),"Gautam stmt – 23.10",IF(ISNUMBER(F33),"Manish Shilpa stmt – live 23.10",IF(ISNUMBER(G33),"Saloni stmt – 20.10 (stale)",IF(ISNUMBER(H33),"Vidushi stmt – LTP 05.10",IF(ISNUMBER(I33),"Umesh stmt – NSE live 09.10",IF(ISNUMBER(J33),"DA stmt – older (stale)","No price on any statement"))))))) -> Close 22.10.2026 (Screener.in) | E33: =IFERROR(INDEX(Gautam!$M$7:$M$300,MATCH($A33,Gautam!$B$7:$B$300,0)),"") | F33: =IFERROR(INDEX('Manish Shilpa'!$M$7:$M$300,MATCH($A33,'Manish Shilpa'!$B$7:$B$300,0)),"") -> 721.2 | G33: =IFERROR(INDEX('Saloni Mehra'!$M$7:$M$300,MATCH($A33,'Saloni Mehra'!$B$7:$B$300,0)),"") | H33: =IFERROR(INDEX('Vidushi Malhotra'!$M$7:$M$300,MATCH($A33,'Vidushi Malhotra'!$B$7:$B$300,0)),"") | I33: =IFERROR(INDEX('Dr Umesh Choudhry'!$M$7:$M$300,MATCH($A33,'Dr Umesh Choudhry'!$B$7:$B$300,0)),"") | J33: =IFERROR(INDEX(DA!$M$7:$M$300,MATCH($A33,DA!$B$7:$B$300,0)),"") | K33: Close 22.10.2026 (Screener.in) | L33: 740.7 | M33: =IF(AND(ISNUMBER(B33),ISNUMBER(L33),N(L33)>0),B33/L33-1,"") -> 0.012015661
A34: GFL Ltd | B34: 54.58 | C34: =IF(ISNUMBER(B34),B34,IF(ISNUMBER(E34),E34,IF(ISNUMBER(F34),F34,IF(ISNUMBER(G34),G34,IF(ISNUMBER(H34),H34,IF(ISNUMBER(I34),I34,IF(ISNUMBER(J34),J34,""))))))) -> 54.58 | D34: =IF(ISNUMBER(B34),IF(K34<>"",K34,"Manual override"),IF(ISNUMBER(E34),"Gautam stmt – 23.10",IF(ISNUMBER(F34),"Manish Shilpa stmt – live 23.10",IF(ISNUMBER(G34),"Saloni stmt – 20.10 (stale)",IF(ISNUMBER(H34),"Vidushi stmt – LTP 05.10",IF(ISNUMBER(I34),"Umesh stmt – NSE live 09.10",IF(ISNUMBER(J34),"DA stmt – older (stale)","No price on any statement"))))))) -> Close 22.10.2026 (Screener.in) | E34: =IFERROR(INDEX(Gautam!$M$7:$M$300,MATCH($A34,Gautam!$B$7:$B$300,0)),"") | F34: =IFERROR(INDEX('Manish Shilpa'!$M$7:$M$300,MATCH($A34,'Manish Shilpa'!$B$7:$B$300,0)),"") | G34: =IFERROR(INDEX('Saloni Mehra'!$M$7:$M$300,MATCH($A34,'Saloni Mehra'!$B$7:$B$300,0)),"") | H34: =IFERROR(INDEX('Vidushi Malhotra'!$M$7:$M$300,MATCH($A34,'Vidushi Malhotra'!$B$7:$B$300,0)),"") | I34: =IFERROR(INDEX('Dr Umesh Choudhry'!$M$7:$M$300,MATCH($A34,'Dr Umesh Choudhry'!$B$7:$B$300,0)),"") | J34: =IFERROR(INDEX(DA!$M$7:$M$300,MATCH($A34,DA!$B$7:$B$300,0)),"") -> 58 | K34: Close 22.10.2026 (Screener.in) | L34: 55.21 | M34: =IF(AND(ISNUMBER(B34),ISNUMBER(L34),N(L34)>0),B34/L34-1,"") -> -0.011410976
... A39: HDFC Bank Ltd | B39: 694.05 | C39: =IF(ISNUMBER(B39),B39,IF(ISNUMBER(E39),E39,IF(ISNUMBER(F39),F39,IF(ISNUMBER(G39),G39,IF(ISNUMBER(H39),H39,IF(ISNUMBER(I39),I39,IF(ISNUMBER(J39),J39,""))))))) -> 694.05 | D39: =IF(ISNUMBER(B39),IF(K39<>"",K39,"Manual override"),IF(ISNUMBER(E39),"Gautam stmt – 23.10",IF(ISNUMBER(F39),"Manish Shilpa stmt – live 23.10",IF(ISNUMBER(G39),"Saloni stmt – 20.10 (stale)",IF(ISNUMBER(H39),"Vidushi stmt – LTP 05.10",IF(ISNUMBER(I39),"Umesh stmt – NSE live 09.10",IF(ISNUMBER(J39),"DA stmt – older (stale)","No price on any statement"))))))) -> Close 22.10.2026 (Screener.in) | E39: =IFERROR(INDEX(Gautam!$M$7:$M$300,MATCH($A39,Gautam!$B$7:$B$300,0)),"") -> 694 | F39: =IFERROR(INDEX('Manish Shilpa'!$M$7:$M$300,MATCH($A39,'Manish Shilpa'!$B$7:$B$300,0)),"") -> 688.98618 | G39: =IFERROR(INDEX('Saloni Mehra'!$M$7:$M$300,MATCH($A39,'Saloni Mehra'!$B$7:$B$300,0)),"") | H39: =IFERROR(INDEX('Vidushi Malhotra'!$M$7:$M$300,MATCH($A39,'Vidushi Malhotra'!$B$7:$B$300,0)),"") -> 707.7619 | I39: =IFERROR(INDEX('Dr Umesh Choudhry'!$M$7:$M$300,MATCH($A39,'Dr Umesh Choudhry'!$B$7:$B$300,0)),"") -> 702.15007 | J39: =IFERROR(INDEX(DA!$M$7:$M$300,MATCH($A39,DA!$B$7:$B$300,0)),"") -> 708 | K39: Close 22.10.2026 (Screener.in) | L39: 706.95 | M39: =IF(AND(ISNUMBER(B39),ISNUMBER(L39),N(L39)>0),B39/L39-1,"") -> -0.018247401
A40: HDFC Gold ETF | C40: =IF(ISNUMBER(B40),B40,IF(ISNUMBER(E40),E40,IF(ISNUMBER(F40),F40,IF(ISNUMBER(G40),G40,IF(ISNUMBER(H40),H40,IF(ISNUMBER(I40),I40,IF(ISNUMBER(J40),J40,""))))))) -> 127 | D40: =IF(ISNUMBER(B40),IF(K40<>"",K40,"Manual override"),IF(ISNUMBER(E40),"Gautam stmt – 23.10",IF(ISNUMBER(F40),"Manish Shilpa stmt – live 23.10",IF(ISNUMBER(G40),"Saloni stmt – 20.10 (stale)",IF(ISNUMBER(H40),"Vidushi stmt – LTP 05.10",IF(ISNUMBER(I40),"Umesh stmt – NSE live 09.10",IF(ISNUMBER(J40),"DA stmt – older (stale)","No price on any statement"))))))) -> Gautam stmt – 23.10 | E40: =IFERROR(INDEX(Gautam!$M$7:$M$300,MATCH($A40,Gautam!$B$7:$B$300,0)),"") -> 127 | F40: =IFERROR(INDEX('Manish Shilpa'!$M$7:$M$300,MATCH($A40,'Manish Shilpa'!$B$7:$B$300,0)),"") -> 119.82738 | G40: =IFERROR(INDEX('Saloni Mehra'!$M$7:$M$300,MATCH($A40,'Saloni Mehra'!$B$7:$B$300,0)),"") -> 123.90909 | H40: =IFERROR(INDEX('Vidushi Malhotra'!$M$7:$M$300,MATCH($A40,'Vidushi Malhotra'!$B$7:$B$300,0)),"") | I40: =IFERROR(INDEX('Dr Umesh Choudhry'!$M$7:$M$300,MATCH($A40,'Dr Umesh Choudhry'!$B$7:$B$300,0)),"") | J40: =IFERROR(INDEX(DA!$M$7:$M$300,MATCH($A40,DA!$B$7:$B$300,0)),"") -> 129 | K40: No exchange close found – statement price used | M40: =IF(AND(ISNUMBER(B40),ISNUMBER(L40),N(L40)>0),B40/L40-1,"")
A41: HUDCO Ltd | B41: 151.77 | C41: =IF(ISNUMBER(B41),B41,IF(ISNUMBER(E41),E41,IF(ISNUMBER(F41),F41,IF(ISNUMBER(G41),G41,IF(ISNUMBER(H41),H41,IF(ISNUMBER(I41),I41,IF(ISNUMBER(J41),J41,""))))))) -> 151.77 | D41: =IF(ISNUMBER(B41),IF(K41<>"",K41,"Manual override"),IF(ISNUMBER(E41),"Gautam stmt – 23.10",IF(ISNUMBER(F41),"Manish Shilpa stmt – live 23.10",IF(ISNUMBER(G41),"Saloni stmt – 20.10 (stale)",IF(ISNUMBER(H41),"Vidushi stmt – LTP 05.10",IF(ISNUMBER(I41),"Umesh stmt – NSE live 09.10",IF(ISNUMBER(J41),"DA stmt – older (stale)","No price on any statement"))))))) -> Close 22.10.2026 (Screener.in) | E41: =IFERROR(INDEX(Gautam!$M$7:$M$300,MATCH($A41,Gautam!$B$7:$B$300,0)),"") | F41: =IFERROR(INDEX('Manish Shilpa'!$M$7:$M$300,MATCH($A41,'Manish Shilpa'!$B$7:$B$300,0)),"") | G41: =IFERROR(INDEX('Saloni Mehra'!$M$7:$M$300,MATCH($A41,'Saloni Mehra'!$B$7:$B$300,0)),"") | H41: =IFERROR(INDEX('Vidushi Malhotra'!$M$7:$M$300,MATCH($A41,'Vidushi Malhotra'!$B$7:$B$300,0)),"") | I41: =IFERROR(INDEX('Dr Umesh Choudhry'!$M$7:$M$300,MATCH($A41,'Dr Umesh Choudhry'!$B$7:$B$300,0)),"") | J41: =IFERROR(INDEX(DA!$M$7:$M$300,MATCH($A41,DA!$B$7:$B$300,0)),"") -> 173 | K41: Close 22.10.2026 (Screener.in) | L41: 154.34 | M41: =IF(AND(ISNUMBER(B41),ISNUMBER(L41),N(L41)>0),B41/L41-1,"") -> -0.016651549
A42: ICICI Prudential Life Insurance Co Ltd | B42: 431 | C42: =IF(ISNUMBER(B42),B42,IF(ISNUMBER(E42),E42,IF(ISNUMBER(F42),F42,IF(ISNUMBER(G42),G42,IF(ISNUMBER(H42),H42,IF(ISNUMBER(I42),I42,IF(ISNUMBER(J42),J42,""))))))) -> 431 | D42: =IF(ISNUMBER(B42),IF(K42<>"",K42,"Manual override"),IF(ISNUMBER(E42),"Gautam stmt – 23.10",IF(ISNUMBER(F42),"Manish Shilpa stmt – live 23.10",IF(ISNUMBER(G42),"Saloni stmt – 20.10 (stale)",IF(ISNUMBER(H42),"Vidushi stmt – LTP 05.10",IF(ISNUMBER(I42),"Umesh stmt – NSE live 09.10",IF(ISNUMBER(J42),"DA stmt – older (stale)","No price on any statement"))))))) -> Close 22.10.2026 (Screener.in) | E42: =IFERROR(INDEX(Gautam!$M$7:$M$300,MATCH($A42,Gautam!$B$7:$B$300,0)),"") | F42: =IFERROR(INDEX('Manish Shilpa'!$M$7:$M$300,MATCH($A42,'Manish Shilpa'!$B$7:$B$300,0)),"") | G42: =IFERROR(INDEX('Saloni Mehra'!$M$7:$M$300,MATCH($A42,'Saloni Mehra'!$B$7:$B$300,0)),"") -> 438 | H42: =IFERROR(INDEX('Vidushi Malhotra'!$M$7:$M$300,MATCH($A42,'Vidushi Malhotra'!$B$7:$B$300,0)),"") | I42: =IFERROR(INDEX('Dr Umesh Choudhry'!$M$7:$M$300,MATCH($A42,'Dr Umesh Choudhry'!$B$7:$B$300,0)),"") | J42: =IFERROR(INDEX(DA!$M$7:$M$300,MATCH($A42,DA!$B$7:$B$300,0)),"") | K42: Close 22.10.2026 (Screener.in) | L42: 431.5 | M42: =IF(AND(ISNUMBER(B42),ISNUMBER(L42),N(L42)>0),B42/L42-1,"") -> -0.0011587486
A43: Indian Energy Exchange Ltd | B43: 104 | C43: =IF(ISNUMBER(B43),B43,IF(ISNUMBER(E43),E43,IF(ISNUMBER(F43),F43,IF(ISNUMBER(G43),G43,IF(ISNUMBER(H43),H43,IF(ISNUMBER(I43),I43,IF(ISNUMBER(J43),J43,""))))))) -> 104 | D43: =IF(ISNUMBER(B43),IF(K43<>"",K43,"Manual override"),IF(ISNUMBER(E43),"Gautam stmt – 23.10",IF(ISNUMBER(F43),"Manish Shilpa stmt – live 23.10",IF(ISNUMBER(G43),"Saloni stmt – 20.10 (stale)",IF(ISNUMBER(H43),"Vidushi stmt – LTP 05.10",IF(ISNUMBER(I43),"Umesh stmt – NSE live 09.10",IF(ISNUMBER(J43),"DA stmt – older (stale)","No price on any statement"))))))) -> Close 22.10.2026 (Screener.in) | E43: =IFERROR(INDEX(Gautam!$M$7:$M$300,MATCH($A43,Gautam!$B$7:$B$300,0)),"") | F43: =IFERROR(INDEX('Manish Shilpa'!$M$7:$M$300,MATCH($A43,'Manish Shilpa'!$B$7:$B$300,0)),"") -> 100.75 | G43: =IFERROR(INDEX('Saloni Mehra'!$M$7:$M$300,MATCH($A43,'Saloni Mehra'!$B$7:$B$300,0)),"") | H43: =IFERROR(INDEX('Vidushi Malhotra'!$M$7:$M$300,MATCH($A43,'Vidushi Malhotra'!$B$7:$B$300,0)),"") | I43: =IFERROR(INDEX('Dr Umesh Choudhry'!$M$7:$M$300,MATCH($A43,'Dr Umesh Choudhry'!$B$7:$B$300,0)),"") | J43: =IFERROR(INDEX(DA!$M$7:$M$300,MATCH($A43,DA!$B$7:$B$300,0)),"") -> 114 | K43: Close 22.10.2026 (Screener.in) | L43: 103.28 | M43: =IF(AND(ISNUMBER(B43),ISNUMBER(L43),N(L43)>0),B43/L43-1,"") -> 0.00697134
A44: Indian Railway Finance Corp Ltd | B44: 77 | C44: =IF(ISNUMBER(B44),B44,IF(ISNUMBER(E44),E44,IF(ISNUMBER(F44),F44,IF(ISNUMBER(G44),G44,IF(ISNUMBER(H44),H44,IF(ISNUMBER(I44),I44,IF(ISNUMBER(J44),J44,""))))))) -> 77 | D44: =IF(ISNUMBER(B44),IF(K44<>"",K44,"Manual override"),IF(ISNUMBER(E44),"Gautam stmt – 23.10",IF(ISNUMBER(F44),"Manish Shilpa stmt – live 23.10",IF(ISNUMBER(G44),"Saloni stmt – 20.10 (stale)",IF(ISNUMBER(H44),"Vidushi stmt – LTP 05.10",IF(ISNUMBER(I44),"Umesh stmt – NSE live 09.10",IF(ISNUMBER(J44),"DA stmt – older (stale)","No price on any statement"))))))) -> Close 22.10.2026 (Screener.in) | E44: =IFERROR(INDEX(Gautam!$M$7:$M$300,MATCH($A44,Gautam!$B$7:$B$300,0)),"") | F44: =IFERROR(INDEX('Manish Shilpa'!$M$7:$M$300,MATCH($A44,'Manish Shilpa'!$B$7:$B$300,0)),"") | G44: =IFERROR(INDEX('Saloni Mehra'!$M$7:$M$300,MATCH($A44,'Saloni Mehra'!$B$7:$B$300,0)),"") | H44: =IFERROR(INDEX('Vidushi Malhotra'!$M$7:$M$300,MATCH($A44,'Vidushi Malhotra'!$B$7:$B$300,0)),"") | I44: =IFERROR(INDEX('Dr Umesh Choudhry'!$M$7:$M$300,MATCH($A44,'Dr Umesh Choudhry'!$B$7:$B$300,0)),"") | J44: =IFERROR(INDEX(DA!$M$7:$M$300,MATCH($A44,DA!$B$7:$B$300,0)),"") -> 81 | K44: Close 22.10.2026 (Screener.in) | L44: 76.8 | M44: =IF(AND(ISNUMBER(B44),ISNUMBER(L44),N(L44)>0),B44/L44-1,"") -> 0.0026041667
A45: Indraprastha Gas Ltd | B45: 140.01 | C45: =IF(ISNUMBER(B45),B45,IF(ISNUMBER(E45),E45,IF(ISNUMBER(F45),F45,IF(ISNUMBER(G45),G45,IF(ISNUMBER(H45),H45,IF(ISNUMBER(I45),I45,IF(ISNUMBER(J45),J45,""))))))) -> 140.01 | D45: =IF(ISNUMBER(B45),IF(K45<>"",K45,"Manual override"),IF(ISNUMBER(E45),"Gautam stmt – 23.10",IF(ISNUMBER(F45),"Manish Shilpa stmt – live 23.10",IF(ISNUMBER(G45),"Saloni stmt – 20.10 (stale)",IF(ISNUMBER(H45),"Vidushi stmt – LTP 05.10",IF(ISNUMBER(I45),"Umesh stmt – NSE live 09.10",IF(ISNUMBER(J45),"DA stmt – older (stale)","No price on any statement"))))))) -> Close 22.10.2026 (Screener.in) | E45: =IFERROR(INDEX(Gautam!$M$7:$M$300,MATCH($A45,Gautam!$B$7:$B$300,0)),"") | F45: =IFERROR(INDEX('Manish Shilpa'!$M$7:$M$300,MATCH($A45,'Manish Shilpa'!$B$7:$B$300,0)),"") | G45: =IFERROR(INDEX('Saloni Mehra'!$M$7:$M$300,MATCH($A45,'Saloni Mehra'!$B$7:$B$300,0)),"") | H45: =IFERROR(INDEX('Vidushi Malhotra'!$M$7:$M$300,MATCH($A45,'Vidushi Malhotra'!$B$7:$B$300,0)),"") | I45: =IFERROR(INDEX('Dr Umesh Choudhry'!$M$7:$M$300,MATCH($A45,'Dr Umesh Choudhry'!$B$7:$B$300,0)),"") | J45: =IFERROR(INDEX(DA!$M$7:$M$300,MATCH($A45,DA!$B$7:$B$300,0)),"") -> 152 | K45: Close 22.10.2026 (Screener.in) | L45: 142.31 | M45: =IF(AND(ISNUMBER(B45),ISNUMBER(L45),N(L45)>0),B45/L45-1,"") -> -0.0161619
A46: Indus Towers Ltd | B46: 381.85 | C46: =IF(ISNUMBER(B46),B46,IF(ISNUMBER(E46),E46,IF(ISNUMBER(F46),F46,IF(ISNUMBER(G46),G46,IF(ISNUMBER(H46),H46,IF(ISNUMBER(I46),I46,IF(ISNUMBER(J46),J46,""))))))) -> 381.85 | D46: =IF(ISNUMBER(B46),IF(K46<>"",K46,"Manual override"),IF(ISNUMBER(E46),"Gautam stmt – 23.10",IF(ISNUMBER(F46),"Manish Shilpa stmt – live 23.10",IF(ISNUMBER(G46),"Saloni stmt – 20.10 (stale)",IF(ISNUMBER(H46),"Vidushi stmt – LTP 05.10",IF(ISNUMBER(I46),"Umesh stmt – NSE live 09.10",IF(ISNUMBER(J46),"DA stmt – older (stale)","No price on any statement"))))))) -> Close 22.10.2026 (Screener.in) | E46: =IFERROR(INDEX(Gautam!$M$7:$M$300,MATCH($A46,Gautam!$B$7:$B$300,0)),"") | F46: =IFERROR(INDEX('Manish Shilpa'!$M$7:$M$300,MATCH($A46,'Manish Shilpa'!$B$7:$B$300,0)),"") | G46: =IFERROR(INDEX('Saloni Mehra'!$M$7:$M$300,MATCH($A46,'Saloni Mehra'!$B$7:$B$300,0)),"") | H46: =IFERROR(INDEX('Vidushi Malhotra'!$M$7:$M$300,MATCH($A46,'Vidushi Malhotra'!$B$7:$B$300,0)),"") | I46: =IFERROR(INDEX('Dr Umesh Choudhry'!$M$7:$M$300,MATCH($A46,'Dr Umesh Choudhry'!$B$7:$B$300,0)),"") | J46: =IFERROR(INDEX(DA!$M$7:$M$300,MATCH($A46,DA!$B$7:$B$300,0)),"") -> 388 | K46: Close 22.10.2026 (Screener.in) | L46: 379 | M46: =IF(AND(ISNUMBER(B46),ISNUMBER(L46),N(L46)>0),B46/L46-1,"") -> 0.0075197889
A47: Infosys Ltd | B47: 1153.35 | C47: =IF(ISNUMBER(B47),B47,IF(ISNUMBER(E47),E47,IF(ISNUMBER(F47),F47,IF(ISNUMBER(G47),G47,IF(ISNUMBER(H47),H47,IF(ISNUMBER(I47),I47,IF(ISNUMBER(J47),J47,""))))))) -> 1153.35 | D47: =IF(ISNUMBER(B47),IF(K47<>"",K47,"Manual override"),IF(ISNUMBER(E47),"Gautam stmt – 23.10",IF(ISNUMBER(F47),"Manish Shilpa stmt – live 23.10",IF(ISNUMBER(G47),"Saloni stmt – 20.10 (stale)",IF(ISNUMBER(H47),"Vidushi stmt – LTP 05.10",IF(ISNUMBER(I47),"Umesh stmt – NSE live 09.10",IF(ISNUMBER(J47),"DA stmt – older (stale)","No price on any statement"))))))) -> Close 22.10.2026 (Screener.in) | E47: =IFERROR(INDEX(Gautam!$M$7:$M$300,MATCH($A47,Gautam!$B$7:$B$300,0)),"") | F47: =IFERROR(INDEX('Manish Shilpa'!$M$7:$M$300,MATCH($A47,'Manish Shilpa'!$B$7:$B$300,0)),"") -> 1160 | G47: =IFERROR(INDEX('Saloni Mehra'!$M$7:$M$300,MATCH($A47,'Saloni Mehra'!$B$7:$B$300,0)),"") | H47: =IFERROR(INDEX('Vidushi Malhotra'!$M$7:$M$300,MATCH($A47,'Vidushi Malhotra'!$B$7:$B$300,0)),"") | I47: =IFERROR(INDEX('Dr Umesh Choudhry'!$M$7:$M$300,MATCH($A47,'Dr Umesh Choudhry'!$B$7:$B$300,0)),"") | J47: =IFERROR(INDEX(DA!$M$7:$M$300,MATCH($A47,DA!$B$7:$B$300,0)),"") | K47: Close 22.10.2026 (Screener.in) | L47: 1168 | M47: =IF(AND(ISNUMBER(B47),ISNUMBER(L47),N(L47)>0),B47/L47-1,"") -> -0.012542808
A48: InterGlobe Aviation Ltd (IndiGo) | B48: 4600 | C48: =IF(ISNUMBER(B48),B48,IF(ISNUMBER(E48),E48,IF(ISNUMBER(F48),F48,IF(ISNUMBER(G48),G48,IF(ISNUMBER(H48),H48,IF(ISNUMBER(I48),I48,IF(ISNUMBER(J48),J48,""))))))) -> 4600 | D48: =IF(ISNUMBER(B48),IF(K48<>"",K48,"Manual override"),IF(ISNUMBER(E48),"Gautam stmt – 23.10",IF(ISNUMBER(F48),"Manish Shilpa stmt – live 23.10",IF(ISNUMBER(G48),"Saloni stmt – 20.10 (stale)",IF(ISNUMBER(H48),"Vidushi stmt – LTP 05.10",IF(ISNUMBER(I48),"Umesh stmt – NSE live 09.10",IF(ISNUMBER(J48),"DA stmt – older (stale)","No price on any statement"))))))) -> Close 22.10.2026 (Screener.in) | E48: =IFERROR(INDEX(Gautam!$M$7:$M$300,MATCH($A48,Gautam!$B$7:$B$300,0)),"") -> 4608 | F48: =IFERROR(INDEX('Manish Shilpa'!$M$7:$M$300,MATCH($A48,'Manish Shilpa'!$B$7:$B$300,0)),"") | G48: =IFERROR(INDEX('Saloni Mehra'!$M$7:$M$300,MATCH($A48,'Saloni Mehra'!$B$7:$B$300,0)),"") | H48: =IFERROR(INDEX('Vidushi Malhotra'!$M$7:$M$300,MATCH($A48,'Vidushi Malhotra'!$B$7:$B$300,0)),"") | I48: =IFERROR(INDEX('Dr Umesh Choudhry'!$M$7:$M$300,MATCH($A48,'Dr Umesh Choudhry'!$B$7:$B$300,0)),"") | J48: =IFERROR(INDEX(DA!$M$7:$M$300,MATCH($A48,DA!$B$7:$B$300,0)),"") | K48: Close 22.10.2026 (Screener.in) | L48: 4641.5 | M48: =IF(AND(ISNUMBER(B48),ISNUMBER(L48),N(L48)>0),B48/L48-1,"") -> -0.0089410751
A49: Jio Financial Services Ltd | B49: 210.8 | C49: =IF(ISNUMBER(B49),B49,IF(ISNUMBER(E49),E49,IF(ISNUMBER(F49),F49,IF(ISNUMBER(G49),G49,IF(ISNUMBER(H49),H49,IF(ISNUMBER(I49),I49,IF(ISNUMBER(J49),J49,""))))))) -> 210.8 | D49: =IF(ISNUMBER(B49),IF(K49<>"",K49,"Manual override"),IF(ISNUMBER(E49),"Gautam stmt – 23.10",IF(ISNUMBER(F49),"Manish Shilpa stmt – live 23.10",IF(ISNUMBER(G49),"Saloni stmt – 20.10 (stale)",IF(ISNUMBER(H49),"Vidushi stmt – LTP 05.10",IF(ISNUMBER(I49),"Umesh stmt – NSE live 09.10",IF(ISNUMBER(J49),"DA stmt – older (stale)","No price on any statement"))))))) -> Close 22.10.2026 (Screener.in) | E49: =IFERROR(INDEX(Gautam!$M$7:$M$300,MATCH($A49,Gautam!$B$7:$B$300,0)),"") | F49: =IFERROR(INDEX('Manish Shilpa'!$M$7:$M$300,MATCH($A49,'Manish Shilpa'!$B$7:$B$300,0)),"") -> 204.875 | G49: =IFERROR(INDEX('Saloni Mehra'!$M$7:$M$300,MATCH($A49,'Saloni Mehra'!$B$7:$B$300,0)),"") | H49: =IFERROR(INDEX('Vidushi Malhotra'!$M$7:$M$300,MATCH($A49,'Vidushi Malhotra'!$B$7:$B$300,0)),"") | I49: =IFERROR(INDEX('Dr Umesh Choudhry'!$M$7:$M$300,MATCH($A49,'Dr Umesh Choudhry'!$B$7:$B$300,0)),"") | J49: =IFERROR(INDEX(DA!$M$7:$M$300,MATCH($A49,DA!$B$7:$B$300,0)),"") -> 230 | K49: Close 22.10.2026 (Screener.in) | L49: 211.39 | M49: =IF(AND(ISNUMBER(B49),ISNUMBER(L49),N(L49)>0),B49/L49-1,"") -> -0.0027910497
A50: JK Tyre & Industries Ltd | B50: 323 | C50: =IF(ISNUMBER(B50),B50,IF(ISNUMBER(E50),E50,IF(ISNUMBER(F50),F50,IF(ISNUMBER(G50),G50,IF(ISNUMBER(H50),H50,IF(ISNUMBER(I50),I50,IF(ISNUMBER(J50),J50,""))))))) -> 323 | D50: =IF(ISNUMBER(B50),IF(K50<>"",K50,"Manual override"),IF(ISNUMBER(E50),"Gautam stmt – 23.10",IF(ISNUMBER(F50),"Manish Shilpa stmt – live 23.10",IF(ISNUMBER(G50),"Saloni stmt – 20.10 (stale)",IF(ISNUMBER(H50),"Vidushi stmt – LTP 05.10",IF(ISNUMBER(I50),"Umesh stmt – NSE live 09.10",IF(ISNUMBER(J50),"DA stmt – older (stale)","No price on any statement"))))))) -> Close 22.10.2026 (Screener.in) | E50: =IFERROR(INDEX(Gautam!$M$7:$M$300,MATCH($A50,Gautam!$B$7:$B$300,0)),"") | F50: =IFERROR(INDEX('Manish Shilpa'!$M$7:$M$300,MATCH($A50,'Manish Shilpa'!$B$7:$B$300,0)),"") | G50: =IFERROR(INDEX('Saloni Mehra'!$M$7:$M$300,MATCH($A50,'Saloni Mehra'!$B$7:$B$300,0)),"") | H50: =IFERROR(INDEX('Vidushi Malhotra'!$M$7:$M$300,MATCH($A50,'Vidushi Malhotra'!$B$7:$B$300,0)),"") | I50: =IFERROR(INDEX('Dr Umesh Choudhry'!$M$7:$M$300,MATCH($A50,'Dr Umesh Choudhry'!$B$7:$B$300,0)),"") | J50: =IFERROR(INDEX(DA!$M$7:$M$300,MATCH($A50,DA!$B$7:$B$300,0)),"") -> 354 | K50: Close 22.10.2026 (Screener.in) | L50: 327.55 | M50: =IF(AND(ISNUMBER(B50),ISNUMBER(L50),N(L50)>0),B50/L50-1,"") -> -0.013891009
A51: Jubilant FoodWorks Ltd | B51: 404.9 | C51: =IF(ISNUMBER(B51),B51,IF(ISNUMBER(E51),E51,IF(ISNUMBER(F51),F51,IF(ISNUMBER(G51),G51,IF(ISNUMBER(H51),H51,IF(ISNUMBER(I51),I51,IF(ISNUMBER(J51),J51,""))))))) -> 404.9 | D51: =IF(ISNUMBER(B51),IF(K51<>"",K51,"Manual override"),IF(ISNUMBER(E51),"Gautam stmt – 23.10",IF(ISNUMBER(F51),"Manish Shilpa stmt – live 23.10",IF(ISNUMBER(G51),"Saloni stmt – 20.10 (stale)",IF(ISNUMBER(H51),"Vidushi stmt – LTP 05.10",IF(ISNUMBER(I51),"Umesh stmt – NSE live 09.10",IF(ISNUMBER(J51),"DA stmt – older (stale)","No price on any statement"))))))) -> Close 22.10.2026 (Screener.in) | E51: =IFERROR(INDEX(Gautam!$M$7:$M$300,MATCH($A51,Gautam!$B$7:$B$300,0)),"") | F51: =IFERROR(INDEX('Manish Shilpa'!$M$7:$M$300,MATCH($A51,'Manish Shilpa'!$B$7:$B$300,0)),"") | G51: =IFERROR(INDEX('Saloni Mehra'!$M$7:$M$300,MATCH($A51,'Saloni Mehra'!$B$7:$B$300,0)),"") -> 413.5 | H51: =IFERROR(INDEX('Vidushi Malhotra'!$M$7:$M$300,MATCH($A51,'Vidushi Malhotra'!$B$7:$B$300,0)),"") | I51: =IFERROR(INDEX('Dr Umesh Choudhry'!$M$7:$M$300,MATCH($A51,'Dr Umesh Choudhry'!$B$7:$B$300,0)),"") | J51: =IFERROR(INDEX(DA!$M$7:$M$300,MATCH($A51,DA!$B$7:$B$300,0)),"") | K51: Close 22.10.2026 (Screener.in) | L51: 405 | M51: =IF(AND(ISNUMBER(B51),ISNUMBER(L51),N(L51)>0),B51/L51-1,"") -> -0.00024691358
A52: Kotak Mahindra Bank Ltd | B52: 437 | C52: =IF(ISNUMBER(B52),B52,IF(ISNUMBER(E52),E52,IF(ISNUMBER(F52),F52,IF(ISNUMBER(G52),G52,IF(ISNUMBER(H52),H52,IF(ISNUMBER(I52),I52,IF(ISNUMBER(J52),J52,""))))))) -> 437 | D52: =IF(ISNUMBER(B52),IF(K52<>"",K52,"Manual override"),IF(ISNUMBER(E52),"Gautam stmt – 23.10",IF(ISNUMBER(F52),"Manish Shilpa stmt – live 23.10",IF(ISNUMBER(G52),"Saloni stmt – 20.10 (stale)",IF(ISNUMBER(H52),"Vidushi stmt – LTP 05.10",IF(ISNUMBER(I52),"Umesh stmt – NSE live 09.10",IF(ISNUMBER(J52),"DA stmt – older (stale)","No price on any statement"))))))) -> Close 22.10.2026 (Screener.in) | E52: =IFERROR(INDEX(Gautam!$M$7:$M$300,MATCH($A52,Gautam!$B$7:$B$300,0)),"") | F52: =IFERROR(INDEX('Manish Shilpa'!$M$7:$M$300,MATCH($A52,'Manish Shilpa'!$B$7:$B$300,0)),"") -> 433.1125 | G52: =IFERROR(INDEX('Saloni Mehra'!$M$7:$M$300,MATCH($A52,'Saloni Mehra'!$B$7:$B$300,0)),"") | H52: =IFERROR(INDEX('Vidushi Malhotra'!$M$7:$M$300,MATCH($A52,'Vidushi Malhotra'!$B$7:$B$300,0)),"") | I52: =IFERROR(INDEX('Dr Umesh Choudhry'!$M$7:$M$300,MATCH($A52,'Dr Umesh Choudhry'!$B$7:$B$300,0)),"") | J52: =IFERROR(INDEX(DA!$M$7:$M$300,MATCH($A52,DA!$B$7:$B$300,0)),"") | K52: Close 22.10.2026 (Screener.in) | L52: 437.8 | M52: =IF(AND(ISNUMBER(B52),ISNUMBER(L52),N(L52)>0),B52/L52-1,"") -> -0.0018273184
... A56: NCC Ltd | B56: 120.17 | C56: =IF(ISNUMBER(B56),B56,IF(ISNUMBER(E56),E56,IF(ISNUMBER(F56),F56,IF(ISNUMBER(G56),G56,IF(ISNUMBER(H56),H56,IF(ISNUMBER(I56),I56,IF(ISNUMBER(J56),J56,""))))))) -> 120.17 | D56: =IF(ISNUMBER(B56),IF(K56<>"",K56,"Manual override"),IF(ISNUMBER(E56),"Gautam stmt – 23.10",IF(ISNUMBER(F56),"Manish Shilpa stmt – live 23.10",IF(ISNUMBER(G56),"Saloni stmt – 20.10 (stale)",IF(ISNUMBER(H56),"Vidushi stmt – LTP 05.10",IF(ISNUMBER(I56),"Umesh stmt – NSE live 09.10",IF(ISNUMBER(J56),"DA stmt – older (stale)","No price on any statement"))))))) -> Close 22.10.2026 (Screener.in) | E56: =IFERROR(INDEX(Gautam!$M$7:$M$300,MATCH($A56,Gautam!$B$7:$B$300,0)),"") | F56: =IFERROR(INDEX('Manish Shilpa'!$M$7:$M$300,MATCH($A56,'Manish Shilpa'!$B$7:$B$300,0)),"") | G56: =IFERROR(INDEX('Saloni Mehra'!$M$7:$M$300,MATCH($A56,'Saloni Mehra'!$B$7:$B$300,0)),"") | H56: =IFERROR(INDEX('Vidushi Malhotra'!$M$7:$M$300,MATCH($A56,'Vidushi Malhotra'!$B$7:$B$300,0)),"") | I56: =IFERROR(INDEX('Dr Umesh Choudhry'!$M$7:$M$300,MATCH($A56,'Dr Umesh Choudhry'!$B$7:$B$300,0)),"") | J56: =IFERROR(INDEX(DA!$M$7:$M$300,MATCH($A56,DA!$B$7:$B$300,0)),"") -> 141 | K56: Close 22.10.2026 (Screener.in) | L56: 123.2 | M56: =IF(AND(ISNUMBER(B56),ISNUMBER(L56),N(L56)>0),B56/L56-1,"") -> -0.024594156
A57: NEPC Agro Foods Ltd | C57: =IF(ISNUMBER(B57),B57,IF(ISNUMBER(E57),E57,IF(ISNUMBER(F57),F57,IF(ISNUMBER(G57),G57,IF(ISNUMBER(H57),H57,IF(ISNUMBER(I57),I57,IF(ISNUMBER(J57),J57,""))))))) | D57: =IF(ISNUMBER(B57),IF(K57<>"",K57,"Manual override"),IF(ISNUMBER(E57),"Gautam stmt – 23.10",IF(ISNUMBER(F57),"Manish Shilpa stmt – live 23.10",IF(ISNUMBER(G57),"Saloni stmt – 20.10 (stale)",IF(ISNUMBER(H57),"Vidushi stmt – LTP 05.10",IF(ISNUMBER(I57),"Umesh stmt – NSE live 09.10",IF(ISNUMBER(J57),"DA stmt – older (stale)","No price on any statement"))))))) -> No price on any statement | E57: =IFERROR(INDEX(Gautam!$M$7:$M$300,MATCH($A57,Gautam!$B$7:$B$300,0)),"") | F57: =IFERROR(INDEX('Manish Shilpa'!$M$7:$M$300,MATCH($A57,'Manish Shilpa'!$B$7:$B$300,0)),"") | G57: =IFERROR(INDEX('Saloni Mehra'!$M$7:$M$300,MATCH($A57,'Saloni Mehra'!$B$7:$B$300,0)),"") | H57: =IFERROR(INDEX('Vidushi Malhotra'!$M$7:$M$300,MATCH($A57,'Vidushi Malhotra'!$B$7:$B$300,0)),"") | I57: =IFERROR(INDEX('Dr Umesh Choudhry'!$M$7:$M$300,MATCH($A57,'Dr Umesh Choudhry'!$B$7:$B$300,0)),"") | J57: =IFERROR(INDEX(DA!$M$7:$M$300,MATCH($A57,DA!$B$7:$B$300,0)),"") | K57: No exchange close found – statement price used | M57: =IF(AND(ISNUMBER(B57),ISNUMBER(L57),N(L57)>0),B57/L57-1,"")
A58: Nestle India Ltd | B58: 1189.9 | C58: =IF(ISNUMBER(B58),B58,IF(ISNUMBER(E58),E58,IF(ISNUMBER(F58),F58,IF(ISNUMBER(G58),G58,IF(ISNUMBER(H58),H58,IF(ISNUMBER(I58),I58,IF(ISNUMBER(J58),J58,""))))))) -> 1189.9 | D58: =IF(ISNUMBER(B58),IF(K58<>"",K58,"Manual override"),IF(ISNUMBER(E58),"Gautam stmt – 23.10",IF(ISNUMBER(F58),"Manish Shilpa stmt – live 23.10",IF(ISNUMBER(G58),"Saloni stmt – 20.10 (stale)",IF(ISNUMBER(H58),"Vidushi stmt – LTP 05.10",IF(ISNUMBER(I58),"Umesh stmt – NSE live 09.10",IF(ISNUMBER(J58),"DA stmt – older (stale)","No price on any statement"))))))) -> Close 22.10.2026 (Screener.in) | E58: =IFERROR(INDEX(Gautam!$M$7:$M$300,MATCH($A58,Gautam!$B$7:$B$300,0)),"") -> 1190 | F58: =IFERROR(INDEX('Manish Shilpa'!$M$7:$M$300,MATCH($A58,'Manish Shilpa'!$B$7:$B$300,0)),"") | G58: =IFERROR(INDEX('Saloni Mehra'!$M$7:$M$300,MATCH($A58,'Saloni Mehra'!$B$7:$B$300,0)),"") -> 1242.75 | H58: =IFERROR(INDEX('Vidushi Malhotra'!$M$7:$M$300,MATCH($A58,'Vidushi Malhotra'!$B$7:$B$300,0)),"") | I58: =IFERROR(INDEX('Dr Umesh Choudhry'!$M$7:$M$300,MATCH($A58,'Dr Umesh Choudhry'!$B$7:$B$300,0)),"") -> 1325 | J58: =IFERROR(INDEX(DA!$M$7:$M$300,MATCH($A58,DA!$B$7:$B$300,0)),"") -> 1383 | K58: Close 22.10.2026 (Screener.in) | L58: 1223.9 | M58: =IF(AND(ISNUMBER(B58),ISNUMBER(L58),N(L58)>0),B58/L58-1,"") -> -0.027780047
A59: Nippon India ETF Gold BeES | C59: =IF(ISNUMBER(B59),B59,IF(ISNUMBER(E59),E59,IF(ISNUMBER(F59),F59,IF(ISNUMBER(G59),G59,IF(ISNUMBER(H59),H59,IF(ISNUMBER(I59),I59,IF(ISNUMBER(J59),J59,""))))))) -> 123 | D59: =IF(ISNUMBER(B59),IF(K59<>"",K59,"Manual override"),IF(ISNUMBER(E59),"Gautam stmt – 23.10",IF(ISNUMBER(F59),"Manish Shilpa stmt – live 23.10",IF(ISNUMBER(G59),"Saloni stmt – 20.10 (stale)",IF(ISNUMBER(H59),"Vidushi stmt – LTP 05.10",IF(ISNUMBER(I59),"Umesh stmt – NSE live 09.10",IF(ISNUMBER(J59),"DA stmt – older (stale)","No price on any statement"))))))) -> Gautam stmt – 23.10 | E59: =IFERROR(INDEX(Gautam!$M$7:$M$300,MATCH($A59,Gautam!$B$7:$B$300,0)),"") -> 123 | F59: =IFERROR(INDEX('Manish Shilpa'!$M$7:$M$300,MATCH($A59,'Manish Shilpa'!$B$7:$B$300,0)),"") | G59: =IFERROR(INDEX('Saloni Mehra'!$M$7:$M$300,MATCH($A59,'Saloni Mehra'!$B$7:$B$300,0)),"") | H59: =IFERROR(INDEX('Vidushi Malhotra'!$M$7:$M$300,MATCH($A59,'Vidushi Malhotra'!$B$7:$B$300,0)),"") -> 121 | I59: =IFERROR(INDEX('Dr Umesh Choudhry'!$M$7:$M$300,MATCH($A59,'Dr Umesh Choudhry'!$B$7:$B$300,0)),"") | J59: =IFERROR(INDEX(DA!$M$7:$M$300,MATCH($A59,DA!$B$7:$B$300,0)),"") | K59: No exchange close found – statement price used | M59: =IF(AND(ISNUMBER(B59),ISNUMBER(L59),N(L59)>0),B59/L59-1,"")
A60: Nippon India ETF Infra BeES | C60: =IF(ISNUMBER(B60),B60,IF(ISNUMBER(E60),E60,IF(ISNUMBER(F60),F60,IF(ISNUMBER(G60),G60,IF(ISNUMBER(H60),H60,IF(ISNUMBER(I60),I60,IF(ISNUMBER(J60),J60,""))))))) -> 877.02941 | D60: =IF(ISNUMBER(B60),IF(K60<>"",K60,"Manual override"),IF(ISNUMBER(E60),"Gautam stmt – 23.10",IF(ISNUMBER(F60),"Manish Shilpa stmt – live 23.10",IF(ISNUMBER(G60),"Saloni stmt – 20.10 (stale)",IF(ISNUMBER(H60),"Vidushi stmt – LTP 05.10",IF(ISNUMBER(I60),"Umesh stmt – NSE live 09.10",IF(ISNUMBER(J60),"DA stmt – older (stale)","No price on any statement"))))))) -> Manish Shilpa stmt – live 23.10 | E60: =IFERROR(INDEX(Gautam!$M$7:$M$300,MATCH($A60,Gautam!$B$7:$B$300,0)),"") | F60: =IFERROR(INDEX('Manish Shilpa'!$M$7:$M$300,MATCH($A60,'Manish Shilpa'!$B$7:$B$300,0)),"") -> 877.02941 | G60: =IFERROR(INDEX('Saloni Mehra'!$M$7:$M$300,MATCH($A60,'Saloni Mehra'!$B$7:$B$300,0)),"") | H60: =IFERROR(INDEX('Vidushi Malhotra'!$M$7:$M$300,MATCH($A60,'Vidushi Malhotra'!$B$7:$B$300,0)),"") | I60: =IFERROR(INDEX('Dr Umesh Choudhry'!$M$7:$M$300,MATCH($A60,'Dr Umesh Choudhry'!$B$7:$B$300,0)),"") | J60: =IFERROR(INDEX(DA!$M$7:$M$300,MATCH($A60,DA!$B$7:$B$300,0)),"") | K60: No exchange close found – statement price used | M60: =IF(AND(ISNUMBER(B60),ISNUMBER(L60),N(L60)>0),B60/L60-1,"")
A61: Nippon India ETF Nifty 1D Rate Liquid BeES | C61: =IF(ISNUMBER(B61),B61,IF(ISNUMBER(E61),E61,IF(ISNUMBER(F61),F61,IF(ISNUMBER(G61),G61,IF(ISNUMBER(H61),H61,IF(ISNUMBER(I61),I61,IF(ISNUMBER(J61),J61,""))))))) -> 1000 | D61: =IF(ISNUMBER(B61),IF(K61<>"",K61,"Manual override"),IF(ISNUMBER(E61),"Gautam stmt – 23.10",IF(ISNUMBER(F61),"Manish Shilpa stmt – live 23.10",IF(ISNUMBER(G61),"Saloni stmt – 20.10 (stale)",IF(ISNUMBER(H61),"Vidushi stmt – LTP 05.10",IF(ISNUMBER(I61),"Umesh stmt – NSE live 09.10",IF(ISNUMBER(J61),"DA stmt – older (stale)","No price on any statement"))))))) -> Gautam stmt – 23.10 | E61: =IFERROR(INDEX(Gautam!$M$7:$M$300,MATCH($A61,Gautam!$B$7:$B$300,0)),"") -> 1000 | F61: =IFERROR(INDEX('Manish Shilpa'!$M$7:$M$300,MATCH($A61,'Manish Shilpa'!$B$7:$B$300,0)),"") -> 1389.75 | G61: =IFERROR(INDEX('Saloni Mehra'!$M$7:$M$300,MATCH($A61,'Saloni Mehra'!$B$7:$B$300,0)),"") | H61: =IFERROR(INDEX('Vidushi Malhotra'!$M$7:$M$300,MATCH($A61,'Vidushi Malhotra'!$B$7:$B$300,0)),"") | I61: =IFERROR(INDEX('Dr Umesh Choudhry'!$M$7:$M$300,MATCH($A61,'Dr Umesh Choudhry'!$B$7:$B$300,0)),"") | J61: =IFERROR(INDEX(DA!$M$7:$M$300,MATCH($A61,DA!$B$7:$B$300,0)),"") | K61: No exchange close found – statement price used | M61: =IF(AND(ISNUMBER(B61),ISNUMBER(L61),N(L61)>0),B61/L61-1,"")
A62: Nippon India ETF Nifty 50 BeES | C62: =IF(ISNUMBER(B62),B62,IF(ISNUMBER(E62),E62,IF(ISNUMBER(F62),F62,IF(ISNUMBER(G62),G62,IF(ISNUMBER(H62),H62,IF(ISNUMBER(I62),I62,IF(ISNUMBER(J62),J62,""))))))) -> 256.69292 | D62: =IF(ISNUMBER(B62),IF(K62<>"",K62,"Manual override"),IF(ISNUMBER(E62),"Gautam stmt – 23.10",IF(ISNUMBER(F62),"Manish Shilpa stmt – live 23.10",IF(ISNUMBER(G62),"Saloni stmt – 20.10 (stale)",IF(ISNUMBER(H62),"Vidushi stmt – LTP 05.10",IF(ISNUMBER(I62),"Umesh stmt – NSE live 09.10",IF(ISNUMBER(J62),"DA stmt – older (stale)","No price on any statement"))))))) -> Manish Shilpa stmt – live 23.10 | E62: =IFERROR(INDEX(Gautam!$M$7:$M$300,MATCH($A62,Gautam!$B$7:$B$300,0)),"") | F62: =IFERROR(INDEX('Manish Shilpa'!$M$7:$M$300,MATCH($A62,'Manish Shilpa'!$B$7:$B$300,0)),"") -> 256.69292 | G62: =IFERROR(INDEX('Saloni Mehra'!$M$7:$M$300,MATCH($A62,'Saloni Mehra'!$B$7:$B$300,0)),"") | H62: =IFERROR(INDEX('Vidushi Malhotra'!$M$7:$M$300,MATCH($A62,'Vidushi Malhotra'!$B$7:$B$300,0)),"") -> 257 | I62: =IFERROR(INDEX('Dr Umesh Choudhry'!$M$7:$M$300,MATCH($A62,'Dr Umesh Choudhry'!$B$7:$B$300,0)),"") | J62: =IFERROR(INDEX(DA!$M$7:$M$300,MATCH($A62,DA!$B$7:$B$300,0)),"") | K62: No exchange close found – statement price used | M62: =IF(AND(ISNUMBER(B62),ISNUMBER(L62),N(L62)>0),B62/L62-1,"")
A63: NTPC Green Energy Ltd | B63: 84.35 | C63: =IF(ISNUMBER(B63),B63,IF(ISNUMBER(E63),E63,IF(ISNUMBER(F63),F63,IF(ISNUMBER(G63),G63,IF(ISNUMBER(H63),H63,IF(ISNUMBER(I63),I63,IF(ISNUMBER(J63),J63,""))))))) -> 84.35 | D63: =IF(ISNUMBER(B63),IF(K63<>"",K63,"Manual override"),IF(ISNUMBER(E63),"Gautam stmt – 23.10",IF(ISNUMBER(F63),"Manish Shilpa stmt – live 23.10",IF(ISNUMBER(G63),"Saloni stmt – 20.10 (stale)",IF(ISNUMBER(H63),"Vidushi stmt – LTP 05.10",IF(ISNUMBER(I63),"Umesh stmt – NSE live 09.10",IF(ISNUMBER(J63),"DA stmt – older (stale)","No price on any statement"))))))) -> Close 22.10.2026 (Screener.in) | E63: =IFERROR(INDEX(Gautam!$M$7:$M$300,MATCH($A63,Gautam!$B$7:$B$300,0)),"") | F63: =IFERROR(INDEX('Manish Shilpa'!$M$7:$M$300,MATCH($A63,'Manish Shilpa'!$B$7:$B$300,0)),"") | G63: =IFERROR(INDEX('Saloni Mehra'!$M$7:$M$300,MATCH($A63,'Saloni Mehra'!$B$7:$B$300,0)),"") | H63: =IFERROR(INDEX('Vidushi Malhotra'!$M$7:$M$300,MATCH($A63,'Vidushi Malhotra'!$B$7:$B$300,0)),"") | I63: =IFERROR(INDEX('Dr Umesh Choudhry'!$M$7:$M$300,MATCH($A63,'Dr Umesh Choudhry'!$B$7:$B$300,0)),"") | J63: =IFERROR(INDEX(DA!$M$7:$M$300,MATCH($A63,DA!$B$7:$B$300,0)),"") -> 87 | K63: Close 22.10.2026 (Screener.in) | L63: 84.04 | M63: =IF(AND(ISNUMBER(B63),ISNUMBER(L63),N(L63)>0),B63/L63-1,"") -> 0.0036887197
A64: Orient Cement Ltd | B64: 116.89 | C64: =IF(ISNUMBER(B64),B64,IF(ISNUMBER(E64),E64,IF(ISNUMBER(F64),F64,IF(ISNUMBER(G64),G64,IF(ISNUMBER(H64),H64,IF(ISNUMBER(I64),I64,IF(ISNUMBER(J64),J64,""))))))) -> 116.89 | D64: =IF(ISNUMBER(B64),IF(K64<>"",K64,"Manual override"),IF(ISNUMBER(E64),"Gautam stmt – 23.10",IF(ISNUMBER(F64),"Manish Shilpa stmt – live 23.10",IF(ISNUMBER(G64),"Saloni stmt – 20.10 (stale)",IF(ISNUMBER(H64),"Vidushi stmt – LTP 05.10",IF(ISNUMBER(I64),"Umesh stmt – NSE live 09.10",IF(ISNUMBER(J64),"DA stmt – older (stale)","No price on any statement"))))))) -> Close 22.10.2026 (Screener.in) | E64: =IFERROR(INDEX(Gautam!$M$7:$M$300,MATCH($A64,Gautam!$B$7:$B$300,0)),"") | F64: =IFERROR(INDEX('Manish Shilpa'!$M$7:$M$300,MATCH($A64,'Manish Shilpa'!$B$7:$B$300,0)),"") | G64: =IFERROR(INDEX('Saloni Mehra'!$M$7:$M$300,MATCH($A64,'Saloni Mehra'!$B$7:$B$300,0)),"") | H64: =IFERROR(INDEX('Vidushi Malhotra'!$M$7:$M$300,MATCH($A64,'Vidushi Malhotra'!$B$7:$B$300,0)),"") | I64: =IFERROR(INDEX('Dr Umesh Choudhry'!$M$7:$M$300,MATCH($A64,'Dr Umesh Choudhry'!$B$7:$B$300,0)),"") | J64: =IFERROR(INDEX(DA!$M$7:$M$300,MATCH($A64,DA!$B$7:$B$300,0)),"") -> 126 | K64: Close 22.10.2026 (Screener.in) | L64: 113.81 | M64: =IF(AND(ISNUMBER(B64),ISNUMBER(L64),N(L64)>0),B64/L64-1,"") -> 0.027062648
A65: Orient Electric Ltd | B65: 188.91 | C65: =IF(ISNUMBER(B65),B65,IF(ISNUMBER(E65),E65,IF(ISNUMBER(F65),F65,IF(ISNUMBER(G65),G65,IF(ISNUMBER(H65),H65,IF(ISNUMBER(I65),I65,IF(ISNUMBER(J65),J65,""))))))) -> 188.91 | D65: =IF(ISNUMBER(B65),IF(K65<>"",K65,"Manual override"),IF(ISNUMBER(E65),"Gautam stmt – 23.10",IF(ISNUMBER(F65),"Manish Shilpa stmt – live 23.10",IF(ISNUMBER(G65),"Saloni stmt – 20.10 (stale)",IF(ISNUMBER(H65),"Vidushi stmt – LTP 05.10",IF(ISNUMBER(I65),"Umesh stmt – NSE live 09.10",IF(ISNUMBER(J65),"DA stmt – older (stale)","No price on any statement"))))))) -> Close 22.10.2026 (Screener.in) | E65: =IFERROR(INDEX(Gautam!$M$7:$M$300,MATCH($A65,Gautam!$B$7:$B$300,0)),"") -> 154 | F65: =IFERROR(INDEX('Manish Shilpa'!$M$7:$M$300,MATCH($A65,'Manish Shilpa'!$B$7:$B$300,0)),"") | G65: =IFERROR(INDEX('Saloni Mehra'!$M$7:$M$300,MATCH($A65,'Saloni Mehra'!$B$7:$B$300,0)),"") | H65: =IFERROR(INDEX('Vidushi Malhotra'!$M$7:$M$300,MATCH($A65,'Vidushi Malhotra'!$B$7:$B$300,0)),"") | I65: =IFERROR(INDEX('Dr Umesh Choudhry'!$M$7:$M$300,MATCH($A65,'Dr Umesh Choudhry'!$B$7:$B$300,0)),"") | J65: =IFERROR(INDEX(DA!$M$7:$M$300,MATCH($A65,DA!$B$7:$B$300,0)),"") | K65: Close 22.10.2026 (Screener.in) | L65: 189.6 | M65: =IF(AND(ISNUMBER(B65),ISNUMBER(L65),N(L65)>0),B65/L65-1,"") -> -0.0036392405
A66: Page Industries Ltd | B66: 34425 | C66: =IF(ISNUMBER(B66),B66,IF(ISNUMBER(E66),E66,IF(ISNUMBER(F66),F66,IF(ISNUMBER(G66),G66,IF(ISNUMBER(H66),H66,IF(ISNUMBER(I66),I66,IF(ISNUMBER(J66),J66,""))))))) -> 34425 | D66: =IF(ISNUMBER(B66),IF(K66<>"",K66,"Manual override"),IF(ISNUMBER(E66),"Gautam stmt – 23.10",IF(ISNUMBER(F66),"Manish Shilpa stmt – live 23.10",IF(ISNUMBER(G66),"Saloni stmt – 20.10 (stale)",IF(ISNUMBER(H66),"Vidushi stmt – LTP 05.10",IF(ISNUMBER(I66),"Umesh stmt – NSE live 09.10",IF(ISNUMBER(J66),"DA stmt – older (stale)","No price on any statement"))))))) -> Close 22.10.2026 (Screener.in) | E66: =IFERROR(INDEX(Gautam!$M$7:$M$300,MATCH($A66,Gautam!$B$7:$B$300,0)),"") | F66: =IFERROR(INDEX('Manish Shilpa'!$M$7:$M$300,MATCH($A66,'Manish Shilpa'!$B$7:$B$300,0)),"") -> 33825 | G66: =IFERROR(INDEX('Saloni Mehra'!$M$7:$M$300,MATCH($A66,'Saloni Mehra'!$B$7:$B$300,0)),"") | H66: =IFERROR(INDEX('Vidushi Malhotra'!$M$7:$M$300,MATCH($A66,'Vidushi Malhotra'!$B$7:$B$300,0)),"") | I66: =IFERROR(INDEX('Dr Umesh Choudhry'!$M$7:$M$300,MATCH($A66,'Dr Umesh Choudhry'!$B$7:$B$300,0)),"") | J66: =IFERROR(INDEX(DA!$M$7:$M$300,MATCH($A66,DA!$B$7:$B$300,0)),"") | K66: Close 22.10.2026 (Screener.in) | L66: 34870 | M66: =IF(AND(ISNUMBER(B66),ISNUMBER(L66),N(L66)>0),B66/L66-1,"") -> -0.012761686
A67: Persistent Systems Ltd | B67: 5740.5 | C67: =IF(ISNUMBER(B67),B67,IF(ISNUMBER(E67),E67,IF(ISNUMBER(F67),F67,IF(ISNUMBER(G67),G67,IF(ISNUMBER(H67),H67,IF(ISNUMBER(I67),I67,IF(ISNUMBER(J67),J67,""))))))) -> 5740.5 | D67: =IF(ISNUMBER(B67),IF(K67<>"",K67,"Manual override"),IF(ISNUMBER(E67),"Gautam stmt – 23.10",IF(ISNUMBER(F67),"Manish Shilpa stmt – live 23.10",IF(ISNUMBER(G67),"Saloni stmt – 20.10 (stale)",IF(ISNUMBER(H67),"Vidushi stmt – LTP 05.10",IF(ISNUMBER(I67),"Umesh stmt – NSE live 09.10",IF(ISNUMBER(J67),"DA stmt – older (stale)","No price on any statement"))))))) -> Close 22.10.2026 (Screener.in) | E67: =IFERROR(INDEX(Gautam!$M$7:$M$300,MATCH($A67,Gautam!$B$7:$B$300,0)),"") -> 5740 | F67: =IFERROR(INDEX('Manish Shilpa'!$M$7:$M$300,MATCH($A67,'Manish Shilpa'!$B$7:$B$300,0)),"") -> 5786.1818 | G67: =IFERROR(INDEX('Saloni Mehra'!$M$7:$M$300,MATCH($A67,'Saloni Mehra'!$B$7:$B$300,0)),"") | H67: =IFERROR(INDEX('Vidushi Malhotra'!$M$7:$M$300,MATCH($A67,'Vidushi Malhotra'!$B$7:$B$300,0)),"") | I67: =IFERROR(INDEX('Dr Umesh Choudhry'!$M$7:$M$300,MATCH($A67,'Dr Umesh Choudhry'!$B$7:$B$300,0)),"") -> 5625.5294 | J67: =IFERROR(INDEX(DA!$M$7:$M$300,MATCH($A67,DA!$B$7:$B$300,0)),"") -> 5516 | K67: Close 22.10.2026 (Screener.in) | L67: 5858.5 | M67: =IF(AND(ISNUMBER(B67),ISNUMBER(L67),N(L67)>0),B67/L67-1,"") -> -0.020141674
A68: Pfizer Ltd | B68: 3688.9 | C68: =IF(ISNUMBER(B68),B68,IF(ISNUMBER(E68),E68,IF(ISNUMBER(F68),F68,IF(ISNUMBER(G68),G68,IF(ISNUMBER(H68),H68,IF(ISNUMBER(I68),I68,IF(ISNUMBER(J68),J68,""))))))) -> 3688.9 | D68: =IF(ISNUMBER(B68),IF(K68<>"",K68,"Manual override"),IF(ISNUMBER(E68),"Gautam stmt – 23.10",IF(ISNUMBER(F68),"Manish Shilpa stmt – live 23.10",IF(ISNUMBER(G68),"Saloni stmt – 20.10 (stale)",IF(ISNUMBER(H68),"Vidushi stmt – LTP 05.10",IF(ISNUMBER(I68),"Umesh stmt – NSE live 09.10",IF(ISNUMBER(J68),"DA stmt – older (stale)","No price on any statement"))))))) -> Close 22.10.2026 (Screener.in) | E68: =IFERROR(INDEX(Gautam!$M$7:$M$300,MATCH($A68,Gautam!$B$7:$B$300,0)),"") | F68: =IFERROR(INDEX('Manish Shilpa'!$M$7:$M$300,MATCH($A68,'Manish Shilpa'!$B$7:$B$300,0)),"") -> 3601 | G68: =IFERROR(INDEX('Saloni Mehra'!$M$7:$M$300,MATCH($A68,'Saloni Mehra'!$B$7:$B$300,0)),"") | H68: =IFERROR(INDEX('Vidushi Malhotra'!$M$7:$M$300,MATCH($A68,'Vidushi Malhotra'!$B$7:$B$300,0)),"") | I68: =IFERROR(INDEX('Dr Umesh Choudhry'!$M$7:$M$300,MATCH($A68,'Dr Umesh Choudhry'!$B$7:$B$300,0)),"") | J68: =IFERROR(INDEX(DA!$M$7:$M$300,MATCH($A68,DA!$B$7:$B$300,0)),"") | K68: Close 22.10.2026 (Screener.in) | L68: 3754.7 | M68: =IF(AND(ISNUMBER(B68),ISNUMBER(L68),N(L68)>0),B68/L68-1,"") -> -0.017524702
A69: Poonawalla Fincorp Ltd | B69: 432.45 | C69: =IF(ISNUMBER(B69),B69,IF(ISNUMBER(E69),E69,IF(ISNUMBER(F69),F69,IF(ISNUMBER(G69),G69,IF(ISNUMBER(H69),H69,IF(ISNUMBER(I69),I69,IF(ISNUMBER(J69),J69,""))))))) -> 432.45 | D69: =IF(ISNUMBER(B69),IF(K69<>"",K69,"Manual override"),IF(ISNUMBER(E69),"Gautam stmt – 23.10",IF(ISNUMBER(F69),"Manish Shilpa stmt – live 23.10",IF(ISNUMBER(G69),"Saloni stmt – 20.10 (stale)",IF(ISNUMBER(H69),"Vidushi stmt – LTP 05.10",IF(ISNUMBER(I69),"Umesh stmt – NSE live 09.10",IF(ISNUMBER(J69),"DA stmt – older (stale)","No price on any statement"))))))) -> Close 22.10.2026 (Screener.in) | E69: =IFERROR(INDEX(Gautam!$M$7:$M$300,MATCH($A69,Gautam!$B$7:$B$300,0)),"") -> 432 | F69: =IFERROR(INDEX('Manish Shilpa'!$M$7:$M$300,MATCH($A69,'Manish Shilpa'!$B$7:$B$300,0)),"") -> 414.67575 | G69: =IFERROR(INDEX('Saloni Mehra'!$M$7:$M$300,MATCH($A69,'Saloni Mehra'!$B$7:$B$300,0)),"") | H69: =IFERROR(INDEX('Vidushi Malhotra'!$M$7:$M$300,MATCH($A69,'Vidushi Malhotra'!$B$7:$B$300,0)),"") -> 450.60526 | I69: =IFERROR(INDEX('Dr Umesh Choudhry'!$M$7:$M$300,MATCH($A69,'Dr Umesh Choudhry'!$B$7:$B$300,0)),"") -> 442.79974 | J69: =IFERROR(INDEX(DA!$M$7:$M$300,MATCH($A69,DA!$B$7:$B$300,0)),"") -> 445 | K69: Close 22.10.2026 (Screener.in) | L69: 437.3 | M69: =IF(AND(ISNUMBER(B69),ISNUMBER(L69),N(L69)>0),B69/L69-1,"") -> -0.011090784
A70: PSL Ltd (formerly PSL Holdings Ltd) | C70: =IF(ISNUMBER(B70),B70,IF(ISNUMBER(E70),E70,IF(ISNUMBER(F70),F70,IF(ISNUMBER(G70),G70,IF(ISNUMBER(H70),H70,IF(ISNUMBER(I70),I70,IF(ISNUMBER(J70),J70,""))))))) | D70: =IF(ISNUMBER(B70),IF(K70<>"",K70,"Manual override"),IF(ISNUMBER(E70),"Gautam stmt – 23.10",IF(ISNUMBER(F70),"Manish Shilpa stmt – live 23.10",IF(ISNUMBER(G70),"Saloni stmt – 20.10 (stale)",IF(ISNUMBER(H70),"Vidushi stmt – LTP 05.10",IF(ISNUMBER(I70),"Umesh stmt – NSE live 09.10",IF(ISNUMBER(J70),"DA stmt – older (stale)","No price on any statement"))))))) -> No price on any statement | E70: =IFERROR(INDEX(Gautam!$M$7:$M$300,MATCH($A70,Gautam!$B$7:$B$300,0)),"") | F70: =IFERROR(INDEX('Manish Shilpa'!$M$7:$M$300,MATCH($A70,'Manish Shilpa'!$B$7:$B$300,0)),"") | G70: =IFERROR(INDEX('Saloni Mehra'!$M$7:$M$300,MATCH($A70,'Saloni Mehra'!$B$7:$B$300,0)),"") | H70: =IFERROR(INDEX('Vidushi Malhotra'!$M$7:$M$300,MATCH($A70,'Vidushi Malhotra'!$B$7:$B$300,0)),"") | I70: =IFERROR(INDEX('Dr Umesh Choudhry'!$M$7:$M$300,MATCH($A70,'Dr Umesh Choudhry'!$B$7:$B$300,0)),"") | J70: =IFERROR(INDEX(DA!$M$7:$M$300,MATCH($A70,DA!$B$7:$B$300,0)),"") | K70: No exchange close found – statement price used | M70: =IF(AND(ISNUMBER(B70),ISNUMBER(L70),N(L70)>0),B70/L70-1,"")
A71: Rategain Travel Technologies Ltd | B71: 788.1 | C71: =IF(ISNUMBER(B71),B71,IF(ISNUMBER(E71),E71,IF(ISNUMBER(F71),F71,IF(ISNUMBER(G71),G71,IF(ISNUMBER(H71),H71,IF(ISNUMBER(I71),I71,IF(ISNUMBER(J71),J71,""))))))) -> 788.1 | D71: =IF(ISNUMBER(B71),IF(K71<>"",K71,"Manual override"),IF(ISNUMBER(E71),"Gautam stmt – 23.10",IF(ISNUMBER(F71),"Manish Shilpa stmt – live 23.10",IF(ISNUMBER(G71),"Saloni stmt – 20.10 (stale)",IF(ISNUMBER(H71),"Vidushi stmt – LTP 05.10",IF(ISNUMBER(I71),"Umesh stmt – NSE live 09.10",IF(ISNUMBER(J71),"DA stmt – older (stale)","No price on any statement"))))))) -> Close 22.10.2026 (Screener.in) | E71: =IFERROR(INDEX(Gautam!$M$7:$M$300,MATCH($A71,Gautam!$B$7:$B$300,0)),"") -> 789 | F71: =IFERROR(INDEX('Manish Shilpa'!$M$7:$M$300,MATCH($A71,'Manish Shilpa'!$B$7:$B$300,0)),"") -> 763 | G71: =IFERROR(INDEX('Saloni Mehra'!$M$7:$M$300,MATCH($A71,'Saloni Mehra'!$B$7:$B$300,0)),"") | H71: =IFERROR(INDEX('Vidushi Malhotra'!$M$7:$M$300,MATCH($A71,'Vidushi Malhotra'!$B$7:$B$300,0)),"") | I71: =IFERROR(INDEX('Dr Umesh Choudhry'!$M$7:$M$300,MATCH($A71,'Dr Umesh Choudhry'!$B$7:$B$300,0)),"") -> 840.875 | J71: =IFERROR(INDEX(DA!$M$7:$M$300,MATCH($A71,DA!$B$7:$B$300,0)),"") | K71: Close 22.10.2026 (Screener.in) | L71: 779.7 | M71: =IF(AND(ISNUMBER(B71),ISNUMBER(L71),N(L71)>0),B71/L71-1,"") -> 0.010773374
A72: REC Ltd | B72: 301.1 | C72: =IF(ISNUMBER(B72),B72,IF(ISNUMBER(E72),E72,IF(ISNUMBER(F72),F72,IF(ISNUMBER(G72),G72,IF(ISNUMBER(H72),H72,IF(ISNUMBER(I72),I72,IF(ISNUMBER(J72),J72,""))))))) -> 301.1 | D72: =IF(ISNUMBER(B72),IF(K72<>"",K72,"Manual override"),IF(ISNUMBER(E72),"Gautam stmt – 23.10",IF(ISNUMBER(F72),"Manish Shilpa stmt – live 23.10",IF(ISNUMBER(G72),"Saloni stmt – 20.10 (stale)",IF(ISNUMBER(H72),"Vidushi stmt – LTP 05.10",IF(ISNUMBER(I72),"Umesh stmt – NSE live 09.10",IF(ISNUMBER(J72),"DA stmt – older (stale)","No price on any statement"))))))) -> Close 22.10.2026 (Screener.in) | E72: =IFERROR(INDEX(Gautam!$M$7:$M$300,MATCH($A72,Gautam!$B$7:$B$300,0)),"") | F72: =IFERROR(INDEX('Manish Shilpa'!$M$7:$M$300,MATCH($A72,'Manish Shilpa'!$B$7:$B$300,0)),"") | G72: =IFERROR(INDEX('Saloni Mehra'!$M$7:$M$300,MATCH($A72,'Saloni Mehra'!$B$7:$B$300,0)),"") | H72: =IFERROR(INDEX('Vidushi Malhotra'!$M$7:$M$300,MATCH($A72,'Vidushi Malhotra'!$B$7:$B$300,0)),"") | I72: =IFERROR(INDEX('Dr Umesh Choudhry'!$M$7:$M$300,MATCH($A72,'Dr Umesh Choudhry'!$B$7:$B$300,0)),"") | J72: =IFERROR(INDEX(DA!$M$7:$M$300,MATCH($A72,DA!$B$7:$B$300,0)),"") -> 313 | K72: Close 22.10.2026 (Screener.in) | L72: 302.5 | M72: =IF(AND(ISNUMBER(B72),ISNUMBER(L72),N(L72)>0),B72/L72-1,"") -> -0.0046280992
A73: Reliance Industries Ltd | B73: 1184.5 | C73: =IF(ISNUMBER(B73),B73,IF(ISNUMBER(E73),E73,IF(ISNUMBER(F73),F73,IF(ISNUMBER(G73),G73,IF(ISNUMBER(H73),H73,IF(ISNUMBER(I73),I73,IF(ISNUMBER(J73),J73,""))))))) -> 1184.5 | D73: =IF(ISNUMBER(B73),IF(K73<>"",K73,"Manual override"),IF(ISNUMBER(E73),"Gautam stmt – 23.10",IF(ISNUMBER(F73),"Manish Shilpa stmt – live 23.10",IF(ISNUMBER(G73),"Saloni stmt – 20.10 (stale)",IF(ISNUMBER(H73),"Vidushi stmt – LTP 05.10",IF(ISNUMBER(I73),"Umesh stmt – NSE live 09.10",IF(ISNUMBER(J73),"DA stmt – older (stale)","No price on any statement"))))))) -> Close 22.10.2026 (Screener.in) | E73: =IFERROR(INDEX(Gautam!$M$7:$M$300,MATCH($A73,Gautam!$B$7:$B$300,0)),"") | F73: =IFERROR(INDEX('Manish Shilpa'!$M$7:$M$300,MATCH($A73,'Manish Shilpa'!$B$7:$B$300,0)),"") -> 1172.6875 | G73: =IFERROR(INDEX('Saloni Mehra'!$M$7:$M$300,MATCH($A73,'Saloni Mehra'!$B$7:$B$300,0)),"") | H73: =IFERROR(INDEX('Vidushi Malhotra'!$M$7:$M$300,MATCH($A73,'Vidushi Malhotra'!$B$7:$B$300,0)),"") | I73: =IFERROR(INDEX('Dr Umesh Choudhry'!$M$7:$M$300,MATCH($A73,'Dr Umesh Choudhry'!$B$7:$B$300,0)),"") | J73: =IFERROR(INDEX(DA!$M$7:$M$300,MATCH($A73,DA!$B$7:$B$300,0)),"") -> 1258 | K73: Close 22.10.2026 (Screener.in) | L73: 1209 | M73: =IF(AND(ISNUMBER(B73),ISNUMBER(L73),N(L73)>0),B73/L73-1,"") -> -0.020264682
A74: RITES Ltd | B74: 196.09 | C74: =IF(ISNUMBER(B74),B74,IF(ISNUMBER(E74),E74,IF(ISNUMBER(F74),F74,IF(ISNUMBER(G74),G74,IF(ISNUMBER(H74),H74,IF(ISNUMBER(I74),I74,IF(ISNUMBER(J74),J74,""))))))) -> 196.09 | D74: =IF(ISNUMBER(B74),IF(K74<>"",K74,"Manual override"),IF(ISNUMBER(E74),"Gautam stmt – 23.10",IF(ISNUMBER(F74),"Manish Shilpa stmt – live 23.10",IF(ISNUMBER(G74),"Saloni stmt – 20.10 (stale)",IF(ISNUMBER(H74),"Vidushi stmt – LTP 05.10",IF(ISNUMBER(I74),"Umesh stmt – NSE live 09.10",IF(ISNUMBER(J74),"DA stmt – older (stale)","No price on any statement"))))))) -> Close 22.10.2026 (Screener.in) | E74: =IFERROR(INDEX(Gautam!$M$7:$M$300,MATCH($A74,Gautam!$B$7:$B$300,0)),"") | F74: =IFERROR(INDEX('Manish Shilpa'!$M$7:$M$300,MATCH($A74,'Manish Shilpa'!$B$7:$B$300,0)),"") | G74: =IFERROR(INDEX('Saloni Mehra'!$M$7:$M$300,MATCH($A74,'Saloni Mehra'!$B$7:$B$300,0)),"") | H74: =IFERROR(INDEX('Vidushi Malhotra'!$M$7:$M$300,MATCH($A74,'Vidushi Malhotra'!$B$7:$B$300,0)),"") | I74: =IFERROR(INDEX('Dr Umesh Choudhry'!$M$7:$M$300,MATCH($A74,'Dr Umesh Choudhry'!$B$7:$B$300,0)),"") | J74: =IFERROR(INDEX(DA!$M$7:$M$300,MATCH($A74,DA!$B$7:$B$300,0)),"") -> 209 | K74: Close 22.10.2026 (Screener.in) | L74: 197.42 | M74: =IF(AND(ISNUMBER(B74),ISNUMBER(L74),N(L74)>0),B74/L74-1,"") -> -0.0067369061
A75: Shakti Pumps (India) Ltd | B75: 400.65 | C75: =IF(ISNUMBER(B75),B75,IF(ISNUMBER(E75),E75,IF(ISNUMBER(F75),F75,IF(ISNUMBER(G75),G75,IF(ISNUMBER(H75),H75,IF(ISNUMBER(I75),I75,IF(ISNUMBER(J75),J75,""))))))) -> 400.65 | D75: =IF(ISNUMBER(B75),IF(K75<>"",K75,"Manual override"),IF(ISNUMBER(E75),"Gautam stmt – 23.10",IF(ISNUMBER(F75),"Manish Shilpa stmt – live 23.10",IF(ISNUMBER(G75),"Saloni stmt – 20.10 (stale)",IF(ISNUMBER(H75),"Vidushi stmt – LTP 05.10",IF(ISNUMBER(I75),"Umesh stmt – NSE live 09.10",IF(ISNUMBER(J75),"DA stmt – older (stale)","No price on any statement"))))))) -> Close 22.10.2026 (Screener.in) | E75: =IFERROR(INDEX(Gautam!$M$7:$M$300,MATCH($A75,Gautam!$B$7:$B$300,0)),"") | F75: =IFERROR(INDEX('Manish Shilpa'!$M$7:$M$300,MATCH($A75,'Manish Shilpa'!$B$7:$B$300,0)),"") | G75: =IFERROR(INDEX('Saloni Mehra'!$M$7:$M$300,MATCH($A75,'Saloni Mehra'!$B$7:$B$300,0)),"") | H75: =IFERROR(INDEX('Vidushi Malhotra'!$M$7:$M$300,MATCH($A75,'Vidushi Malhotra'!$B$7:$B$300,0)),"") | I75: =IFERROR(INDEX('Dr Umesh Choudhry'!$M$7:$M$300,MATCH($A75,'Dr Umesh Choudhry'!$B$7:$B$300,0)),"") | J75: =IFERROR(INDEX(DA!$M$7:$M$300,MATCH($A75,DA!$B$7:$B$300,0)),"") -> 494 | K75: Close 22.10.2026 (Screener.in) | L75: 403.8 | M75: =IF(AND(ISNUMBER(B75),ISNUMBER(L75),N(L75)>0),B75/L75-1,"") -> -0.0078008915
A76: Shriram Properties Ltd | B76: 65.13 | C76: =IF(ISNUMBER(B76),B76,IF(ISNUMBER(E76),E76,IF(ISNUMBER(F76),F76,IF(ISNUMBER(G76),G76,IF(ISNUMBER(H76),H76,IF(ISNUMBER(I76),I76,IF(ISNUMBER(J76),J76,""))))))) -> 65.13 | D76: =IF(ISNUMBER(B76),IF(K76<>"",K76,"Manual override"),IF(ISNUMBER(E76),"Gautam stmt – 23.10",IF(ISNUMBER(F76),"Manish Shilpa stmt – live 23.10",IF(ISNUMBER(G76),"Saloni stmt – 20.10 (stale)",IF(ISNUMBER(H76),"Vidushi stmt – LTP 05.10",IF(ISNUMBER(I76),"Umesh stmt – NSE live 09.10",IF(ISNUMBER(J76),"DA stmt – older (stale)","No price on any statement"))))))) -> Close 22.10.2026 (Screener.in) | E76: =IFERROR(INDEX(Gautam!$M$7:$M$300,MATCH($A76,Gautam!$B$7:$B$300,0)),"") -> 67.7 | F76: =IFERROR(INDEX('Manish Shilpa'!$M$7:$M$300,MATCH($A76,'Manish Shilpa'!$B$7:$B$300,0)),"") | G76: =IFERROR(INDEX('Saloni Mehra'!$M$7:$M$300,MATCH($A76,'Saloni Mehra'!$B$7:$B$300,0)),"") | H76: =IFERROR(INDEX('Vidushi Malhotra'!$M$7:$M$300,MATCH($A76,'Vidushi Malhotra'!$B$7:$B$300,0)),"") | I76: =IFERROR(INDEX('Dr Umesh Choudhry'!$M$7:$M$300,MATCH($A76,'Dr Umesh Choudhry'!$B$7:$B$300,0)),"") | J76: =IFERROR(INDEX(DA!$M$7:$M$300,MATCH($A76,DA!$B$7:$B$300,0)),"") | K76: Close 22.10.2026 (Screener.in) | L76: 66.01 | M76: =IF(AND(ISNUMBER(B76),ISNUMBER(L76),N(L76)>0),B76/L76-1,"") -> -0.013331313
A77: Sonata Software Ltd | B77: 239.75 | C77: =IF(ISNUMBER(B77),B77,IF(ISNUMBER(E77),E77,IF(ISNUMBER(F77),F77,IF(ISNUMBER(G77),G77,IF(ISNUMBER(H77),H77,IF(ISNUMBER(I77),I77,IF(ISNUMBER(J77),J77,""))))))) -> 239.75 | D77: =IF(ISNUMBER(B77),IF(K77<>"",K77,"Manual override"),IF(ISNUMBER(E77),"Gautam stmt – 23.10",IF(ISNUMBER(F77),"Manish Shilpa stmt – live 23.10",IF(ISNUMBER(G77),"Saloni stmt – 20.10 (stale)",IF(ISNUMBER(H77),"Vidushi stmt – LTP 05.10",IF(ISNUMBER(I77),"Umesh stmt – NSE live 09.10",IF(ISNUMBER(J77),"DA stmt – older (stale)","No price on any statement"))))))) -> Close 22.10.2026 (Screener.in) | E77: =IFERROR(INDEX(Gautam!$M$7:$M$300,MATCH($A77,Gautam!$B$7:$B$300,0)),"") | F77: =IFERROR(INDEX('Manish Shilpa'!$M$7:$M$300,MATCH($A77,'Manish Shilpa'!$B$7:$B$300,0)),"") | G77: =IFERROR(INDEX('Saloni Mehra'!$M$7:$M$300,MATCH($A77,'Saloni Mehra'!$B$7:$B$300,0)),"") | H77: =IFERROR(INDEX('Vidushi Malhotra'!$M$7:$M$300,MATCH($A77,'Vidushi Malhotra'!$B$7:$B$300,0)),"") | I77: =IFERROR(INDEX('Dr Umesh Choudhry'!$M$7:$M$300,MATCH($A77,'Dr Umesh Choudhry'!$B$7:$B$300,0)),"") | J77: =IFERROR(INDEX(DA!$M$7:$M$300,MATCH($A77,DA!$B$7:$B$300,0)),"") -> 266 | K77: Close 22.10.2026 (Screener.in) | L77: 240.5 | M77: =IF(AND(ISNUMBER(B77),ISNUMBER(L77),N(L77)>0),B77/L77-1,"") -> -0.0031185031
A78: Syngene International Ltd | B78: 372.5 | C78: =IF(ISNUMBER(B78),B78,IF(ISNUMBER(E78),E78,IF(ISNUMBER(F78),F78,IF(ISNUMBER(G78),G78,IF(ISNUMBER(H78),H78,IF(ISNUMBER(I78),I78,IF(ISNUMBER(J78),J78,""))))))) -> 372.5 | D78: =IF(ISNUMBER(B78),IF(K78<>"",K78,"Manual override"),IF(ISNUMBER(E78),"Gautam stmt – 23.10",IF(ISNUMBER(F78),"Manish Shilpa stmt – live 23.10",IF(ISNUMBER(G78),"Saloni stmt – 20.10 (stale)",IF(ISNUMBER(H78),"Vidushi stmt – LTP 05.10",IF(ISNUMBER(I78),"Umesh stmt – NSE live 09.10",IF(ISNUMBER(J78),"DA stmt – older (stale)","No price on any statement"))))))) -> Close 22.10.2026 (Screener.in) | E78: =IFERROR(INDEX(Gautam!$M$7:$M$300,MATCH($A78,Gautam!$B$7:$B$300,0)),"") | F78: =IFERROR(INDEX('Manish Shilpa'!$M$7:$M$300,MATCH($A78,'Manish Shilpa'!$B$7:$B$300,0)),"") | G78: =IFERROR(INDEX('Saloni Mehra'!$M$7:$M$300,MATCH($A78,'Saloni Mehra'!$B$7:$B$300,0)),"") | H78: =IFERROR(INDEX('Vidushi Malhotra'!$M$7:$M$300,MATCH($A78,'Vidushi Malhotra'!$B$7:$B$300,0)),"") | I78: =IFERROR(INDEX('Dr Umesh Choudhry'!$M$7:$M$300,MATCH($A78,'Dr Umesh Choudhry'!$B$7:$B$300,0)),"") | J78: =IFERROR(INDEX(DA!$M$7:$M$300,MATCH($A78,DA!$B$7:$B$300,0)),"") -> 383 | K78: Close 22.10.2026 (Screener.in) | L78: 376.45 | M78: =IF(AND(ISNUMBER(B78),ISNUMBER(L78),N(L78)>0),B78/L78-1,"") -> -0.010492761
A79: Tanla Platforms Ltd | B79: 581.3 | C79: =IF(ISNUMBER(B79),B79,IF(ISNUMBER(E79),E79,IF(ISNUMBER(F79),F79,IF(ISNUMBER(G79),G79,IF(ISNUMBER(H79),H79,IF(ISNUMBER(I79),I79,IF(ISNUMBER(J79),J79,""))))))) -> 581.3 | D79: =IF(ISNUMBER(B79),IF(K79<>"",K79,"Manual override"),IF(ISNUMBER(E79),"Gautam stmt – 23.10",IF(ISNUMBER(F79),"Manish Shilpa stmt – live 23.10",IF(ISNUMBER(G79),"Saloni stmt – 20.10 (stale)",IF(ISNUMBER(H79),"Vidushi stmt – LTP 05.10",IF(ISNUMBER(I79),"Umesh stmt – NSE live 09.10",IF(ISNUMBER(J79),"DA stmt – older (stale)","No price on any statement"))))))) -> Close 22.10.2026 (Screener.in) | E79: =IFERROR(INDEX(Gautam!$M$7:$M$300,MATCH($A79,Gautam!$B$7:$B$300,0)),"") | F79: =IFERROR(INDEX('Manish Shilpa'!$M$7:$M$300,MATCH($A79,'Manish Shilpa'!$B$7:$B$300,0)),"") -> 563.93939 | G79: =IFERROR(INDEX('Saloni Mehra'!$M$7:$M$300,MATCH($A79,'Saloni Mehra'!$B$7:$B$300,0)),"") | H79: =IFERROR(INDEX('Vidushi Malhotra'!$M$7:$M$300,MATCH($A79,'Vidushi Malhotra'!$B$7:$B$300,0)),"") | I79: =IFERROR(INDEX('Dr Umesh Choudhry'!$M$7:$M$300,MATCH($A79,'Dr Umesh Choudhry'!$B$7:$B$300,0)),"") | J79: =IFERROR(INDEX(DA!$M$7:$M$300,MATCH($A79,DA!$B$7:$B$300,0)),"") | K79: Close 22.10.2026 (Screener.in) | L79: 562.1 | M79: =IF(AND(ISNUMBER(B79),ISNUMBER(L79),N(L79)>0),B79/L79-1,"") -> 0.034157623
A80: Tata Consultancy Services Ltd | B80: 2506.9 | C80: =IF(ISNUMBER(B80),B80,IF(ISNUMBER(E80),E80,IF(ISNUMBER(F80),F80,IF(ISNUMBER(G80),G80,IF(ISNUMBER(H80),H80,IF(ISNUMBER(I80),I80,IF(ISNUMBER(J80),J80,""))))))) -> 2506.9 | D80: =IF(ISNUMBER(B80),IF(K80<>"",K80,"Manual override"),IF(ISNUMBER(E80),"Gautam stmt – 23.10",IF(ISNUMBER(F80),"Manish Shilpa stmt – live 23.10",IF(ISNUMBER(G80),"Saloni stmt – 20.10 (stale)",IF(ISNUMBER(H80),"Vidushi stmt – LTP 05.10",IF(ISNUMBER(I80),"Umesh stmt – NSE live 09.10",IF(ISNUMBER(J80),"DA stmt – older (stale)","No price on any statement"))))))) -> Close 22.10.2026 (Screener.in) | E80: =IFERROR(INDEX(Gautam!$M$7:$M$300,MATCH($A80,Gautam!$B$7:$B$300,0)),"") -> 2507 | F80: =IFERROR(INDEX('Manish Shilpa'!$M$7:$M$300,MATCH($A80,'Manish Shilpa'!$B$7:$B$300,0)),"") -> 2556.1034 | G80: =IFERROR(INDEX('Saloni Mehra'!$M$7:$M$300,MATCH($A80,'Saloni Mehra'!$B$7:$B$300,0)),"") -> 2460.9016 | H80: =IFERROR(INDEX('Vidushi Malhotra'!$M$7:$M$300,MATCH($A80,'Vidushi Malhotra'!$B$7:$B$300,0)),"") | I80: =IFERROR(INDEX('Dr Umesh Choudhry'!$M$7:$M$300,MATCH($A80,'Dr Umesh Choudhry'!$B$7:$B$300,0)),"") -> 2178.1034 | J80: =IFERROR(INDEX(DA!$M$7:$M$300,MATCH($A80,DA!$B$7:$B$300,0)),"") -> 2201 | K80: Close 22.10.2026 (Screener.in) | L80: 2529 | M80: =IF(AND(ISNUMBER(B80),ISNUMBER(L80),N(L80)>0),B80/L80-1,"") -> -0.0087386319
A81: Tata Elxsi Ltd | B81: 3846.8 | C81: =IF(ISNUMBER(B81),B81,IF(ISNUMBER(E81),E81,IF(ISNUMBER(F81),F81,IF(ISNUMBER(G81),G81,IF(ISNUMBER(H81),H81,IF(ISNUMBER(I81),I81,IF(ISNUMBER(J81),J81,""))))))) -> 3846.8 | D81: =IF(ISNUMBER(B81),IF(K81<>"",K81,"Manual override"),IF(ISNUMBER(E81),"Gautam stmt – 23.10",IF(ISNUMBER(F81),"Manish Shilpa stmt – live 23.10",IF(ISNUMBER(G81),"Saloni stmt – 20.10 (stale)",IF(ISNUMBER(H81),"Vidushi stmt – LTP 05.10",IF(ISNUMBER(I81),"Umesh stmt – NSE live 09.10",IF(ISNUMBER(J81),"DA stmt – older (stale)","No price on any statement"))))))) -> Close 22.10.2026 (Screener.in) | E81: =IFERROR(INDEX(Gautam!$M$7:$M$300,MATCH($A81,Gautam!$B$7:$B$300,0)),"") -> 3847 | F81: =IFERROR(INDEX('Manish Shilpa'!$M$7:$M$300,MATCH($A81,'Manish Shilpa'!$B$7:$B$300,0)),"") -> 3764.6875 | G81: =IFERROR(INDEX('Saloni Mehra'!$M$7:$M$300,MATCH($A81,'Saloni Mehra'!$B$7:$B$300,0)),"") | H81: =IFERROR(INDEX('Vidushi Malhotra'!$M$7:$M$300,MATCH($A81,'Vidushi Malhotra'!$B$7:$B$300,0)),"") | I81: =IFERROR(INDEX('Dr Umesh Choudhry'!$M$7:$M$300,MATCH($A81,'Dr Umesh Choudhry'!$B$7:$B$300,0)),"") -> 3071.4091 | J81: =IFERROR(INDEX(DA!$M$7:$M$300,MATCH($A81,DA!$B$7:$B$300,0)),"") -> 3383 | K81: Close 22.10.2026 (Screener.in) | L81: 3848.6 | M81: =IF(AND(ISNUMBER(B81),ISNUMBER(L81),N(L81)>0),B81/L81-1,"") -> -0.00046770254
A82: Titan Company Ltd | B82: 4350 | C82: =IF(ISNUMBER(B82),B82,IF(ISNUMBER(E82),E82,IF(ISNUMBER(F82),F82,IF(ISNUMBER(G82),G82,IF(ISNUMBER(H82),H82,IF(ISNUMBER(I82),I82,IF(ISNUMBER(J82),J82,""))))))) -> 4350 | D82: =IF(ISNUMBER(B82),IF(K82<>"",K82,"Manual override"),IF(ISNUMBER(E82),"Gautam stmt – 23.10",IF(ISNUMBER(F82),"Manish Shilpa stmt – live 23.10",IF(ISNUMBER(G82),"Saloni stmt – 20.10 (stale)",IF(ISNUMBER(H82),"Vidushi stmt – LTP 05.10",IF(ISNUMBER(I82),"Umesh stmt – NSE live 09.10",IF(ISNUMBER(J82),"DA stmt – older (stale)","No price on any statement"))))))) -> Close 22.10.2026 (Screener.in) | E82: =IFERROR(INDEX(Gautam!$M$7:$M$300,MATCH($A82,Gautam!$B$7:$B$300,0)),"") -> 4350 | F82: =IFERROR(INDEX('Manish Shilpa'!$M$7:$M$300,MATCH($A82,'Manish Shilpa'!$B$7:$B$300,0)),"") -> 4246.8182 | G82: =IFERROR(INDEX('Saloni Mehra'!$M$7:$M$300,MATCH($A82,'Saloni Mehra'!$B$7:$B$300,0)),"") | H82: =IFERROR(INDEX('Vidushi Malhotra'!$M$7:$M$300,MATCH($A82,'Vidushi Malhotra'!$B$7:$B$300,0)),"") -> 4570 | I82: =IFERROR(INDEX('Dr Umesh Choudhry'!$M$7:$M$300,MATCH($A82,'Dr Umesh Choudhry'!$B$7:$B$300,0)),"") -> 4372 | J82: =IFERROR(INDEX(DA!$M$7:$M$300,MATCH($A82,DA!$B$7:$B$300,0)),"") -> 5010 | K82: Close 22.10.2026 (Screener.in) | L82: 4380.9 | M82: =IF(AND(ISNUMBER(B82),ISNUMBER(L82),N(L82)>0),B82/L82-1,"") -> -0.0070533452
A83: Trent Ltd | B83: 2775.8 | C83: =IF(ISNUMBER(B83),B83,IF(ISNUMBER(E83),E83,IF(ISNUMBER(F83),F83,IF(ISNUMBER(G83),G83,IF(ISNUMBER(H83),H83,IF(ISNUMBER(I83),I83,IF(ISNUMBER(J83),J83,""))))))) -> 2775.8 | D83: =IF(ISNUMBER(B83),IF(K83<>"",K83,"Manual override"),IF(ISNUMBER(E83),"Gautam stmt – 23.10",IF(ISNUMBER(F83),"Manish Shilpa stmt – live 23.10",IF(ISNUMBER(G83),"Saloni stmt – 20.10 (stale)",IF(ISNUMBER(H83),"Vidushi stmt – LTP 05.10",IF(ISNUMBER(I83),"Umesh stmt – NSE live 09.10",IF(ISNUMBER(J83),"DA stmt – older (stale)","No price on any statement"))))))) -> Close 22.10.2026 (Screener.in) | E83: =IFERROR(INDEX(Gautam!$M$7:$M$300,MATCH($A83,Gautam!$B$7:$B$300,0)),"") -> 2776 | F83: =IFERROR(INDEX('Manish Shilpa'!$M$7:$M$300,MATCH($A83,'Manish Shilpa'!$B$7:$B$300,0)),"") -> 2713 | G83: =IFERROR(INDEX('Saloni Mehra'!$M$7:$M$300,MATCH($A83,'Saloni Mehra'!$B$7:$B$300,0)),"") | H83: =IFERROR(INDEX('Vidushi Malhotra'!$M$7:$M$300,MATCH($A83,'Vidushi Malhotra'!$B$7:$B$300,0)),"") | I83: =IFERROR(INDEX('Dr Umesh Choudhry'!$M$7:$M$300,MATCH($A83,'Dr Umesh Choudhry'!$B$7:$B$300,0)),"") -> 2910 | J83: =IFERROR(INDEX(DA!$M$7:$M$300,MATCH($A83,DA!$B$7:$B$300,0)),"") -> 2802 | K83: Close 22.10.2026 (Screener.in) | L83: 2822 | M83: =IF(AND(ISNUMBER(B83),ISNUMBER(L83),N(L83)>0),B83/L83-1,"") -> -0.016371368
A84: UTI Nifty 50 Index Fund - Growth | C84: =IF(ISNUMBER(B84),B84,IF(ISNUMBER(E84),E84,IF(ISNUMBER(F84),F84,IF(ISNUMBER(G84),G84,IF(ISNUMBER(H84),H84,IF(ISNUMBER(I84),I84,IF(ISNUMBER(J84),J84,""))))))) -> 157.3291 | D84: =IF(ISNUMBER(B84),IF(K84<>"",K84,"Manual override"),IF(ISNUMBER(E84),"Gautam stmt – 23.10",IF(ISNUMBER(F84),"Manish Shilpa stmt – live 23.10",IF(ISNUMBER(G84),"Saloni stmt – 20.10 (stale)",IF(ISNUMBER(H84),"Vidushi stmt – LTP 05.10",IF(ISNUMBER(I84),"Umesh stmt – NSE live 09.10",IF(ISNUMBER(J84),"DA stmt – older (stale)","No price on any statement"))))))) -> Manish Shilpa stmt – live 23.10 | E84: =IFERROR(INDEX(Gautam!$M$7:$M$300,MATCH($A84,Gautam!$B$7:$B$300,0)),"") | F84: =IFERROR(INDEX('Manish Shilpa'!$M$7:$M$300,MATCH($A84,'Manish Shilpa'!$B$7:$B$300,0)),"") -> 157.3291 | G84: =IFERROR(INDEX('Saloni Mehra'!$M$7:$M$300,MATCH($A84,'Saloni Mehra'!$B$7:$B$300,0)),"") | H84: =IFERROR(INDEX('Vidushi Malhotra'!$M$7:$M$300,MATCH($A84,'Vidushi Malhotra'!$B$7:$B$300,0)),"") | I84: =IFERROR(INDEX('Dr Umesh Choudhry'!$M$7:$M$300,MATCH($A84,'Dr Umesh Choudhry'!$B$7:$B$300,0)),"") | J84: =IFERROR(INDEX(DA!$M$7:$M$300,MATCH($A84,DA!$B$7:$B$300,0)),"") | K84: No exchange close found – statement price used | M84: =IF(AND(ISNUMBER(B84),ISNUMBER(L84),N(L84)>0),B84/L84-1,"")
A85: Utkarsh SFB – Rights Entitlement | C85: =IF(ISNUMBER(B85),B85,IF(ISNUMBER(E85),E85,IF(ISNUMBER(F85),F85,IF(ISNUMBER(G85),G85,IF(ISNUMBER(H85),H85,IF(ISNUMBER(I85),I85,IF(ISNUMBER(J85),J85,""))))))) -> 4 | D85: =IF(ISNUMBER(B85),IF(K85<>"",K85,"Manual override"),IF(ISNUMBER(E85),"Gautam stmt – 23.10",IF(ISNUMBER(F85),"Manish Shilpa stmt – live 23.10",IF(ISNUMBER(G85),"Saloni stmt – 20.10 (stale)",IF(ISNUMBER(H85),"Vidushi stmt – LTP 05.10",IF(ISNUMBER(I85),"Umesh stmt – NSE live 09.10",IF(ISNUMBER(J85),"DA stmt – older (stale)","No price on any statement"))))))) -> DA stmt – older (stale) | E85: =IFERROR(INDEX(Gautam!$M$7:$M$300,MATCH($A85,Gautam!$B$7:$B$300,0)),"") | F85: =IFERROR(INDEX('Manish Shilpa'!$M$7:$M$300,MATCH($A85,'Manish Shilpa'!$B$7:$B$300,0)),"") | G85: =IFERROR(INDEX('Saloni Mehra'!$M$7:$M$300,MATCH($A85,'Saloni Mehra'!$B$7:$B$300,0)),"") | H85: =IFERROR(INDEX('Vidushi Malhotra'!$M$7:$M$300,MATCH($A85,'Vidushi Malhotra'!$B$7:$B$300,0)),"") | I85: =IFERROR(INDEX('Dr Umesh Choudhry'!$M$7:$M$300,MATCH($A85,'Dr Umesh Choudhry'!$B$7:$B$300,0)),"") | J85: =IFERROR(INDEX(DA!$M$7:$M$300,MATCH($A85,DA!$B$7:$B$300,0)),"") -> 4 | K85: No exchange close found – statement price used | M85: =IF(AND(ISNUMBER(B85),ISNUMBER(L85),N(L85)>0),B85/L85-1,"")
A86: Utkarsh Small Finance Bank Ltd | B86: 12.17 | C86: =IF(ISNUMBER(B86),B86,IF(ISNUMBER(E86),E86,IF(ISNUMBER(F86),F86,IF(ISNUMBER(G86),G86,IF(ISNUMBER(H86),H86,IF(ISNUMBER(I86),I86,IF(ISNUMBER(J86),J86,""))))))) -> 12.17 | D86: =IF(ISNUMBER(B86),IF(K86<>"",K86,"Manual override"),IF(ISNUMBER(E86),"Gautam stmt – 23.10",IF(ISNUMBER(F86),"Manish Shilpa stmt – live 23.10",IF(ISNUMBER(G86),"Saloni stmt – 20.10 (stale)",IF(ISNUMBER(H86),"Vidushi stmt – LTP 05.10",IF(ISNUMBER(I86),"Umesh stmt – NSE live 09.10",IF(ISNUMBER(J86),"DA stmt – older (stale)","No price on any statement"))))))) -> Close 22.10.2026 (Screener.in) | E86: =IFERROR(INDEX(Gautam!$M$7:$M$300,MATCH($A86,Gautam!$B$7:$B$300,0)),"") | F86: =IFERROR(INDEX('Manish Shilpa'!$M$7:$M$300,MATCH($A86,'Manish Shilpa'!$B$7:$B$300,0)),"") | G86: =IFERROR(INDEX('Saloni Mehra'!$M$7:$M$300,MATCH($A86,'Saloni Mehra'!$B$7:$B$300,0)),"") | H86: =IFERROR(INDEX('Vidushi Malhotra'!$M$7:$M$300,MATCH($A86,'Vidushi Malhotra'!$B$7:$B$300,0)),"") | I86: =IFERROR(INDEX('Dr Umesh Choudhry'!$M$7:$M$300,MATCH($A86,'Dr Umesh Choudhry'!$B$7:$B$300,0)),"") | J86: =IFERROR(INDEX(DA!$M$7:$M$300,MATCH($A86,DA!$B$7:$B$300,0)),"") -> 14.5 | K86: Close 22.10.2026 (Screener.in) | L86: 12.55 | M86: =IF(AND(ISNUMBER(B86),ISNUMBER(L86),N(L86)>0),B86/L86-1,"") -> -0.030278884
A87: Vaibhav Global Ltd | B87: 195.22 | C87: =IF(ISNUMBER(B87),B87,IF(ISNUMBER(E87),E87,IF(ISNUMBER(F87),F87,IF(ISNUMBER(G87),G87,IF(ISNUMBER(H87),H87,IF(ISNUMBER(I87),I87,IF(ISNUMBER(J87),J87,""))))))) -> 195.22 | D87: =IF(ISNUMBER(B87),IF(K87<>"",K87,"Manual override"),IF(ISNUMBER(E87),"Gautam stmt – 23.10",IF(ISNUMBER(F87),"Manish Shilpa stmt – live 23.10",IF(ISNUMBER(G87),"Saloni stmt – 20.10 (stale)",IF(ISNUMBER(H87),"Vidushi stmt – LTP 05.10",IF(ISNUMBER(I87),"Umesh stmt – NSE live 09.10",IF(ISNUMBER(J87),"DA stmt – older (stale)","No price on any statement"))))))) -> Close 22.10.2026 (Screener.in) | E87: =IFERROR(INDEX(Gautam!$M$7:$M$300,MATCH($A87,Gautam!$B$7:$B$300,0)),"") | F87: =IFERROR(INDEX('Manish Shilpa'!$M$7:$M$300,MATCH($A87,'Manish Shilpa'!$B$7:$B$300,0)),"") -> 187.2 | G87: =IFERROR(INDEX('Saloni Mehra'!$M$7:$M$300,MATCH($A87,'Saloni Mehra'!$B$7:$B$300,0)),"") | H87: =IFERROR(INDEX('Vidushi Malhotra'!$M$7:$M$300,MATCH($A87,'Vidushi Malhotra'!$B$7:$B$300,0)),"") | I87: =IFERROR(INDEX('Dr Umesh Choudhry'!$M$7:$M$300,MATCH($A87,'Dr Umesh Choudhry'!$B$7:$B$300,0)),"") | J87: =IFERROR(INDEX(DA!$M$7:$M$300,MATCH($A87,DA!$B$7:$B$300,0)),"") | K87: Close 22.10.2026 (Screener.in) | L87: 199.32 | M87: =IF(AND(ISNUMBER(B87),ISNUMBER(L87),N(L87)>0),B87/L87-1,"") -> -0.020569938
A88: Vedant Fashions (Manyavar) Ltd | B88: 490.05 | C88: =IF(ISNUMBER(B88),B88,IF(ISNUMBER(E88),E88,IF(ISNUMBER(F88),F88,IF(ISNUMBER(G88),G88,IF(ISNUMBER(H88),H88,IF(ISNUMBER(I88),I88,IF(ISNUMBER(J88),J88,""))))))) -> 490.05 | D88: =IF(ISNUMBER(B88),IF(K88<>"",K88,"Manual override"),IF(ISNUMBER(E88),"Gautam stmt – 23.10",IF(ISNUMBER(F88),"Manish Shilpa stmt – live 23.10",IF(ISNUMBER(G88),"Saloni stmt – 20.10 (stale)",IF(ISNUMBER(H88),"Vidushi stmt – LTP 05.10",IF(ISNUMBER(I88),"Umesh stmt – NSE live 09.10",IF(ISNUMBER(J88),"DA stmt – older (stale)","No price on any statement"))))))) -> Close 22.10.2026 (Screener.in) | E88: =IFERROR(INDEX(Gautam!$M$7:$M$300,MATCH($A88,Gautam!$B$7:$B$300,0)),"") | F88: =IFERROR(INDEX('Manish Shilpa'!$M$7:$M$300,MATCH($A88,'Manish Shilpa'!$B$7:$B$300,0)),"") | G88: =IFERROR(INDEX('Saloni Mehra'!$M$7:$M$300,MATCH($A88,'Saloni Mehra'!$B$7:$B$300,0)),"") | H88: =IFERROR(INDEX('Vidushi Malhotra'!$M$7:$M$300,MATCH($A88,'Vidushi Malhotra'!$B$7:$B$300,0)),"") | I88: =IFERROR(INDEX('Dr Umesh Choudhry'!$M$7:$M$300,MATCH($A88,'Dr Umesh Choudhry'!$B$7:$B$300,0)),"") | J88: =IFERROR(INDEX(DA!$M$7:$M$300,MATCH($A88,DA!$B$7:$B$300,0)),"") -> 582 | K88: Close 22.10.2026 (Screener.in) | L88: 501.7 | M88: =IF(AND(ISNUMBER(B88),ISNUMBER(L88),N(L88)>0),B88/L88-1,"") -> -0.023221048
A89: Vedanta Power (VEDPOWER) | B89: 29.51 | C89: =IF(ISNUMBER(B89),B89,IF(ISNUMBER(E89),E89,IF(ISNUMBER(F89),F89,IF(ISNUMBER(G89),G89,IF(ISNUMBER(H89),H89,IF(ISNUMBER(I89),I89,IF(ISNUMBER(J89),J89,""))))))) -> 29.51 | D89: =IF(ISNUMBER(B89),IF(K89<>"",K89,"Manual override"),IF(ISNUMBER(E89),"Gautam stmt – 23.10",IF(ISNUMBER(F89),"Manish Shilpa stmt – live 23.10",IF(ISNUMBER(G89),"Saloni stmt – 20.10 (stale)",IF(ISNUMBER(H89),"Vidushi stmt – LTP 05.10",IF(ISNUMBER(I89),"Umesh stmt – NSE live 09.10",IF(ISNUMBER(J89),"DA stmt – older (stale)","No price on any statement"))))))) -> Close 22.10.2026 (Screener.in) | E89: =IFERROR(INDEX(Gautam!$M$7:$M$300,MATCH($A89,Gautam!$B$7:$B$300,0)),"") | F89: =IFERROR(INDEX('Manish Shilpa'!$M$7:$M$300,MATCH($A89,'Manish Shilpa'!$B$7:$B$300,0)),"") | G89: =IFERROR(INDEX('Saloni Mehra'!$M$7:$M$300,MATCH($A89,'Saloni Mehra'!$B$7:$B$300,0)),"") | H89: =IFERROR(INDEX('Vidushi Malhotra'!$M$7:$M$300,MATCH($A89,'Vidushi Malhotra'!$B$7:$B$300,0)),"") | I89: =IFERROR(INDEX('Dr Umesh Choudhry'!$M$7:$M$300,MATCH($A89,'Dr Umesh Choudhry'!$B$7:$B$300,0)),"") | J89: =IFERROR(INDEX(DA!$M$7:$M$300,MATCH($A89,DA!$B$7:$B$300,0)),"") -> 34 | K89: Close 22.10.2026 (Screener.in) | L89: 30.3 | M89: =IF(AND(ISNUMBER(B89),ISNUMBER(L89),N(L89)>0),B89/L89-1,"") -> -0.026072607
A90: Vinati Organics Ltd | B90: 1089.9 | C90: =IF(ISNUMBER(B90),B90,IF(ISNUMBER(E90),E90,IF(ISNUMBER(F90),F90,IF(ISNUMBER(G90),G90,IF(ISNUMBER(H90),H90,IF(ISNUMBER(I90),I90,IF(ISNUMBER(J90),J90,""))))))) -> 1089.9 | D90: =IF(ISNUMBER(B90),IF(K90<>"",K90,"Manual override"),IF(ISNUMBER(E90),"Gautam stmt – 23.10",IF(ISNUMBER(F90),"Manish Shilpa stmt – live 23.10",IF(ISNUMBER(G90),"Saloni stmt – 20.10 (stale)",IF(ISNUMBER(H90),"Vidushi stmt – LTP 05.10",IF(ISNUMBER(I90),"Umesh stmt – NSE live 09.10",IF(ISNUMBER(J90),"DA stmt – older (stale)","No price on any statement"))))))) -> Close 22.10.2026 (Screener.in) | E90: =IFERROR(INDEX(Gautam!$M$7:$M$300,MATCH($A90,Gautam!$B$7:$B$300,0)),"") -> 1097 | F90: =IFERROR(INDEX('Manish Shilpa'!$M$7:$M$300,MATCH($A90,'Manish Shilpa'!$B$7:$B$300,0)),"") -> 1067.1765 | G90: =IFERROR(INDEX('Saloni Mehra'!$M$7:$M$300,MATCH($A90,'Saloni Mehra'!$B$7:$B$300,0)),"") -> 1118.6042 | H90: =IFERROR(INDEX('Vidushi Malhotra'!$M$7:$M$300,MATCH($A90,'Vidushi Malhotra'!$B$7:$B$300,0)),"") | I90: =IFERROR(INDEX('Dr Umesh Choudhry'!$M$7:$M$300,MATCH($A90,'Dr Umesh Choudhry'!$B$7:$B$300,0)),"") -> 1127.8049 | J90: =IFERROR(INDEX(DA!$M$7:$M$300,MATCH($A90,DA!$B$7:$B$300,0)),"") | K90: Close 22.10.2026 (Screener.in) | L90: 1096.1 | M90: =IF(AND(ISNUMBER(B90),ISNUMBER(L90),N(L90)>0),B90/L90-1,"") -> -0.0056564182
A91: Vinyl Chemicals (India) Ltd | B91: 205.95 | C91: =IF(ISNUMBER(B91),B91,IF(ISNUMBER(E91),E91,IF(ISNUMBER(F91),F91,IF(ISNUMBER(G91),G91,IF(ISNUMBER(H91),H91,IF(ISNUMBER(I91),I91,IF(ISNUMBER(J91),J91,""))))))) -> 205.95 | D91: =IF(ISNUMBER(B91),IF(K91<>"",K91,"Manual override"),IF(ISNUMBER(E91),"Gautam stmt – 23.10",IF(ISNUMBER(F91),"Manish Shilpa stmt – live 23.10",IF(ISNUMBER(G91),"Saloni stmt – 20.10 (stale)",IF(ISNUMBER(H91),"Vidushi stmt – LTP 05.10",IF(ISNUMBER(I91),"Umesh stmt – NSE live 09.10",IF(ISNUMBER(J91),"DA stmt – older (stale)","No price on any statement"))))))) -> Close 22.10.2026 (Screener.in) | E91: =IFERROR(INDEX(Gautam!$M$7:$M$300,MATCH($A91,Gautam!$B$7:$B$300,0)),"") | F91: =IFERROR(INDEX('Manish Shilpa'!$M$7:$M$300,MATCH($A91,'Manish Shilpa'!$B$7:$B$300,0)),"") | G91: =IFERROR(INDEX('Saloni Mehra'!$M$7:$M$300,MATCH($A91,'Saloni Mehra'!$B$7:$B$300,0)),"") | H91: =IFERROR(INDEX('Vidushi Malhotra'!$M$7:$M$300,MATCH($A91,'Vidushi Malhotra'!$B$7:$B$300,0)),"") | I91: =IFERROR(INDEX('Dr Umesh Choudhry'!$M$7:$M$300,MATCH($A91,'Dr Umesh Choudhry'!$B$7:$B$300,0)),"") | J91: =IFERROR(INDEX(DA!$M$7:$M$300,MATCH($A91,DA!$B$7:$B$300,0)),"") -> 220 | K91: Close 22.10.2026 (Screener.in) | L91: 201.62 | M91: =IF(AND(ISNUMBER(B91),ISNUMBER(L91),N(L91)>0),B91/L91-1,"") -> 0.021476044
A92: VRL Logistics Ltd | B92: 266.55 | C92: =IF(ISNUMBER(B92),B92,IF(ISNUMBER(E92),E92,IF(ISNUMBER(F92),F92,IF(ISNUMBER(G92),G92,IF(ISNUMBER(H92),H92,IF(ISNUMBER(I92),I92,IF(ISNUMBER(J92),J92,""))))))) -> 266.55 | D92: =IF(ISNUMBER(B92),IF(K92<>"",K92,"Manual override"),IF(ISNUMBER(E92),"Gautam stmt – 23.10",IF(ISNUMBER(F92),"Manish Shilpa stmt – live 23.10",IF(ISNUMBER(G92),"Saloni stmt – 20.10 (stale)",IF(ISNUMBER(H92),"Vidushi stmt – LTP 05.10",IF(ISNUMBER(I92),"Umesh stmt – NSE live 09.10",IF(ISNUMBER(J92),"DA stmt – older (stale)","No price on any statement"))))))) -> Close 22.10.2026 (Screener.in) | E92: =IFERROR(INDEX(Gautam!$M$7:$M$300,MATCH($A92,Gautam!$B$7:$B$300,0)),"") | F92: =IFERROR(INDEX('Manish Shilpa'!$M$7:$M$300,MATCH($A92,'Manish Shilpa'!$B$7:$B$300,0)),"") -> 253.36 | G92: =IFERROR(INDEX('Saloni Mehra'!$M$7:$M$300,MATCH($A92,'Saloni Mehra'!$B$7:$B$300,0)),"") | H92: =IFERROR(INDEX('Vidushi Malhotra'!$M$7:$M$300,MATCH($A92,'Vidushi Malhotra'!$B$7:$B$300,0)),"") | I92: =IFERROR(INDEX('Dr Umesh Choudhry'!$M$7:$M$300,MATCH($A92,'Dr Umesh Choudhry'!$B$7:$B$300,0)),"") | J92: =IFERROR(INDEX(DA!$M$7:$M$300,MATCH($A92,DA!$B$7:$B$300,0)),"") | K92: Close 22.10.2026 (Screener.in) | L92: 284.85 | M92: =IF(AND(ISNUMBER(B92),ISNUMBER(L92),N(L92)>0),B92/L92-1,"") -> -0.064244339
A93: Waaree Energies Ltd | B93: 2370 | C93: =IF(ISNUMBER(B93),B93,IF(ISNUMBER(E93),E93,IF(ISNUMBER(F93),F93,IF(ISNUMBER(G93),G93,IF(ISNUMBER(H93),H93,IF(ISNUMBER(I93),I93,IF(ISNUMBER(J93),J93,""))))))) -> 2370 | D93: =IF(ISNUMBER(B93),IF(K93<>"",K93,"Manual override"),IF(ISNUMBER(E93),"Gautam stmt – 23.10",IF(ISNUMBER(F93),"Manish Shilpa stmt – live 23.10",IF(ISNUMBER(G93),"Saloni stmt – 20.10 (stale)",IF(ISNUMBER(H93),"Vidushi stmt – LTP 05.10",IF(ISNUMBER(I93),"Umesh stmt – NSE live 09.10",IF(ISNUMBER(J93),"DA stmt – older (stale)","No price on any statement"))))))) -> Close 22.10.2026 (Screener.in) | E93: =IFERROR(INDEX(Gautam!$M$7:$M$300,MATCH($A93,Gautam!$B$7:$B$300,0)),"") -> 2370 | F93: =IFERROR(INDEX('Manish Shilpa'!$M$7:$M$300,MATCH($A93,'Manish Shilpa'!$B$7:$B$300,0)),"") -> 2316.6667 | G93: =IFERROR(INDEX('Saloni Mehra'!$M$7:$M$300,MATCH($A93,'Saloni Mehra'!$B$7:$B$300,0)),"") -> 2515 | H93: =IFERROR(INDEX('Vidushi Malhotra'!$M$7:$M$300,MATCH($A93,'Vidushi Malhotra'!$B$7:$B$300,0)),"") | I93: =IFERROR(INDEX('Dr Umesh Choudhry'!$M$7:$M$300,MATCH($A93,'Dr Umesh Choudhry'!$B$7:$B$300,0)),"") | J93: =IFERROR(INDEX(DA!$M$7:$M$300,MATCH($A93,DA!$B$7:$B$300,0)),"") -> 2625 | K93: Close 22.10.2026 (Screener.in) | L93: 2455 | M93: =IF(AND(ISNUMBER(B93),ISNUMBER(L93),N(L93)>0),B93/L93-1,"") -> -0.034623218
A94: Waaree Renewable Technologies Ltd | B94: 718.95 | C94: =IF(ISNUMBER(B94),B94,IF(ISNUMBER(E94),E94,IF(ISNUMBER(F94),F94,IF(ISNUMBER(G94),G94,IF(ISNUMBER(H94),H94,IF(ISNUMBER(I94),I94,IF(ISNUMBER(J94),J94,""))))))) -> 718.95 | D94: =IF(ISNUMBER(B94),IF(K94<>"",K94,"Manual override"),IF(ISNUMBER(E94),"Gautam stmt – 23.10",IF(ISNUMBER(F94),"Manish Shilpa stmt – live 23.10",IF(ISNUMBER(G94),"Saloni stmt – 20.10 (stale)",IF(ISNUMBER(H94),"Vidushi stmt – LTP 05.10",IF(ISNUMBER(I94),"Umesh stmt – NSE live 09.10",IF(ISNUMBER(J94),"DA stmt – older (stale)","No price on any statement"))))))) -> Close 22.10.2026 (Screener.in) | E94: =IFERROR(INDEX(Gautam!$M$7:$M$300,MATCH($A94,Gautam!$B$7:$B$300,0)),"") | F94: =IFERROR(INDEX('Manish Shilpa'!$M$7:$M$300,MATCH($A94,'Manish Shilpa'!$B$7:$B$300,0)),"") -> 679.6 | G94: =IFERROR(INDEX('Saloni Mehra'!$M$7:$M$300,MATCH($A94,'Saloni Mehra'!$B$7:$B$300,0)),"") -> 826.33333 | H94: =IFERROR(INDEX('Vidushi Malhotra'!$M$7:$M$300,MATCH($A94,'Vidushi Malhotra'!$B$7:$B$300,0)),"") | I94: =IFERROR(INDEX('Dr Umesh Choudhry'!$M$7:$M$300,MATCH($A94,'Dr Umesh Choudhry'!$B$7:$B$300,0)),"") | J94: =IFERROR(INDEX(DA!$M$7:$M$300,MATCH($A94,DA!$B$7:$B$300,0)),"") | K94: Close 22.10.2026 (Screener.in) | L94: 743.25 | M94: =IF(AND(ISNUMBER(B94),ISNUMBER(L94),N(L94)>0),B94/L94-1,"") -> -0.032694248

Sheet Gautam
A1: GAUTAM – HDFC Securities
A2: Holdings as of 23.10.2026. Statement prices: HDFC statement prices 23.10.2026. Market value uses the common Ref Price from the Prices sheet so all portfolios are valued alike.
A3: Blue = figures from the statement (inputs). Black = formulas. Green = pulled from another sheet.
A5: # | B5: Company | C5: Broker | D5: No. of Shares | E5: Total Invested (₹) | F5: Wtd Avg Cost (₹) | G5: Ref Price (₹) | H5: Market Value (₹) | I5: Unrealised P&L (₹) | J5: P&L % | K5: Portfolio Weight % | L5: Statement Mkt Value (₹) | M5: Statement Price (₹) | N5: Repricing Diff vs Stmt (₹) | O5: Note | Q5: Changes between 05.10 and 23.10 statements (derived; buys at implied avg cost, sells at 05.10 statement price)
B6: TOTAL | E6: =SUM(E7:E37) -> 5501448 | H6: =SUM(H7:H37) -> 5225157.3 | I6: =H6-E6 -> -276290.7 | J6: =IF(E6>0,I6/E6,"") -> -0.050221451 | K6: =SUM(K7:K37) -> 1 | L6: =SUM(L7:L37) -> 5224564 | N6: =SUM(N7:N37) -> 593.3 | Q6: Date / Time | R6: Type | S6: Instrument | T6: Qty | U6: Fill Price (₹) | V6: Value (₹)
A7: 1 | B7: Bajaj Finance Ltd | C7: HDFC Securities | D7: 1901 | E7: 1912279 | F7: =IF(AND(D7>0,N(E7)>0),E7/D7,"") -> 1005.9332 | G7: =IFERROR(INDEX(Prices!$C$6:$C$300,MATCH(B7,Prices!$A$6:$A$300,0)),"") -> 942.1 | H7: =IF(ISNUMBER(G7),D7*G7,0) -> 1790932.1 | I7: =H7-N(E7) -> -121346.9 | J7: =IF(N(E7)>0,I7/E7,"") -> -0.063456692 | K7: =IF($H$6=0,"",H7/$H$6) -> 0.34275181 | L7: 1783138 | M7: =IF(ISNUMBER(L7),L7/D7,"") -> 938 | N7: =IF(ISNUMBER(L7),H7-L7,"") -> 7794.1 | Q7: 05.10–23.10.2026 | R7: BUY | S7: Affle 3i Ltd | T7: 8 | U7: 1364.62 | V7: 10917
A8: 2 | B8: Poonawalla Fincorp Ltd | C8: HDFC Securities | D8: 1132 | E8: 527172 | F8: =IF(AND(D8>0,N(E8)>0),E8/D8,"") -> 465.69965 | G8: =IFERROR(INDEX(Prices!$C$6:$C$300,MATCH(B8,Prices!$A$6:$A$300,0)),"") -> 432.45 | H8: =IF(ISNUMBER(G8),D8*G8,0) -> 489533.4 | I8: =H8-N(E8) -> -37638.6 | J8: =IF(N(E8)>0,I8/E8,"") -> -0.071397191 | K8: =IF($H$6=0,"",H8/$H$6) -> 0.093687782 | L8: 489024 | M8: =IF(ISNUMBER(L8),L8/D8,"") -> 432 | N8: =IF(ISNUMBER(L8),H8-L8,"") -> 509.4 | Q8: 05.10–23.10.2026 | R8: BUY | S8: Avenue Supermarts (DMart) Ltd | T8: 3 | U8: 3179 | V8: 9537
A9: 3 | B9: Nippon India ETF Nifty 1D Rate Liquid BeES | C9: HDFC Securities | D9: 325 | E9: 325000 | F9: =IF(AND(D9>0,N(E9)>0),E9/D9,"") -> 1000 | G9: =IFERROR(INDEX(Prices!$C$6:$C$300,MATCH(B9,Prices!$A$6:$A$300,0)),"") -> 1000 | H9: =IF(ISNUMBER(G9),D9*G9,0) -> 325000 | I9: =H9-N(E9) -> 0 | J9: =IF(N(E9)>0,I9/E9,"") -> 0 | K9: =IF($H$6=0,"",H9/$H$6) -> 0.062199084 | L9: 325000 | M9: =IF(ISNUMBER(L9),L9/D9,"") -> 1000 | N9: =IF(ISNUMBER(L9),H9-L9,"") -> 0 | Q9: 05.10–23.10.2026 | R9: BUY | S9: Bajaj Finance Ltd | T9: 237 | U9: 932.3 | V9: 220956
A10: 4 | B10: HDFC Bank Ltd | C10: HDFC Securities | D10: 447 | E10: 320122 | F10: =IF(AND(D10>0,N(E10)>0),E10/D10,"") -> 716.1566 | G10: =IFERROR(INDEX(Prices!$C$6:$C$300,MATCH(B10,Prices!$A$6:$A$300,0)),"") -> 694.05 | H10: =IF(ISNUMBER(G10),D10*G10,0) -> 310240.35 | I10: =H10-N(E10) -> -9881.65 | J10: =IF(N(E10)>0,I10/E10,"") -> -0.030868388 | K10: =IF($H$6=0,"",H10/$H$6) -> 0.059374356 | L10: 310218 | M10: =IF(ISNUMBER(L10),L10/D10,"") -> 694 | N10: =IF(ISNUMBER(L10),H10-L10,"") -> 22.35 | Q10: 05.10–23.10.2026 | R10: BUY | S10: Bajaj Housing Finance Ltd | T10: 274 | U10: 81.1 | V10: 22222
A11: 5 | B11: LTM Ltd (formerly LTIMindtree) | C11: HDFC Securities | D11: 60 | E11: 273840 | F11: =IF(AND(D11>0,N(E11)>0),E11/D11,"") -> 4564 | G11: =IFERROR(INDEX(Prices!$C$6:$C$300,MATCH(B11,Prices!$A$6:$A$300,0)),"") -> 4274 | H11: =IF(ISNUMBER(G11),D11*G11,0) -> 256440 | I11: =H11-N(E11) -> -17400 | J11: =IF(N(E11)>0,I11/E11,"") -> -0.063540754 | K11: =IF($H$6=0,"",H11/$H$6) -> 0.049077948 | L11: 256440 | M11: =IF(ISNUMBER(L11),L11/D11,"") -> 4274 | N11: =IF(ISNUMBER(L11),H11-L11,"") -> 0 | O11: Shown as LTM Limited | Q11: 05.10–23.10.2026 | R11: BUY | S11: Eicher Motors Ltd | T11: 3 | U11: 7055 | V11: 21165
A12: 6 | B12: Tata Consultancy Services Ltd | C12: HDFC Securities | D12: 92 | E12: 210588 | F12: =IF(AND(D12>0,N(E12)>0),E12/D12,"") -> 2289 | G12: =IFERROR(INDEX(Prices!$C$6:$C$300,MATCH(B12,Prices!$A$6:$A$300,0)),"") -> 2506.9 | H12: =IF(ISNUMBER(G12),D12*G12,0) -> 230634.8 | I12: =H12-N(E12) -> 20046.8 | J12: =IF(N(E12)>0,I12/E12,"") -> 0.095194408 | K12: =IF($H$6=0,"",H12/$H$6) -> 0.044139303 | L12: 230644 | M12: =IF(ISNUMBER(L12),L12/D12,"") -> 2507 | N12: =IF(ISNUMBER(L12),H12-L12,"") -> -9.2 | Q12: 05.10–23.10.2026 | R12: BUY | S12: Fineotex Chemical Ltd | T12: 138 | U12: 52.29 | V12: 7216
A13: 7 | B13: Titan Company Ltd | C13: HDFC Securities | D13: 47 | E13: 223898 | F13: =IF(AND(D13>0,N(E13)>0),E13/D13,"") -> 4763.7872 | G13: =IFERROR(INDEX(Prices!$C$6:$C$300,MATCH(B13,Prices!$A$6:$A$300,0)),"") -> 4350 | H13: =IF(ISNUMBER(G13),D13*G13,0) -> 204450 | I13: =H13-N(E13) -> -19448 | J13: =IF(N(E13)>0,I13/E13,"") -> -0.086860981 | K13: =IF($H$6=0,"",H13/$H$6) -> 0.039128009 | L13: 204450 | M13: =IF(ISNUMBER(L13),L13/D13,"") -> 4350 | N13: =IF(ISNUMBER(L13),H13-L13,"") -> 0 | Q13: 05.10–23.10.2026 | R13: BUY | S13: HDFC Bank Ltd | T13: 57 | U13: 693.96 | V13: 39556
A14: 8 | B14: Connplex Cinemas Ltd | C14: HDFC Securities | D14: 800 | E14: 211200 | F14: =IF(AND(D14>0,N(E14)>0),E14/D14,"") -> 264 | G14: =IFERROR(INDEX(Prices!$C$6:$C$300,MATCH(B14,Prices!$A$6:$A$300,0)),"") -> 234.25 | H14: =IF(ISNUMBER(G14),D14*G14,0) -> 187400 | I14: =H14-N(E14) -> -23800 | J14: =IF(N(E14)>0,I14/E14,"") -> -0.11268939 | K14: =IF($H$6=0,"",H14/$H$6) -> 0.035864949 | L14: 192000 | M14: =IF(ISNUMBER(L14),L14/D14,"") -> 240 | N14: =IF(ISNUMBER(L14),H14-L14,"") -> -4600 | Q14: 05.10–23.10.2026 | R14: SELL | S14: International Gemmological Institute (India) Ltd | T14: 80 | U14: 314 | V14: 25120
A15: 9 | B15: AFCOM Holdings Ltd | C15: HDFC Securities | D15: 120 | E15: 199920 | F15: =IF(AND(D15>0,N(E15)>0),E15/D15,"") -> 1666 | G15: =IFERROR(INDEX(Prices!$C$6:$C$300,MATCH(B15,Prices!$A$6:$A$300,0)),"") -> 1371.45 | H15: =IF(ISNUMBER(G15),D15*G15,0) -> 164574 | I15: =H15-N(E15) -> -35346 | J15: =IF(N(E15)>0,I15/E15,"") -> -0.17680072 | K15: =IF($H$6=0,"",H15/$H$6) -> 0.031496468 | L15: 165240 | M15: =IF(ISNUMBER(L15),L15/D15,"") -> 1377 | N15: =IF(ISNUMBER(L15),H15-L15,"") -> -666 | O15: Shown as AFCOM | Q15: 05.10–23.10.2026 | R15: BUY | S15: L&T Technology Services Ltd | T15: 5 | U15: 3954 | V15: 19770
A16: 10 | B16: Tata Elxsi Ltd | C16: HDFC Securities | D16: 41 | E16: 140474 | F16: =IF(AND(D16>0,N(E16)>0),E16/D16,"") -> 3426.1951 | G16: =IFERROR(INDEX(Prices!$C$6:$C$300,MATCH(B16,Prices!$A$6:$A$300,0)),"") -> 3846.8 | H16: =IF(ISNUMBER(G16),D16*G16,0) -> 157718.8 | I16: =H16-N(E16) -> 17244.8 | J16: =IF(N(E16)>0,I16/E16,"") -> 0.12276151 | K16: =IF($H$6=0,"",H16/$H$6) -> 0.030184508 | L16: 157727 | M16: =IF(ISNUMBER(L16),L16/D16,"") -> 3847 | N16: =IF(ISNUMBER(L16),H16-L16,"") -> -8.2 | Q16: 05.10–23.10.2026 | R16: BUY | S16: Nippon India ETF Nifty 1D Rate Liquid BeES | T16: 25 | U16: 1000 | V16: 25000
A17: 11 | B17: Eicher Motors Ltd | C17: HDFC Securities | D17: 20 | E17: 147414 | F17: =IF(AND(D17>0,N(E17)>0),E17/D17,"") -> 7370.7 | G17: =IFERROR(INDEX(Prices!$C$6:$C$300,MATCH(B17,Prices!$A$6:$A$300,0)),"") -> 7084.5 | H17: =IF(ISNUMBER(G17),D17*G17,0) -> 141690 | I17: =H17-N(E17) -> -5724 | J17: =IF(N(E17)>0,I17/E17,"") -> -0.038829419 | K17: =IF($H$6=0,"",H17/$H$6) -> 0.027116887 | L17: 141680 | M17: =IF(ISNUMBER(L17),L17/D17,"") -> 7084 | N17: =IF(ISNUMBER(L17),H17-L17,"") -> 10 | Q17: 05.10–23.10.2026 | R17: BUY | S17: Persistent Systems Ltd | T17: 3 | U17: 5806 | V17: 17418
A18: 12 | B18: Bajaj Housing Finance Ltd | C18: HDFC Securities | D18: 1600 | E18: 132930 | F18: =IF(AND(D18>0,N(E18)>0),E18/D18,"") -> 83.08125 | G18: =IFERROR(INDEX(Prices!$C$6:$C$300,MATCH(B18,Prices!$A$6:$A$300,0)),"") -> 81.02 | H18: =IF(ISNUMBER(G18),D18*G18,0) -> 129632 | I18: =H18-N(E18) -> -3298 | J18: =IF(N(E18)>0,I18/E18,"") -> -0.02481005 | K18: =IF($H$6=0,"",H18/$H$6) -> 0.024809205 | L18: 129920 | M18: =IF(ISNUMBER(L18),L18/D18,"") -> 81.2 | N18: =IF(ISNUMBER(L18),H18-L18,"") -> -288 | Q18: 05.10–23.10.2026 | R18: BUY | S18: Poonawalla Fincorp Ltd | T18: 131 | U18: 432.84 | V18: 56702
A19: 13 | B19: L&T Technology Services Ltd | C19: HDFC Securities | D19: 30 | E19: 104531 | F19: =IF(AND(D19>0,N(E19)>0),E19/D19,"") -> 3484.3667 | G19: =IFERROR(INDEX(Prices!$C$6:$C$300,MATCH(B19,Prices!$A$6:$A$300,0)),"") -> 3954.8 | H19: =IF(ISNUMBER(G19),D19*G19,0) -> 118644 | I19: =H19-N(E19) -> 14113 | J19: =IF(N(E19)>0,I19/E19,"") -> 0.13501258 | K19: =IF($H$6=0,"",H19/$H$6) -> 0.022706302 | L19: 119880 | M19: =IF(ISNUMBER(L19),L19/D19,"") -> 3996 | N19: =IF(ISNUMBER(L19),H19-L19,"") -> -1236 | Q19: 05.10–23.10.2026 | R19: BUY | S19: Rategain Travel Technologies Ltd | T19: 9 | U19: 789.22 | V19: 7103
A20: 14 | B20: Persistent Systems Ltd | C20: HDFC Securities | D20: 19 | E20: 105436 | F20: =IF(AND(D20>0,N(E20)>0),E20/D20,"") -> 5549.2632 | G20: =IFERROR(INDEX(Prices!$C$6:$C$300,MATCH(B20,Prices!$A$6:$A$300,0)),"") -> 5740.5 | H20: =IF(ISNUMBER(G20),D20*G20,0) -> 109069.5 | I20: =H20-N(E20) -> 3633.5 | J20: =IF(N(E20)>0,I20/E20,"") -> 0.034461664 | K20: =IF($H$6=0,"",H20/$H$6) -> 0.020873917 | L20: 109060 | M20: =IF(ISNUMBER(L20),L20/D20,"") -> 5740 | N20: =IF(ISNUMBER(L20),H20-L20,"") -> 9.5 | Q20: 05.10–23.10.2026 | R20: BUY | S20: Tata Elxsi Ltd | T20: 7 | U20: 3852.57 | V20: 26968
A21: 15 | B21: InterGlobe Aviation Ltd (IndiGo) | C21: HDFC Securities | D21: 20 | E21: 103860 | F21: =IF(AND(D21>0,N(E21)>0),E21/D21,"") -> 5193 | G21: =IFERROR(INDEX(Prices!$C$6:$C$300,MATCH(B21,Prices!$A$6:$A$300,0)),"") -> 4600 | H21: =IF(ISNUMBER(G21),D21*G21,0) -> 92000 | I21: =H21-N(E21) -> -11860 | J21: =IF(N(E21)>0,I21/E21,"") -> -0.11419218 | K21: =IF($H$6=0,"",H21/$H$6) -> 0.017607125 | L21: 92160 | M21: =IF(ISNUMBER(L21),L21/D21,"") -> 4608 | N21: =IF(ISNUMBER(L21),H21-L21,"") -> -160 | O21: Shown as InterGlobe Aviation Ltd (Indigo) | Q21: 05.10–23.10.2026 | R21: BUY | S21: Titan Company Ltd | T21: 6 | U21: 4349 | V21: 26094
A22: 16 | B22: Affle 3i Ltd | C22: HDFC Securities | D22: 66 | E22: 106115 | F22: =IF(AND(D22>0,N(E22)>0),E22/D22,"") -> 1607.803 | G22: =IFERROR(INDEX(Prices!$C$6:$C$300,MATCH(B22,Prices!$A$6:$A$300,0)),"") -> 1362.8 | H22: =IF(ISNUMBER(G22),D22*G22,0) -> 89944.8 | I22: =H22-N(E22) -> -16170.2 | J22: =IF(N(E22)>0,I22/E22,"") -> -0.15238373 | K22: =IF($H$6=0,"",H22/$H$6) -> 0.017213798 | L22: 89958 | M22: =IF(ISNUMBER(L22),L22/D22,"") -> 1363 | N22: =IF(ISNUMBER(L22),H22-L22,"") -> -13.2 | Q22: 05.10–23.10.2026 | R22: BUY | S22: Trent Ltd | T22: 3 | U22: 2787.33 | V22: 8362
A23: 17 | B23: Trent Ltd | C23: HDFC Securities | D23: 31 | E23: 86006 | F23: =IF(AND(D23>0,N(E23)>0),E23/D23,"") -> 2774.3871 | G23: =IFERROR(INDEX(Prices!$C$6:$C$300,MATCH(B23,Prices!$A$6:$A$300,0)),"") -> 2775.8 | H23: =IF(ISNUMBER(G23),D23*G23,0) -> 86049.8 | I23: =H23-N(E23) -> 43.8 | J23: =IF(N(E23)>0,I23/E23,"") -> 0.0005092668 | K23: =IF($H$6=0,"",H23/$H$6) -> 0.016468365 | L23: 86056 | M23: =IF(ISNUMBER(L23),L23/D23,"") -> 2776 | N23: =IF(ISNUMBER(L23),H23-L23,"") -> -6.2 | Q23: 05.10–23.10.2026 | R23: BUY | S23: Waaree Energies Ltd | T23: 3 | U23: 2367.33 | V23: 7102
A24: 18 | B24: Avenue Supermarts (DMart) Ltd | C24: HDFC Securities | D24: 24 | E24: 89946 | F24: =IF(AND(D24>0,N(E24)>0),E24/D24,"") -> 3747.75 | G24: =IFERROR(INDEX(Prices!$C$6:$C$300,MATCH(B24,Prices!$A$6:$A$300,0)),"") -> 3166 | H24: =IF(ISNUMBER(G24),D24*G24,0) -> 75984 | I24: =H24-N(E24) -> -13962 | J24: =IF(N(E24)>0,I24/E24,"") -> -0.15522647 | K24: =IF($H$6=0,"",H24/$H$6) -> 0.014541955 | L24: 75984 | M24: =IF(ISNUMBER(L24),L24/D24,"") -> 3166 | N24: =IF(ISNUMBER(L24),H24-L24,"") -> 0 | S24: Net bought (buys − sells) | V24: =SUMIFS(V7:V23,R7:R23,"BUY")-SUMIFS(V7:V23,R7:R23,"SELL") -> 500968
A25: 19 | B25: Waaree Energies Ltd | C25: HDFC Securities | D25: 27 | E25: 68363 | F25: =IF(AND(D25>0,N(E25)>0),E25/D25,"") -> 2531.963 | G25: =IFERROR(INDEX(Prices!$C$6:$C$300,MATCH(B25,Prices!$A$6:$A$300,0)),"") -> 2370 | H25: =IF(ISNUMBER(G25),D25*G25,0) -> 63990 | I25: =H25-N(E25) -> -4373 | J25: =IF(N(E25)>0,I25/E25,"") -> -0.063967351 | K25: =IF($H$6=0,"",H25/$H$6) -> 0.012246521 | L25: 63990 | M25: =IF(ISNUMBER(L25),L25/D25,"") -> 2370 | N25: =IF(ISNUMBER(L25),H25-L25,"") -> 0
A26: 20 | B26: Rategain Travel Technologies Ltd | C26: HDFC Securities | D26: 72 | E26: 59636 | F26: =IF(AND(D26>0,N(E26)>0),E26/D26,"") -> 828.27778 | G26: =IFERROR(INDEX(Prices!$C$6:$C$300,MATCH(B26,Prices!$A$6:$A$300,0)),"") -> 788.1 | H26: =IF(ISNUMBER(G26),D26*G26,0) -> 56743.2 | I26: =H26-N(E26) -> -2892.8 | J26: =IF(N(E26)>0,I26/E26,"") -> -0.048507613 | K26: =IF($H$6=0,"",H26/$H$6) -> 0.010859616 | L26: 56808 | M26: =IF(ISNUMBER(L26),L26/D26,"") -> 789 | N26: =IF(ISNUMBER(L26),H26-L26,"") -> -64.8
A27: 21 | B27: Fineotex Chemical Ltd | C27: HDFC Securities | D27: 830 | E27: 46702 | F27: =IF(AND(D27>0,N(E27)>0),E27/D27,"") -> 56.26747 | G27: =IFERROR(INDEX(Prices!$C$6:$C$300,MATCH(B27,Prices!$A$6:$A$300,0)),"") -> 51.55 | H27: =IF(ISNUMBER(G27),D27*G27,0) -> 42786.5 | I27: =H27-N(E27) -> -3915.5 | J27: =IF(N(E27)>0,I27/E27,"") -> -0.083840093 | K27: =IF($H$6=0,"",H27/$H$6) -> 0.0081885573 | L27: 43575 | M27: =IF(ISNUMBER(L27),L27/D27,"") -> 52.5 | N27: =IF(ISNUMBER(L27),H27-L27,"") -> -788.5
A28: 22 | B28: Nestle India Ltd | C28: HDFC Securities | D28: 22 | E28: 27683 | F28: =IF(AND(D28>0,N(E28)>0),E28/D28,"") -> 1258.3182 | G28: =IFERROR(INDEX(Prices!$C$6:$C$300,MATCH(B28,Prices!$A$6:$A$300,0)),"") -> 1189.9 | H28: =IF(ISNUMBER(G28),D28*G28,0) -> 26177.8 | I28: =H28-N(E28) -> -1505.2 | J28: =IF(N(E28)>0,I28/E28,"") -> -0.05437272 | K28: =IF($H$6=0,"",H28/$H$6) -> 0.0050099544 | L28: 26180 | M28: =IF(ISNUMBER(L28),L28/D28,"") -> 1190 | N28: =IF(ISNUMBER(L28),H28-L28,"") -> -2.2
A29: 23 | B29: Shriram Properties Ltd | C29: HDFC Securities | D29: 250 | E29: 19250 | F29: =IF(AND(D29>0,N(E29)>0),E29/D29,"") -> 77 | G29: =IFERROR(INDEX(Prices!$C$6:$C$300,MATCH(B29,Prices!$A$6:$A$300,0)),"") -> 65.13 | H29: =IF(ISNUMBER(G29),D29*G29,0) -> 16282.5 | I29: =H29-N(E29) -> -2967.5 | J29: =IF(N(E29)>0,I29/E29,"") -> -0.15415584 | K29: =IF($H$6=0,"",H29/$H$6) -> 0.0031161741 | L29: 16925 | M29: =IF(ISNUMBER(L29),L29/D29,"") -> 67.7 | N29: =IF(ISNUMBER(L29),H29-L29,"") -> -642.5
A30: 24 | B30: Bagmane Prime Office REIT | C30: HDFC Securities | D30: 150 | E30: 16050 | F30: =IF(AND(D30>0,N(E30)>0),E30/D30,"") -> 107 | G30: =IFERROR(INDEX(Prices!$C$6:$C$300,MATCH(B30,Prices!$A$6:$A$300,0)),"") -> 105.54 | H30: =IF(ISNUMBER(G30),D30*G30,0) -> 15831 | I30: =H30-N(E30) -> -219 | J30: =IF(N(E30)>0,I30/E30,"") -> -0.01364486 | K30: =IF($H$6=0,"",H30/$H$6) -> 0.0030297652 | L30: 15900 | M30: =IF(ISNUMBER(L30),L30/D30,"") -> 106 | N30: =IF(ISNUMBER(L30),H30-L30,"") -> -69
A31: 25 | B31: Nippon India ETF Gold BeES | C31: HDFC Securities | D31: 121 | E31: 13310 | F31: =IF(AND(D31>0,N(E31)>0),E31/D31,"") -> 110 | G31: =IFERROR(INDEX(Prices!$C$6:$C$300,MATCH(B31,Prices!$A$6:$A$300,0)),"") -> 123 | H31: =IF(ISNUMBER(G31),D31*G31,0) -> 14883 | I31: =H31-N(E31) -> 1573 | J31: =IF(N(E31)>0,I31/E31,"") -> 0.11818182 | K31: =IF($H$6=0,"",H31/$H$6) -> 0.0028483353 | L31: 14883 | M31: =IF(ISNUMBER(L31),L31/D31,"") -> 123 | N31: =IF(ISNUMBER(L31),H31-L31,"") -> 0
A32: 26 | B32: Vinati Organics Ltd | C32: HDFC Securities | D32: 10 | E32: 11941 | F32: =IF(AND(D32>0,N(E32)>0),E32/D32,"") -> 1194.1 | G32: =IFERROR(INDEX(Prices!$C$6:$C$300,MATCH(B32,Prices!$A$6:$A$300,0)),"") -> 1089.9 | H32: =IF(ISNUMBER(G32),D32*G32,0) -> 10899 | I32: =H32-N(E32) -> -1042 | J32: =IF(N(E32)>0,I32/E32,"") -> -0.087262373 | K32: =IF($H$6=0,"",H32/$H$6) -> 0.0020858702 | L32: 10970 | M32: =IF(ISNUMBER(L32),L32/D32,"") -> 1097 | N32: =IF(ISNUMBER(L32),H32-L32,"") -> -71
A33: 27 | B33: Bharti Airtel Ltd | C33: HDFC Securities | D33: 5 | E33: 9610 | F33: =IF(AND(D33>0,N(E33)>0),E33/D33,"") -> 1922 | G33: =IFERROR(INDEX(Prices!$C$6:$C$300,MATCH(B33,Prices!$A$6:$A$300,0)),"") -> 1895 | H33: =IF(ISNUMBER(G33),D33*G33,0) -> 9475 | I33: =H33-N(E33) -> -135 | J33: =IF(N(E33)>0,I33/E33,"") -> -0.014047867 | K33: =IF($H$6=0,"",H33/$H$6) -> 0.0018133425 | L33: 9475 | M33: =IF(ISNUMBER(L33),L33/D33,"") -> 1895 | N33: =IF(ISNUMBER(L33),H33-L33,"") -> 0
A34: 28 | B34: Orient Electric Ltd | C34: HDFC Securities | D34: 25 | E34: 4500 | F34: =IF(AND(D34>0,N(E34)>0),E34/D34,"") -> 180 | G34: =IFERROR(INDEX(Prices!$C$6:$C$300,MATCH(B34,Prices!$A$6:$A$300,0)),"") -> 188.91 | H34: =IF(ISNUMBER(G34),D34*G34,0) -> 4722.75 | I34: =H34-N(E34) -> 222.75 | J34: =IF(N(E34)>0,I34/E34,"") -> 0.0495 | K34: =IF($H$6=0,"",H34/$H$6) -> 0.00090384839 | L34: 3850 | M34: =IF(ISNUMBER(L34),L34/D34,"") -> 154 | N34: =IF(ISNUMBER(L34),H34-L34,"") -> 872.75
A35: 29 | B35: HDFC Gold ETF | C35: HDFC Securities | D35: 27 | E35: 3672 | F35: =IF(AND(D35>0,N(E35)>0),E35/D35,"") -> 136 | G35: =IFERROR(INDEX(Prices!$C$6:$C$300,MATCH(B35,Prices!$A$6:$A$300,0)),"") -> 127 | H35: =IF(ISNUMBER(G35),D35*G35,0) -> 3429 | I35: =H35-N(E35) -> -243 | J35: =IF(N(E35)>0,I35/E35,"") -> -0.066176471 | K35: =IF($H$6=0,"",H35/$H$6) -> 0.00065624819 | L35: 3429 | M35: =IF(ISNUMBER(L35),L35/D35,"") -> 127 | N35: =IF(ISNUMBER(L35),H35-L35,"") -> 0
A36: 30 | B36: NEPC Agro Foods Ltd | C36: HDFC Securities | D36: 144 | F36: =IF(AND(D36>0,N(E36)>0),E36/D36,"") | G36: =IFERROR(INDEX(Prices!$C$6:$C$300,MATCH(B36,Prices!$A$6:$A$300,0)),"") | H36: =IF(ISNUMBER(G36),D36*G36,0) -> 0 | I36: =H36-N(E36) -> 0 | J36: =IF(N(E36)>0,I36/E36,"") | K36: =IF($H$6=0,"",H36/$H$6) -> 0 | M36: =IF(ISNUMBER(L36),L36/D36,"") | N36: =IF(ISNUMBER(L36),H36-L36,"") | O36: No cost or price on statement (marked *) – carried at nil
A37: 31 | B37: PSL Ltd (formerly PSL Holdings Ltd) | C37: HDFC Securities | D37: 1000 | F37: =IF(AND(D37>0,N(E37)>0),E37/D37,"") | G37: =IFERROR(INDEX(Prices!$C$6:$C$300,MATCH(B37,Prices!$A$6:$A$300,0)),"") | H37: =IF(ISNUMBER(G37),D37*G37,0) -> 0 | I37: =H37-N(E37) -> 0 | J37: =IF(N(E37)>0,I37/E37,"") | K37: =IF($H$6=0,"",H37/$H$6) -> 0 | M37: =IF(ISNUMBER(L37),L37/D37,"") | N37: =IF(ISNUMBER(L37),H37-L37,"") | O37: No cost or price on statement (marked *) – carried at nil

Sheet Manish Shilpa
A1: MANISH SHILPA – Axis Direct + HDFC Securities
A2: Holdings as of 23.10.2026 (live, ~11:23 IST). Statement prices: Live LTP 23.10.2026 ~11:23 IST (equity); MF NAV per Axis statement 23.10.2026 (three demats + MF merged). Market value uses the common Ref Price from the Prices sheet so all portfolios are valued alike.
A3: Blue = figures from the statement (inputs). Black = formulas. Green = pulled from another sheet.
A5: # | B5: Company | C5: Broker | D5: No. of Shares | E5: Total Invested (₹) | F5: Wtd Avg Cost (₹) | G5: Ref Price (₹) | H5: Market Value (₹) | I5: Unrealised P&L (₹) | J5: P&L % | K5: Portfolio Weight % | L5: Statement Mkt Value (₹) | M5: Statement Price (₹) | N5: Repricing Diff vs Stmt (₹) | O5: Note
B6: TOTAL | E6: =SUM(E7:E53) -> 9857778 | H6: =SUM(H7:H53) -> 11825895 | I6: =H6-E6 -> 1968116.9 | J6: =IF(E6>0,I6/E6,"") -> 0.19965117 | K6: =SUM(K7:K53) -> 1 | L6: =SUM(L7:L53) -> 11636414 | N6: =SUM(N7:N53) -> 189480.74
A7: 1 | B7: Bajaj Finance Ltd | C7: Axis Direct (Shilpa) + Axis Direct (Manish) + HDFC Securities (Manish) | D7: 3895 | E7: 2912389 | F7: =IF(AND(D7>0,N(E7)>0),E7/D7,"") -> 747.72503 | G7: =IFERROR(INDEX(Prices!$C$6:$C$300,MATCH(B7,Prices!$A$6:$A$300,0)),"") -> 942.1 | H7: =IF(ISNUMBER(G7),D7*G7,0) -> 3669479.5 | I7: =H7-N(E7) -> 757090.5 | J7: =IF(N(E7)>0,I7/E7,"") -> 0.25995514 | K7: =IF($H$6=0,"",H7/$H$6) -> 0.31029191 | L7: 3625900 | M7: =IF(ISNUMBER(L7),L7/D7,"") -> 930.91142 | N7: =IF(ISNUMBER(L7),H7-L7,"") -> 43579.5 | O7: Axis Direct Shilpa 226; Axis Direct Manish 3165; HDFC Securities Manish 504
A8: 2 | B8: Nippon India ETF Nifty 50 BeES | C8: Axis Direct (Shilpa) + Axis Direct (Manish) + HDFC Securities (Manish) | D8: 11160 | E8: 1687580 | F8: =IF(AND(D8>0,N(E8)>0),E8/D8,"") -> 151.21685 | G8: =IFERROR(INDEX(Prices!$C$6:$C$300,MATCH(B8,Prices!$A$6:$A$300,0)),"") -> 256.69292 | H8: =IF(ISNUMBER(G8),D8*G8,0) -> 2864693 | I8: =H8-N(E8) -> 1177113 | J8: =IF(N(E8)>0,I8/E8,"") -> 0.69751538 | K8: =IF($H$6=0,"",H8/$H$6) -> 0.242239 | L8: 2864693 | M8: =IF(ISNUMBER(L8),L8/D8,"") -> 256.69292 | N8: =IF(ISNUMBER(L8),H8-L8,"") -> 0 | O8: Axis Direct Shilpa 10; Axis Direct Manish 11049; HDFC Securities Manish 101
A9: 3 | B9: Titan Company Ltd | C9: Axis Direct (Shilpa) + Axis Direct (Manish) + HDFC Securities (Manish) | D9: 165 | E9: 564530 | F9: =IF(AND(D9>0,N(E9)>0),E9/D9,"") -> 3421.3939 | G9: =IFERROR(INDEX(Prices!$C$6:$C$300,MATCH(B9,Prices!$A$6:$A$300,0)),"") -> 4350 | H9: =IF(ISNUMBER(G9),D9*G9,0) -> 717750 | I9: =H9-N(E9) -> 153220 | J9: =IF(N(E9)>0,I9/E9,"") -> 0.27141162 | K9: =IF($H$6=0,"",H9/$H$6) -> 0.060693081 | L9: 700725 | M9: =IF(ISNUMBER(L9),L9/D9,"") -> 4246.8182 | N9: =IF(ISNUMBER(L9),H9-L9,"") -> 17025 | O9: Axis Direct Shilpa 7; Axis Direct Manish 153; HDFC Securities Manish 5
A10: 4 | B10: HDFC Bank Ltd | C10: Axis Direct (Shilpa) + Axis Direct (Manish) + HDFC Securities (Manish) | D10: 1013 | E10: 812683 | F10: =IF(AND(D10>0,N(E10)>0),E10/D10,"") -> 802.2537 | G10: =IFERROR(INDEX(Prices!$C$6:$C$300,MATCH(B10,Prices!$A$6:$A$300,0)),"") -> 694.05 | H10: =IF(ISNUMBER(G10),D10*G10,0) -> 703072.65 | I10: =H10-N(E10) -> -109610.35 | J10: =IF(N(E10)>0,I10/E10,"") -> -0.13487467 | K10: =IF($H$6=0,"",H10/$H$6) -> 0.059451962 | L10: 697943 | M10: =IF(ISNUMBER(L10),L10/D10,"") -> 688.98618 | N10: =IF(ISNUMBER(L10),H10-L10,"") -> 5129.65 | O10: Axis Direct Shilpa 58; Axis Direct Manish 899; HDFC Securities Manish 56
A11: 5 | B11: Poonawalla Fincorp Ltd | C11: Axis Direct (Shilpa) + Axis Direct (Manish) + HDFC Securities (Manish) | D11: 1394 | E11: 622513 | F11: =IF(AND(D11>0,N(E11)>0),E11/D11,"") -> 446.566 | G11: =IFERROR(INDEX(Prices!$C$6:$C$300,MATCH(B11,Prices!$A$6:$A$300,0)),"") -> 432.45 | H11: =IF(ISNUMBER(G11),D11*G11,0) -> 602835.3 | I11: =H11-N(E11) -> -19677.7 | J11: =IF(N(E11)>0,I11/E11,"") -> -0.031610103 | K11: =IF($H$6=0,"",H11/$H$6) -> 0.050975872 | L11: 578058 | M11: =IF(ISNUMBER(L11),L11/D11,"") -> 414.67575 | N11: =IF(ISNUMBER(L11),H11-L11,"") -> 24777.3 | O11: Axis Direct Shilpa 206; Axis Direct Manish 1180; HDFC Securities Manish 8
A12: 6 | B12: AFCOM Holdings Ltd | C12: Axis Direct (Manish) | D12: 360 | E12: 362724 | F12: =IF(AND(D12>0,N(E12)>0),E12/D12,"") -> 1007.5667 | G12: =IFERROR(INDEX(Prices!$C$6:$C$300,MATCH(B12,Prices!$A$6:$A$300,0)),"") -> 1371.45 | H12: =IF(ISNUMBER(G12),D12*G12,0) -> 493722 | I12: =H12-N(E12) -> 130998 | J12: =IF(N(E12)>0,I12/E12,"") -> 0.36115063 | K12: =IF($H$6=0,"",H12/$H$6) -> 0.041749229 | L12: 457200 | M12: =IF(ISNUMBER(L12),L12/D12,"") -> 1270 | N12: =IF(ISNUMBER(L12),H12-L12,"") -> 36522
A13: 7 | B13: UTI Nifty 50 Index Fund - Growth | C13: Axis Direct (Manish) MF | D13: 2004.589 | E13: 199990 | F13: =IF(AND(D13>0,N(E13)>0),E13/D13,"") -> 99.766087 | G13: =IFERROR(INDEX(Prices!$C$6:$C$300,MATCH(B13,Prices!$A$6:$A$300,0)),"") -> 157.3291 | H13: =IF(ISNUMBER(G13),D13*G13,0) -> 315380.18 | I13: =H13-N(E13) -> 115390.18 | J13: =IF(N(E13)>0,I13/E13,"") -> 0.57697975 | K13: =IF($H$6=0,"",H13/$H$6) -> 0.02666861 | L13: 315380.18 | M13: =IF(ISNUMBER(L13),L13/D13,"") -> 157.3291 | N13: =IF(ISNUMBER(L13),H13-L13,"") -> 0 | O13: Mutual fund, 2 folios (1,804.130 + 200.459 units); NAV ₹157.3291 per Axis statement 23.10.2026 – no exchange close, statement NAV used
A14: 8 | B14: Bajaj Housing Finance Ltd | C14: Axis Direct (Shilpa) + Axis Direct (Manish) + HDFC Securities (Manish) | D14: 3762 | E14: 432693 | F14: =IF(AND(D14>0,N(E14)>0),E14/D14,"") -> 115.01675 | G14: =IFERROR(INDEX(Prices!$C$6:$C$300,MATCH(B14,Prices!$A$6:$A$300,0)),"") -> 81.02 | H14: =IF(ISNUMBER(G14),D14*G14,0) -> 304797.24 | I14: =H14-N(E14) -> -127895.76 | J14: =IF(N(E14)>0,I14/E14,"") -> -0.29558084 | K14: =IF($H$6=0,"",H14/$H$6) -> 0.025773715 | L14: 292084 | M14: =IF(ISNUMBER(L14),L14/D14,"") -> 77.640617 | N14: =IF(ISNUMBER(L14),H14-L14,"") -> 12713.24 | O14: Axis Direct Shilpa 267; Axis Direct Manish 3396; HDFC Securities Manish 99
A15: 9 | B15: L&T Technology Services Ltd | C15: Axis Direct (Shilpa) + Axis Direct (Manish) + HDFC Securities (Manish) | D15: 72 | E15: 303467 | F15: =IF(AND(D15>0,N(E15)>0),E15/D15,"") -> 4214.8194 | G15: =IFERROR(INDEX(Prices!$C$6:$C$300,MATCH(B15,Prices!$A$6:$A$300,0)),"") -> 3954.8 | H15: =IF(ISNUMBER(G15),D15*G15,0) -> 284745.6 | I15: =H15-N(E15) -> -18721.4 | J15: =IF(N(E15)>0,I15/E15,"") -> -0.061691716 | K15: =IF($H$6=0,"",H15/$H$6) -> 0.024078144 | L15: 282588 | M15: =IF(ISNUMBER(L15),L15/D15,"") -> 3924.8333 | N15: =IF(ISNUMBER(L15),H15-L15,"") -> 2157.6 | O15: Axis Direct Shilpa 2; Axis Direct Manish 64; HDFC Securities Manish 6
A16: 10 | B16: LTM Ltd (formerly LTIMindtree) | C16: Axis Direct (Shilpa) + Axis Direct (Manish) + HDFC Securities (Manish) | D16: 66 | E16: 348137 | F16: =IF(AND(D16>0,N(E16)>0),E16/D16,"") -> 5274.803 | G16: =IFERROR(INDEX(Prices!$C$6:$C$300,MATCH(B16,Prices!$A$6:$A$300,0)),"") -> 4274 | H16: =IF(ISNUMBER(G16),D16*G16,0) -> 282084 | I16: =H16-N(E16) -> -66053 | J16: =IF(N(E16)>0,I16/E16,"") -> -0.18973278 | K16: =IF($H$6=0,"",H16/$H$6) -> 0.023853079 | L16: 276816 | M16: =IF(ISNUMBER(L16),L16/D16,"") -> 4194.1818 | N16: =IF(ISNUMBER(L16),H16-L16,"") -> 5268 | O16: Axis Direct Shilpa 2; Axis Direct Manish 52; HDFC Securities Manish 12
A17: 11 | B17: Connplex Cinemas Ltd | C17: Axis Direct (Manish) | D17: 800 | E17: 188075 | F17: =IF(AND(D17>0,N(E17)>0),E17/D17,"") -> 235.09375 | G17: =IFERROR(INDEX(Prices!$C$6:$C$300,MATCH(B17,Prices!$A$6:$A$300,0)),"") -> 234.25 | H17: =IF(ISNUMBER(G17),D17*G17,0) -> 187400 | I17: =H17-N(E17) -> -675 | J17: =IF(N(E17)>0,I17/E17,"") -> -0.0035889938 | K17: =IF($H$6=0,"",H17/$H$6) -> 0.015846581 | L17: 175200 | M17: =IF(ISNUMBER(L17),L17/D17,"") -> 219 | N17: =IF(ISNUMBER(L17),H17-L17,"") -> 12200
A18: 12 | B18: Fineotex Chemical Ltd | C18: Axis Direct (Manish) | D18: 3500 | E18: 117474 | F18: =IF(AND(D18>0,N(E18)>0),E18/D18,"") -> 33.564 | G18: =IFERROR(INDEX(Prices!$C$6:$C$300,MATCH(B18,Prices!$A$6:$A$300,0)),"") -> 51.55 | H18: =IF(ISNUMBER(G18),D18*G18,0) -> 180425 | I18: =H18-N(E18) -> 62951 | J18: =IF(N(E18)>0,I18/E18,"") -> 0.53587177 | K18: =IF($H$6=0,"",H18/$H$6) -> 0.015256773 | L18: 167755 | M18: =IF(ISNUMBER(L18),L18/D18,"") -> 47.93 | N18: =IF(ISNUMBER(L18),H18-L18,"") -> 12670
A19: 13 | B19: Central Depository Services (India) Ltd | C19: Axis Direct (Manish) | D19: 134 | E19: 51658 | F19: =IF(AND(D19>0,N(E19)>0),E19/D19,"") -> 385.50746 | G19: =IFERROR(INDEX(Prices!$C$6:$C$300,MATCH(B19,Prices!$A$6:$A$300,0)),"") -> 1225 | H19: =IF(ISNUMBER(G19),D19*G19,0) -> 164150 | I19: =H19-N(E19) -> 112492 | J19: =IF(N(E19)>0,I19/E19,"") -> 2.1776298 | K19: =IF($H$6=0,"",H19/$H$6) -> 0.013880556 | L19: 158643 | M19: =IF(ISNUMBER(L19),L19/D19,"") -> 1183.903 | N19: =IF(ISNUMBER(L19),H19-L19,"") -> 5507
A20: 14 | B20: Tata Elxsi Ltd | C20: Axis Direct (Shilpa) + Axis Direct (Manish) | D20: 32 | E20: 212270 | F20: =IF(AND(D20>0,N(E20)>0),E20/D20,"") -> 6633.4375 | G20: =IFERROR(INDEX(Prices!$C$6:$C$300,MATCH(B20,Prices!$A$6:$A$300,0)),"") -> 3846.8 | H20: =IF(ISNUMBER(G20),D20*G20,0) -> 123097.6 | I20: =H20-N(E20) -> -89172.4 | J20: =IF(N(E20)>0,I20/E20,"") -> -0.42008951 | K20: =IF($H$6=0,"",H20/$H$6) -> 0.010409157 | L20: 120470 | M20: =IF(ISNUMBER(L20),L20/D20,"") -> 3764.6875 | N20: =IF(ISNUMBER(L20),H20-L20,"") -> 2627.6 | O20: Axis Direct Shilpa 1; Axis Direct Manish 31
A21: 15 | B21: Dr Lal PathLabs Ltd | C21: HDFC Securities (Manish) | D21: 44 | E21: 52231 | F21: =IF(AND(D21>0,N(E21)>0),E21/D21,"") -> 1187.0682 | G21: =IFERROR(INDEX(Prices!$C$6:$C$300,MATCH(B21,Prices!$A$6:$A$300,0)),"") -> 1843.7 | H21: =IF(ISNUMBER(G21),D21*G21,0) -> 81122.8 | I21: =H21-N(E21) -> 28891.8 | J21: =IF(N(E21)>0,I21/E21,"") -> 0.55315426 | K21: =IF($H$6=0,"",H21/$H$6) -> 0.0068597599 | L21: 80313 | M21: =IF(ISNUMBER(L21),L21/D21,"") -> 1825.2955 | N21: =IF(ISNUMBER(L21),H21-L21,"") -> 809.8
A22: 16 | B22: Abbott India Ltd | C22: Axis Direct (Manish) | D22: 3 | E22: 54700 | F22: =IF(AND(D22>0,N(E22)>0),E22/D22,"") -> 18233.333 | G22: =IFERROR(INDEX(Prices!$C$6:$C$300,MATCH(B22,Prices!$A$6:$A$300,0)),"") -> 25360 | H22: =IF(ISNUMBER(G22),D22*G22,0) -> 76080 | I22: =H22-N(E22) -> 21380 | J22: =IF(N(E22)>0,I22/E22,"") -> 0.39085923 | K22: =IF($H$6=0,"",H22/$H$6) -> 0.0064333398 | L22: 74400 | M22: =IF(ISNUMBER(L22),L22/D22,"") -> 24800 | N22: =IF(ISNUMBER(L22),H22-L22,"") -> 1680
A23: 17 | B23: Infosys Ltd | C23: Axis Direct (Manish) | D23: 64 | E23: 102862 | F23: =IF(AND(D23>0,N(E23)>0),E23/D23,"") -> 1607.2188 | G23: =IFERROR(INDEX(Prices!$C$6:$C$300,MATCH(B23,Prices!$A$6:$A$300,0)),"") -> 1153.35 | H23: =IF(ISNUMBER(G23),D23*G23,0) -> 73814.4 | I23: =H23-N(E23) -> -29047.6 | J23: =IF(N(E23)>0,I23/E23,"") -> -0.28239389 | K23: =IF($H$6=0,"",H23/$H$6) -> 0.0062417602 | L23: 74240 | M23: =IF(ISNUMBER(L23),L23/D23,"") -> 1160 | N23: =IF(ISNUMBER(L23),H23-L23,"") -> -425.6
A24: 18 | B24: Tata Consultancy Services Ltd | C24: Axis Direct (Manish) | D24: 29 | E24: 97994 | F24: =IF(AND(D24>0,N(E24)>0),E24/D24,"") -> 3379.1034 | G24: =IFERROR(INDEX(Prices!$C$6:$C$300,MATCH(B24,Prices!$A$6:$A$300,0)),"") -> 2506.9 | H24: =IF(ISNUMBER(G24),D24*G24,0) -> 72700.1 | I24: =H24-N(E24) -> -25293.9 | J24: =IF(N(E24)>0,I24/E24,"") -> -0.25811682 | K24: =IF($H$6=0,"",H24/$H$6) -> 0.0061475348 | L24: 74127 | M24: =IF(ISNUMBER(L24),L24/D24,"") -> 2556.1034 | N24: =IF(ISNUMBER(L24),H24-L24,"") -> -1426.9
A25: 19 | B25: Kotak Mahindra Bank Ltd | C25: Axis Direct (Shilpa) + HDFC Securities (Manish) | D25: 160 | E25: 63501 | F25: =IF(AND(D25>0,N(E25)>0),E25/D25,"") -> 396.88125 | G25: =IFERROR(INDEX(Prices!$C$6:$C$300,MATCH(B25,Prices!$A$6:$A$300,0)),"") -> 437 | H25: =IF(ISNUMBER(G25),D25*G25,0) -> 69920 | I25: =H25-N(E25) -> 6419 | J25: =IF(N(E25)>0,I25/E25,"") -> 0.10108502 | K25: =IF($H$6=0,"",H25/$H$6) -> 0.0059124489 | L25: 69298 | M25: =IF(ISNUMBER(L25),L25/D25,"") -> 433.1125 | N25: =IF(ISNUMBER(L25),H25-L25,"") -> 622 | O25: Axis Direct Shilpa 30; HDFC Securities Manish 130
A26: 20 | B26: Page Industries Ltd | C26: HDFC Securities (Manish) | D26: 2 | E26: 93537 | F26: =IF(AND(D26>0,N(E26)>0),E26/D26,"") -> 46768.5 | G26: =IFERROR(INDEX(Prices!$C$6:$C$300,MATCH(B26,Prices!$A$6:$A$300,0)),"") -> 34425 | H26: =IF(ISNUMBER(G26),D26*G26,0) -> 68850 | I26: =H26-N(E26) -> -24687 | J26: =IF(N(E26)>0,I26/E26,"") -> -0.26392764 | K26: =IF($H$6=0,"",H26/$H$6) -> 0.0058219695 | L26: 67650 | M26: =IF(ISNUMBER(L26),L26/D26,"") -> 33825 | N26: =IF(ISNUMBER(L26),H26-L26,"") -> 1200
A27: 21 | B27: Affle 3i Ltd | C27: Axis Direct (Shilpa) + Axis Direct (Manish) + HDFC Securities (Manish) | D27: 47 | E27: 76969 | F27: =IF(AND(D27>0,N(E27)>0),E27/D27,"") -> 1637.6383 | G27: =IFERROR(INDEX(Prices!$C$6:$C$300,MATCH(B27,Prices!$A$6:$A$300,0)),"") -> 1362.8 | H27: =IF(ISNUMBER(G27),D27*G27,0) -> 64051.6 | I27: =H27-N(E27) -> -12917.4 | J27: =IF(N(E27)>0,I27/E27,"") -> -0.16782601 | K27: =IF($H$6=0,"",H27/$H$6) -> 0.0054162159 | L27: 62254 | M27: =IF(ISNUMBER(L27),L27/D27,"") -> 1324.5532 | N27: =IF(ISNUMBER(L27),H27-L27,"") -> 1797.6 | O27: Axis Direct Shilpa 18; Axis Direct Manish 25; HDFC Securities Manish 4
A28: 22 | B28: Persistent Systems Ltd | C28: Axis Direct (Shilpa) + Axis Direct (Manish) | D28: 11 | E28: 49823 | F28: =IF(AND(D28>0,N(E28)>0),E28/D28,"") -> 4529.3636 | G28: =IFERROR(INDEX(Prices!$C$6:$C$300,MATCH(B28,Prices!$A$6:$A$300,0)),"") -> 5740.5 | H28: =IF(ISNUMBER(G28),D28*G28,0) -> 63145.5 | I28: =H28-N(E28) -> 13322.5 | J28: =IF(N(E28)>0,I28/E28,"") -> 0.26739658 | K28: =IF($H$6=0,"",H28/$H$6) -> 0.0053395959 | L28: 63648 | M28: =IF(ISNUMBER(L28),L28/D28,"") -> 5786.1818 | N28: =IF(ISNUMBER(L28),H28-L28,"") -> -502.5 | O28: Axis Direct Shilpa 3; Axis Direct Manish 8
A29: 23 | B29: Asian Paints Ltd | C29: Axis Direct (Manish) | D29: 22 | E29: 78545 | F29: =IF(AND(D29>0,N(E29)>0),E29/D29,"") -> 3570.2273 | G29: =IFERROR(INDEX(Prices!$C$6:$C$300,MATCH(B29,Prices!$A$6:$A$300,0)),"") -> 2284.8 | H29: =IF(ISNUMBER(G29),D29*G29,0) -> 50265.6 | I29: =H29-N(E29) -> -28279.4 | J29: =IF(N(E29)>0,I29/E29,"") -> -0.36004074 | K29: =IF($H$6=0,"",H29/$H$6) -> 0.004250469 | L29: 50046 | M29: =IF(ISNUMBER(L29),L29/D29,"") -> 2274.8182 | N29: =IF(ISNUMBER(L29),H29-L29,"") -> 219.6
A30: 24 | B30: Eicher Motors Ltd | C30: Axis Direct (Shilpa) + Axis Direct (Manish) | D30: 6 | E30: 43747 | F30: =IF(AND(D30>0,N(E30)>0),E30/D30,"") -> 7291.1667 | G30: =IFERROR(INDEX(Prices!$C$6:$C$300,MATCH(B30,Prices!$A$6:$A$300,0)),"") -> 7084.5 | H30: =IF(ISNUMBER(G30),D30*G30,0) -> 42507 | I30: =H30-N(E30) -> -1240 | J30: =IF(N(E30)>0,I30/E30,"") -> -0.028344801 | K30: =IF($H$6=0,"",H30/$H$6) -> 0.0035944003 | L30: 41760 | M30: =IF(ISNUMBER(L30),L30/D30,"") -> 6960 | N30: =IF(ISNUMBER(L30),H30-L30,"") -> 747 | O30: Axis Direct Shilpa 1; Axis Direct Manish 5
A31: 25 | B31: Reliance Industries Ltd | C31: Axis Direct (Manish) | D31: 32 | E31: 38635 | F31: =IF(AND(D31>0,N(E31)>0),E31/D31,"") -> 1207.3438 | G31: =IFERROR(INDEX(Prices!$C$6:$C$300,MATCH(B31,Prices!$A$6:$A$300,0)),"") -> 1184.5 | H31: =IF(ISNUMBER(G31),D31*G31,0) -> 37904 | I31: =H31-N(E31) -> -731 | J31: =IF(N(E31)>0,I31/E31,"") -> -0.018920668 | K31: =IF($H$6=0,"",H31/$H$6) -> 0.0032051697 | L31: 37526 | M31: =IF(ISNUMBER(L31),L31/D31,"") -> 1172.6875 | N31: =IF(ISNUMBER(L31),H31-L31,"") -> 378
A32: 26 | B32: Nippon India ETF Infra BeES | C32: Axis Direct (Manish) | D32: 34 | E32: 14923 | F32: =IF(AND(D32>0,N(E32)>0),E32/D32,"") -> 438.91176 | G32: =IFERROR(INDEX(Prices!$C$6:$C$300,MATCH(B32,Prices!$A$6:$A$300,0)),"") -> 877.02941 | H32: =IF(ISNUMBER(G32),D32*G32,0) -> 29819 | I32: =H32-N(E32) -> 14896 | J32: =IF(N(E32)>0,I32/E32,"") -> 0.99819071 | K32: =IF($H$6=0,"",H32/$H$6) -> 0.0025215005 | L32: 29819 | M32: =IF(ISNUMBER(L32),L32/D32,"") -> 877.02941 | N32: =IF(ISNUMBER(L32),H32-L32,"") -> 0
A33: 27 | B33: Trent Ltd | C33: Axis Direct (Shilpa) + Axis Direct (Manish) | D33: 10 | E33: 30536 | F33: =IF(AND(D33>0,N(E33)>0),E33/D33,"") -> 3053.6 | G33: =IFERROR(INDEX(Prices!$C$6:$C$300,MATCH(B33,Prices!$A$6:$A$300,0)),"") -> 2775.8 | H33: =IF(ISNUMBER(G33),D33*G33,0) -> 27758 | I33: =H33-N(E33) -> -2778 | J33: =IF(N(E33)>0,I33/E33,"") -> -0.090974587 | K33: =IF($H$6=0,"",H33/$H$6) -> 0.0023472219 | L33: 27130 | M33: =IF(ISNUMBER(L33),L33/D33,"") -> 2713 | N33: =IF(ISNUMBER(L33),H33-L33,"") -> 628 | O33: Axis Direct Shilpa 3; Axis Direct Manish 7
A34: 28 | B34: HDFC Gold ETF | C34: Axis Direct (Shilpa) + Axis Direct (Manish) | D34: 168 | E34: 15354 | F34: =IF(AND(D34>0,N(E34)>0),E34/D34,"") -> 91.392857 | G34: =IFERROR(INDEX(Prices!$C$6:$C$300,MATCH(B34,Prices!$A$6:$A$300,0)),"") -> 127 | H34: =IF(ISNUMBER(G34),D34*G34,0) -> 21336 | I34: =H34-N(E34) -> 5982 | J34: =IF(N(E34)>0,I34/E34,"") -> 0.38960531 | K34: =IF($H$6=0,"",H34/$H$6) -> 0.0018041764 | L34: 20131 | M34: =IF(ISNUMBER(L34),L34/D34,"") -> 119.82738 | N34: =IF(ISNUMBER(L34),H34-L34,"") -> 1205 | O34: Axis Direct Shilpa 93; Axis Direct Manish 75
A35: 29 | B35: Tanla Platforms Ltd | C35: Axis Direct (Manish) | D35: 33 | E35: 40602 | F35: =IF(AND(D35>0,N(E35)>0),E35/D35,"") -> 1230.3636 | G35: =IFERROR(INDEX(Prices!$C$6:$C$300,MATCH(B35,Prices!$A$6:$A$300,0)),"") -> 581.3 | H35: =IF(ISNUMBER(G35),D35*G35,0) -> 19182.9 | I35: =H35-N(E35) -> -21419.1 | J35: =IF(N(E35)>0,I35/E35,"") -> -0.52753805 | K35: =IF($H$6=0,"",H35/$H$6) -> 0.0016221098 | L35: 18610 | M35: =IF(ISNUMBER(L35),L35/D35,"") -> 563.93939 | N35: =IF(ISNUMBER(L35),H35-L35,"") -> 572.9
A36: 30 | B36: Avenue Supermarts (DMart) Ltd | C36: Axis Direct (Shilpa) + Axis Direct (Manish) | D36: 6 | E36: 23637 | F36: =IF(AND(D36>0,N(E36)>0),E36/D36,"") -> 3939.5 | G36: =IFERROR(INDEX(Prices!$C$6:$C$300,MATCH(B36,Prices!$A$6:$A$300,0)),"") -> 3166 | H36: =IF(ISNUMBER(G36),D36*G36,0) -> 18996 | I36: =H36-N(E36) -> -4641 | J36: =IF(N(E36)>0,I36/E36,"") -> -0.19634471 | K36: =IF($H$6=0,"",H36/$H$6) -> 0.0016063055 | L36: 18758 | M36: =IF(ISNUMBER(L36),L36/D36,"") -> 3126.3333 | N36: =IF(ISNUMBER(L36),H36-L36,"") -> 238 | O36: Axis Direct Shilpa 2; Axis Direct Manish 4
A37: 31 | B37: Vinati Organics Ltd | C37: Axis Direct (Shilpa) + Axis Direct (Manish) + HDFC Securities (Manish) | D37: 17 | E37: 29694 | F37: =IF(AND(D37>0,N(E37)>0),E37/D37,"") -> 1746.7059 | G37: =IFERROR(INDEX(Prices!$C$6:$C$300,MATCH(B37,Prices!$A$6:$A$300,0)),"") -> 1089.9 | H37: =IF(ISNUMBER(G37),D37*G37,0) -> 18528.3 | I37: =H37-N(E37) -> -11165.7 | J37: =IF(N(E37)>0,I37/E37,"") -> -0.37602546 | K37: =IF($H$6=0,"",H37/$H$6) -> 0.0015667567 | L37: 18142 | M37: =IF(ISNUMBER(L37),L37/D37,"") -> 1067.1765 | N37: =IF(ISNUMBER(L37),H37-L37,"") -> 386.3 | O37: Axis Direct Shilpa 1; Axis Direct Manish 15; HDFC Securities Manish 1
